Workbook

Sheet Main
A1: General info | B1: General info | C1: General info | D1: General info | E1: General info | F1: General info | G1: General info | H1: General info | I1: General info | J1: General info | K1: General info | L1: General info | M1: General info | N1: General info | O1: General info | P1: General info | Q1: General info | R1: General info | S1: General info | T1: General info | U1: From report | V1: From report | W1: From report | X1: From report | Y1: From report | Z1: From report | AA1: From report | AB1: From report | AC1: From report | AD1: From report | AE1: From report | AF1: From report | AG1: From report | AH1: From report | AI1: From report | AJ1: From report | AK1: From report | AL1: From report | AM1: From report | AN1: From report | AO1: From report | AP1: From report | AQ1: From report | AR1: From report | AS1: From report | AT1: From report | AU1: From report | AV1: From report | AW1: From report | AX1: From report | AY1: From report | AZ1: From report | BA1: From report | BB1: From report | BC1: From report | BD1: Tracker info | BE1: Tracker info | BF1: Tracker info | BG1: Tracker info | BH1: Tracker info | BI1: Tracker info | BJ1: Tracker info | BK1: Additional info | BL1: Additional info | BM1: Additional info | BN1: Additional info | BO1: Additional info | BQ1: Additional info | BS1: Additional info | BW1: Additional info | BY1: Additional info | BZ1: Additional info | CA1: Additional info | CB1: Additional info | CF1: Additional info
K2: derived fromCC | L2: derived fromCC | M2: derived fromCC | N2: derived fromCC | O2: derived fromCC | P2: derived fromCC | Q2: derived fromCC | R2: derived fromCC | S2: derived fromCC | BO2: Equipment Usage Status | BQ2: Loading capacity / Грузоподьемность | BS2: Generator specifications | BW2: Compressor specifications | CB2: Target utlization
A3: Equipment | B3: Operation Status | C3: License | D3: Description | E3: Service Zone | F3: Class | G3: Location | H3: Serial Number | I3: VIN/Chassis No | J3: CC code | K3: CC status | L3: Division code | M3: CC name | N3: Division name | O3: Group code | P3: Group name | Q3: Department code | R3: Department name from WP | S3: Department name | T3: User Department (from Report) | U3: Title | V3: Fleet | W3: Allocation | X3: Writeoff Status | Y3: Fleet Active Date | Z3: Criticality | AA3: Manufacturer | AB3: Model | AC3: Currency | AD3: Capital Cost | AE3: Year | AF3: Age of Fleet (Yrs) | AG3: Body No | AH3: Engine No | AI3: Date of Registr. In GAI | AJ3: Technical Passport No | AK3: Date Acquired by user | AL3: Life Cycle 2 (years) | AM3: Commission Date | AN3: Withdrawal date | AO3: Total Counter Reading | AP3: Last Reading | AQ3: Last Reading Motor Hour | AR3: FrontTireSize | AS3: RearTireSize | AT3: FleetCode | AU3: PO | AV3: Replace in Year | AW3: TCO Requested Replace in Year | AX3: Replaced by | AY3: TCO Charge | AZ3: ID | BA3: Eng Model | BB3: Transmission model | BC3: NOTES | BD3: Tracker existence | BE3: WIALON Qty | BF3: WIALON "group" | BG3: IVMS Qty | BH3: IVMS "Registration number" | BI3: Vega Qty | BJ3: Vega "deviceId" | BK3: Assigned location | BL3: HDV/HDE classification | BM3: Expected metrics from trackers | BN3: Category | BO3: Equipment Usage Status | BP3: Justification if "Assigned" | BQ3: Weight-based, kg | BR3: Volume-based, m³ | BS3: System Voltage, V | BT3: Battery Capacity, Ah | BU3: Current, A | BV3: Alternator Output, kvA | BW3: Pneumatic Pressure, ft³ (CFM) | BX3: Work output, m³/h | BY3: Maintenance BP | BZ3: Contact number | CA3: Contact e-mail | CB3: if required | CC3: km/day | CD3: mh/day | CE3: comments | CF3: General comments | CG3: Assignee
A4: 108019 | B4: Active | C4: H725152 | D4: TRUCK HD RAILROAD INTERNATIONAL 7400 SBA | E4: TMF1 | F4: HDV Heavy Duty Vehicle | G4: Tengiz | H4: 1HTWEAAN9BJ374649 | I4: 1HTWEAAN9BJ374649 | J4: 20053 | K4: =IFERROR(VLOOKUP(J4,'CC directory'!A:B,2,),"") -> ACTIVE | L4: =IFERROR(VLOOKUP(J4,'CC directory'!A:D,4,),"") -> 200 | M4: =VLOOKUP(J4,'CC directory'!A:I,9,) -> RailRoad Maintenance | N4: =IFERROR(VLOOKUP(J4,'CC directory'!A:C,3,),"") -> Operations | O4: =IFERROR(VLOOKUP(J4,'CC directory'!A:F,6,),"") -> 207 | P4: =IFERROR(VLOOKUP(J4,'CC directory'!A:E,5,),"") -> Production Operations | Q4: =IFERROR(VLOOKUP(J4,'CC directory'!A:H,8,),"") -> 708 | R4: =IFERROR(VLOOKUP(J4,'CC directory'!A:G,7,),"") -> FIELD & EXPORT | S4: FIELD & EXPORT | T4: Rail Road Maintenance | U4: 518 | V4: Tengiz fleet | Z4: Critical | AA4: INTERNATIONAL | AB4: 7400 SBA 4X4 | AC4: USD | AD4: 282616.82 | AE4: 2010 | AF4: 12 | AH4: 2N8006413 | AJ4: ED00011925 | AK4: 40739 | AL4: 15 | AM4: 40758 | AO4: 162086 | AP4: 162086 | AR4: 295/75R22.5 | AS4: 445/50R22.5 | AT4: TRKINTHR 001 | AU4: 142005 | AV4: 2023 | AW4: 2026 | AY4: YES | AZ4: 519 | BA4: IN-LINE 6 | BB4: FR-9210B 10-SPD | BD4: =IF((BE4+BG4+BI4)>0, "YES", "NO") -> YES | BE4: 1 | BF4: INTERNATIONAL H725152 (ТШО 108019) | BG4: 1 | BH4: H 725152 | BI4: 0 | BK4: IB | BL4: Self-propelled motorized (HDV/HDE) - Wheeled | BM4: =VLOOKUP(BL4,'directory all'!C:D,2,) -> Mileage, engine hours, GPS | BN4: Recovery/service truck | BO4: Assigned | BQ4: N/A | BR4: N/A | BS4: N/A | BT4: N/A | BU4: N/A | BV4: N/A | BW4: N/A | BX4: N/A | BY4: TCO SCM Logistics | BZ4: 200-4683 | CA4: RRMLC@tengizchevroil.com | CB4: YES | CC4: 42.294 | CD4: 7.236 | CG4: Maintenance RailRoad
A5: 108020 | B5: Active | C5: H725510 | D5: TRUCK HD RECOVERY KENWORTH T800 | E5: TMF1 | F5: HDV Heavy Duty Vehicle | G5: Tengiz | H5: 1NKDL40X0CR302786 | I5: 1NKDL40X0CR302786 | J5: 13780 | K5: =IFERROR(VLOOKUP(J5,'CC directory'!A:B,2,),"") -> ACTIVE | L5: =IFERROR(VLOOKUP(J5,'CC directory'!A:D,4,),"") -> 200 | M5: =VLOOKUP(J5,'CC directory'!A:I,9,) -> Heavy Equipment Operations | N5: =IFERROR(VLOOKUP(J5,'CC directory'!A:C,3,),"") -> Operations | O5: =IFERROR(VLOOKUP(J5,'CC directory'!A:F,6,),"") -> 209 | P5: =IFERROR(VLOOKUP(J5,'CC directory'!A:E,5,),"") -> Supply Chain Management | Q5: =IFERROR(VLOOKUP(J5,'CC directory'!A:H,8,),"") -> 322 | R5: =IFERROR(VLOOKUP(J5,'CC directory'!A:G,7,),"") -> Tengiz Ground Transportation | S5: SCM Logistics | T5: Heavy Equipment Operations | U5: 519 | V5: Tengiz fleet | Z5: Critical | AA5: KENWORTH | AB5: T800 | AC5: USD | AD5: 281700 | AE5: 2011 | AF5: 12 | AH5: 79465100 | AJ5: ED00012108 | AK5: 40775 | AL5: 15 | AM5: 40779 | AO5: 119321 | AP5: 62200 | AR5: 445 / 65 R 22.5 | AS5: 11R24.5 | AT5: TRKKEN 003 | AU5: 150933 | AV5: 2021 | AW5: 2026 | AZ5: 520 | BA5: IN-LINE 6 | BB5: FRO15210C | BD5: =IF((BE5+BG5+BI5)>0, "YES", "NO") -> YES | BE5: 1 | BF5: KENWORTH H 725510 (ТШО 108020) | BG5: 1 | BH5: H 725510 | BI5: 0 | BK5: Industrial Base | BL5: Self-propelled motorized (HDV/HDE) - Wheeled | BM5: =VLOOKUP(BL5,'directory all'!C:D,2,) -> Mileage, engine hours, GPS | BN5: Recovery/service truck | BO5: Shared without conditions | BQ5: 10600 | BR5: N/A | BS5: N/A | BT5: N/A | BU5: N/A | BV5: N/A | BW5: N/A | BX5: N/A | BY5: TCO SCM Logistics | BZ5: 4559 | CB5: YES | CC5: 40 | CD5: 1.5 | CE5: Emergency | CG5: SCM Logistics: Yerbol Nauryzbay / Yerlan Yeshmagambetov
A6: 108022 | B6: Active | C6: H089106 | D6: TRUCK HD RECOVERY KENWORTH T800 | E6: TMF1 | F6: HDV Heavy Duty Vehicle | G6: Tengiz | H6: 1NKDH08X2ER412644 | I6: 1NKDH08X2ER412644 | J6: 13780 | K6: =IFERROR(VLOOKUP(J6,'CC directory'!A:B,2,),"") -> ACTIVE | L6: =IFERROR(VLOOKUP(J6,'CC directory'!A:D,4,),"") -> 200 | M6: =VLOOKUP(J6,'CC directory'!A:I,9,) -> Heavy Equipment Operations | N6: =IFERROR(VLOOKUP(J6,'CC directory'!A:C,3,),"") -> Operations | O6: =IFERROR(VLOOKUP(J6,'CC directory'!A:F,6,),"") -> 209 | P6: =IFERROR(VLOOKUP(J6,'CC directory'!A:E,5,),"") -> Supply Chain Management | Q6: =IFERROR(VLOOKUP(J6,'CC directory'!A:H,8,),"") -> 322 | R6: =IFERROR(VLOOKUP(J6,'CC directory'!A:G,7,),"") -> Tengiz Ground Transportation | S6: SCM Logistics | T6: Heavy Equipment Operations | U6: 520 | V6: Tengiz fleet | Z6: Non-Critical | AA6: KENWORTH | AB6: T800 | AC6: USD | AD6: 175180 | AE6: 2013 | AF6: 9 | AH6: 35320148 | AJ6: ED00014225 | AK6: 41829 | AL6: 15 | AM6: 41830 | AO6: 207348 | AP6: 207348 | AR6: 11R22.5 | AS6: 11R22.5 | AT6: TRKKEN 007 | AU6: 192678 | AV6: 2024 | AW6: 2029 | AZ6: 521 | BA6: IN-LINE 6 | BD6: =IF((BE6+BG6+BI6)>0, "YES", "NO") -> YES | BE6: 1 | BF6: KENWORTH H 089106 (ТШО 108022) | BG6: 1 | BH6: H 089106 | BI6: 0 | BK6: Industrial Base | BL6: Self-propelled motorized (HDV/HDE) - Wheeled | BM6: =VLOOKUP(BL6,'directory all'!C:D,2,) -> Mileage, engine hours, GPS | BN6: Recovery/service truck | BO6: Shared without conditions | BQ6: 10600 | BR6: N/A | BS6: N/A | BT6: N/A | BU6: N/A | BV6: N/A | BW6: N/A | BX6: N/A | BY6: TCO SCM Logistics | BZ6: 4559 | CB6: YES | CC6: 40 | CD6: 1.5 | CG6: SCM Logistics: Yerbol Nauryzbay / Yerlan Yeshmagambetov
A7: 110008 | B7: Active | C7: 861EAB | D7: TRACTOR WHEELED JCB FASTRAC 2155 | E7: TMF1 | F7: HDV Heavy Duty Vehicle | G7: Tengiz | H7: JCB26H60700742575 | I7: JCB26H60700742575 | J7: 20850 | K7: =IFERROR(VLOOKUP(J7,'CC directory'!A:B,2,),"") -> ACTIVE | L7: =IFERROR(VLOOKUP(J7,'CC directory'!A:D,4,),"") -> 200 | M7: =VLOOKUP(J7,'CC directory'!A:I,9,) -> Maintenance Shared Services | N7: =IFERROR(VLOOKUP(J7,'CC directory'!A:C,3,),"") -> Operations | O7: =IFERROR(VLOOKUP(J7,'CC directory'!A:F,6,),"") -> 207 | P7: =IFERROR(VLOOKUP(J7,'CC directory'!A:E,5,),"") -> Production Operations | Q7: =IFERROR(VLOOKUP(J7,'CC directory'!A:H,8,),"") -> 705 | R7: =IFERROR(VLOOKUP(J7,'CC directory'!A:G,7,),"") -> Maintenance | S7: Maintenance | T7: Maintenance Shared Services | U7: 521 | V7: Tengiz fleet | Z7: Non-Critical | AA7: JCB | AB7: FASTRAC 2155 | AC7: USD | AD7: 118500 | AE7: 2010 | AF7: 13 | AH7: 21946004 | AJ7: 93012 | AK7: 40360 | AL7: 20 | AM7: 40367 | AO7: 25850 | AP7: 25850 | AQ7: 25765.00 mh#1 | AR7: 480/70 R-30 TM- | AS7: 480/70 R30 TM-7 | AT7: CONTW 005 | AU7: 141408 | AV7: 2020 | AW7: 2030 | AY7: YES | AZ7: 522 | BA7: 6 (V) | BD7: =IF((BE7+BG7+BI7)>0, "YES", "NO") -> YES | BE7: 1 | BF7: JCB FASTRAC 861EAB (ТШО 110008) | BG7: 0 | BI7: 0 | BK7: TFM/АРП | BL7: Self-propelled motorized (HDV/HDE) - Wheeled | BM7: =VLOOKUP(BL7,'directory all'!C:D,2,) -> Mileage, engine hours, GPS | BN7: Road construction and cleaning equipment | BO7: Shared with conditions | BQ7: N/A | BR7: N/A | BS7: N/A | BT7: N/A | BU7: N/A | BV7: N/A | BW7: N/A | BX7: N/A | BY7: TCO SCM Logistics | BZ7: 200-4410 | CA7: msslte@tengizchevroil.com | CB7: YES | CC7: 18.279 | CD7: 7.236 | CG7: Maintenance: Assylbek Amangaliyev / Yerkin Dauletov
A8: 110009 | B8: Active | C8: 087EAD | D8: TRACTOR WHEELED KUBOTA M9540DTC | E8: TMF1 | F8: HDV Heavy Duty Vehicle | G8: Tengiz | H8: M9540D87065 | I8: M9540D87065 | J8: 20850 | K8: =IFERROR(VLOOKUP(J8,'CC directory'!A:B,2,),"") -> ACTIVE | L8: =IFERROR(VLOOKUP(J8,'CC directory'!A:D,4,),"") -> 200 | M8: =VLOOKUP(J8,'CC directory'!A:I,9,) -> Maintenance Shared Services | N8: =IFERROR(VLOOKUP(J8,'CC directory'!A:C,3,),"") -> Operations | O8: =IFERROR(VLOOKUP(J8,'CC directory'!A:F,6,),"") -> 207 | P8: =IFERROR(VLOOKUP(J8,'CC directory'!A:E,5,),"") -> Production Operations | Q8: =IFERROR(VLOOKUP(J8,'CC directory'!A:H,8,),"") -> 705 | R8: =IFERROR(VLOOKUP(J8,'CC directory'!A:G,7,),"") -> Maintenance | S8: Maintenance | T8: Maintenance Shared Services | U8: 522 | V8: Tengiz fleet | Z8: Non-Critical | AA8: KUBOTA | AB8: M9540DTC | AC8: USD | AD8: 44993 | AE8: 2011 | AF8: 12 | AH8: AY1569 | AJ8: KGI093656 | AK8: 40807 | AL8: 20 | AM8: 40811 | AO8: 22142 | AP8: 22142 | AQ8: 21957.00 mh#1 | AR8: 12.4/24 | AS8: 18.4/30 | AT8: CONTW006 | AU8: 156681 | AV8: 2021 | AW8: 2031 | AZ8: 523 | BA8: INLINE 4 | BD8: =IF((BE8+BG8+BI8)>0, "YES", "NO") -> NO | BE8: 0 | BG8: 0 | BI8: 0 | BK8: TFM/АРП | BL8: Self-propelled motorized (HDV/HDE) - Wheeled | BM8: =VLOOKUP(BL8,'directory all'!C:D,2,) -> Mileage, engine hours, GPS | BN8: Road construction and cleaning equipment | BO8: Shared with conditions | BQ8: N/A | BR8: N/A | BS8: N/A | BT8: N/A | BU8: N/A | BV8: N/A | BW8: N/A | BX8: N/A | BY8: TCO SCM Logistics | BZ8: 200-4410 | CA8: msslte@tengizchevroil.com | CG8: Maintenance: Assylbek Amangaliyev / Yerkin Dauletov
A9: 110010 | B9: Active | C9: 322EAD | D9: TRACTOR WHEELED JCB HMV 2155 | E9: TMF1 | F9: HDV Heavy Duty Vehicle | G9: Tengiz | H9: JCB26H60V00743037 | I9: JCB26H60V00743037 | J9: 20550 | K9: =IFERROR(VLOOKUP(J9,'CC directory'!A:B,2,),"") -> ACTIVE | L9: =IFERROR(VLOOKUP(J9,'CC directory'!A:D,4,),"") -> 150 | M9: =VLOOKUP(J9,'CC directory'!A:I,9,) -> WM Tengiz - Base | N9: =IFERROR(VLOOKUP(J9,'CC directory'!A:C,3,),"") -> OE/HSE | O9: =IFERROR(VLOOKUP(J9,'CC directory'!A:F,6,),"") -> 205 | P9: =IFERROR(VLOOKUP(J9,'CC directory'!A:E,5,),"") -> OE/HSE | Q9: =IFERROR(VLOOKUP(J9,'CC directory'!A:H,8,),"") -> 607 | R9: =IFERROR(VLOOKUP(J9,'CC directory'!A:G,7,),"") -> Tengiz OE/HSE | S9: Tengiz OE/HSE | T9: WM Tengiz - Base | U9: 523 | V9: Tengiz fleet | Z9: Non-Critical | AA9: JCB | AB9: HMV 2155 | AC9: USD | AD9: 152000 | AE9: 2013 | AF9: 10 | AH9: 22083777 | AJ9: KGI216455 | AK9: 41558 | AL9: 20 | AM9: 41563 | AO9: 3678 | AP9: 3678 | AQ9: 3550.00 mh#1 | AR9: 480/70 R-30 TM- | AS9: 480/70 R30 TM-7 | AT9: CONTW 005 | AU9: 185781 | AV9: 2023 | AW9: 2033 | AZ9: 524 | BA9: IN-LINE 6 | BD9: =IF((BE9+BG9+BI9)>0, "YES", "NO") -> YES | BE9: 1 | BF9: JCB 322 EAD (ТШО 110010) | BG9: 0 | BI9: 0 | BK9: Tengiz Eco Centre | BL9: Self-propelled motorized (HDV/HDE) - Wheeled | BM9: =VLOOKUP(BL9,'directory all'!C:D,2,) -> Mileage, engine hours, GPS | BN9: Road construction and cleaning equipment | BO9: Shared with conditions | BQ9: N/A | BR9: N/A | BS9: N/A | BT9: information missing | BU9: 600–1000 А | BV9: 12 В / 100–120 А | BW9: ~8–10 bar | BX9: ~60–80 m³/h | BY9: TCO SCM Logistics | BZ9: 2234 | CA9: envsvs@tengizchevroil.com | CB9: YES | CD9: 10 | CF9: Currently used in TEC | CG9: Tengiz Base: Azamat Kurmanov / Rustem Konyrbayev
A10: 110011 | B10: Active | C10: AOD112E | D10: TRACTOR WHEELED KUBOTA M5-111 | E10: TMF1 | F10: HDV Heavy Duty Vehicle | G10: Tengiz | H10: KBTMGEDCCG8053456 | I10: KBTMGEDCCG8053456 | J10: 20850 | K10: =IFERROR(VLOOKUP(J10,'CC directory'!A:B,2,),"") -> ACTIVE | L10: =IFERROR(VLOOKUP(J10,'CC directory'!A:D,4,),"") -> 200 | M10: =VLOOKUP(J10,'CC directory'!A:I,9,) -> Maintenance Shared Services | N10: =IFERROR(VLOOKUP(J10,'CC directory'!A:C,3,),"") -> Operations | O10: =IFERROR(VLOOKUP(J10,'CC directory'!A:F,6,),"") -> 207 | P10: =IFERROR(VLOOKUP(J10,'CC directory'!A:E,5,),"") -> Production Operations | Q10: =IFERROR(VLOOKUP(J10,'CC directory'!A:H,8,),"") -> 705 | R10: =IFERROR(VLOOKUP(J10,'CC directory'!A:G,7,),"") -> Maintenance | S10: Maintenance | T10: Maintenance Shared Services | U10: 524 | V10: Tengiz fleet | Z10: Non-Critical | AA10: KUBOTA Corporation | AB10: M5-111 | AC10: GBP | AD10: 46033.15 | AE10: 2017 | AF10: 6 | AH10: 2GU0561 | AI10: 43046 | AJ10: ACY000350 | AL10: 20 | AM10: 43027 | AO10: 22095 | AP10: 22095 | AQ10: 5919.00 mh#1 | AR10: 360/70 R 24 | AS10: 480/70 R 34 | AT10: CONTW 009 | AU10: 267694 | AV10: 2027 | AW10: 2037 | AZ10: 525 | BD10: =IF((BE10+BG10+BI10)>0, "YES", "NO") -> YES | BE10: 1 | BF10: KUBOTA AOD112E (ТШО 110011) | BG10: 0 | BI10: 0 | BK10: TFM/АРП | BL10: Self-propelled motorized (HDV/HDE) - Wheeled | BM10: =VLOOKUP(BL10,'directory all'!C:D,2,) -> Mileage, engine hours, GPS | BN10: Road construction and cleaning equipment | BO10: Shared with conditions | BQ10: N/A | BR10: N/A | BS10: N/A | BT10: N/A | BU10: N/A | BV10: N/A | BW10: N/A | BX10: N/A | BY10: TCO SCM Logistics | BZ10: 200-4410 | CA10: msslte@tengizchevroil.com | CB10: YES | CC10: 18.279 | CD10: 7.236 | CG10: Maintenance: Assylbek Amangaliyev / Yerkin Dauletov
A11: 110012 | B11: Active | C11: 238EAC | D11: TRACTOR WHEELED JCB FASTRAC 4160 | E11: TMF1 | F11: HDV Heavy Duty Vehicle | G11: Tengiz | H11: JCB41Y60CK2765293 | I11: JCB41Y60CK2765293 | J11: 20850 | K11: =IFERROR(VLOOKUP(J11,'CC directory'!A:B,2,),"") -> ACTIVE | L11: =IFERROR(VLOOKUP(J11,'CC directory'!A:D,4,),"") -> 200 | M11: =VLOOKUP(J11,'CC directory'!A:I,9,) -> Maintenance Shared Services | N11: =IFERROR(VLOOKUP(J11,'CC directory'!A:C,3,),"") -> Operations | O11: =IFERROR(VLOOKUP(J11,'CC directory'!A:F,6,),"") -> 207 | P11: =IFERROR(VLOOKUP(J11,'CC directory'!A:E,5,),"") -> Production Operations | Q11: =IFERROR(VLOOKUP(J11,'CC directory'!A:H,8,),"") -> 705 | R11: =IFERROR(VLOOKUP(J11,'CC directory'!A:G,7,),"") -> Maintenance | S11: Maintenance | T11: Maintenance Shared Services | U11: 525 | V11: Tengiz fleet | Z11: Non-Critical | AA11: JCB Construction Equipment | AB11: FASTRAC 4160U | AC11: KZT | AD11: 106080800 | AE11: 2019 | AF11: 4 | AH11: JLKD371202 | AI11: 43713 | AJ11: ACУ000818 | AK11: 43683 | AL11: 20 | AM11: 43692 | AO11: 5562 | AP11: 5562 | AQ11: 4350.00 mh#1 | AR11: 500/70R24 | AS11: 500/70R24 | AT11: CONTW 007 | AU11: 303021 | AV11: 2029 | AW11: 2039 | AZ11: 526 | BD11: =IF((BE11+BG11+BI11)>0, "YES", "NO") -> YES | BE11: 1 | BF11: JCB 238EAC (ТШО 110012) | BG11: 0 | BI11: 0 | BK11: Plant KTL/Завод КТЛ | BL11: Self-propelled motorized (HDV/HDE) - Wheeled | BM11: =VLOOKUP(BL11,'directory all'!C:D,2,) -> Mileage, engine hours, GPS | BN11: Road construction and cleaning equipment | BO11: Shared with conditions | BQ11: N/A | BR11: N/A | BS11: N/A | BT11: N/A | BU11: N/A | BV11: N/A | BW11: N/A | BX11: N/A | BY11: TCO SCM Logistics | BZ11: 200-4410 | CA11: msslte@tengizchevroil.com | CB11: YES | CC11: 18.279 | CD11: 7.236 | CG11: Maintenance: Assylbek Amangaliyev / Yerkin Dauletov
A12: 110013 | B12: Active | C12: E138ACD | D12: TRACTOR WHEELED 6110B | E12: TMF1 | F12: HDV Heavy Duty Vehicle | G12: Tengiz | H12: 1YR6110BEND530287 | I12: 1YR6110BEND530287 | J12: 20850 | K12: =IFERROR(VLOOKUP(J12,'CC directory'!A:B,2,),"") -> ACTIVE | L12: =IFERROR(VLOOKUP(J12,'CC directory'!A:D,4,),"") -> 200 | M12: =VLOOKUP(J12,'CC directory'!A:I,9,) -> Maintenance Shared Services | N12: =IFERROR(VLOOKUP(J12,'CC directory'!A:C,3,),"") -> Operations | O12: =IFERROR(VLOOKUP(J12,'CC directory'!A:F,6,),"") -> 207 | P12: =IFERROR(VLOOKUP(J12,'CC directory'!A:E,5,),"") -> Production Operations | Q12: =IFERROR(VLOOKUP(J12,'CC directory'!A:H,8,),"") -> 705 | R12: =IFERROR(VLOOKUP(J12,'CC directory'!A:G,7,),"") -> Maintenance | S12: Maintenance | T12: Maintenance Shared Services | U12: 526 | V12: Tengiz fleet | Z12: Non-Critical | AA12: JOHN DEERE | AB12: 6110B | AC12: KZT | AD12: 35497050 | AE12: 2022 | AF12: 1 | AH12: PE4045N033113 | AI12: 44868 | AJ12: АТБ000568 | AK12: 44942 | AL12: 10 | AM12: 44852 | AO12: 6 | AP12: 6 | AQ12: 50.00 mh#1 | AR12: 380/85R24 | AS12: 420/85R38 | AT12: CONTW 008 | AU12: 371202 | AV12: 2032 | AW12: 2032 | AZ12: 527 | BD12: =IF((BE12+BG12+BI12)>0, "YES", "NO") -> YES | BE12: 1 | BF12: JohnDeere E138 ACD TCO110013 | BG12: 0 | BI12: 0 | BK12: Plant KTL/Завод КТЛ | BL12: Self-propelled motorized (HDV/HDE) - Wheeled | BM12: =VLOOKUP(BL12,'directory all'!C:D,2,) -> Mileage, engine hours, GPS | BN12: Road construction and cleaning equipment | BO12: Shared with conditions | BQ12: N/A | BR12: N/A | BS12: N/A | BT12: N/A | BU12: N/A | BV12: N/A | BW12: N/A | BX12: N/A | BY12: TCO SCM Logistics | BZ12: 200-4410 | CA12: msslte@tengizchevroil.com | CB12: YES | CC12: 18.279 | CD12: 7.236 | CG12: Maintenance: Assylbek Amangaliyev / Yerkin Dauletov
A13: 110014 | B13: Active | C13: E140ACD | D13: TRACTOR WHEELED 6110B | E13: TMF1 | F13: HDV Heavy Duty Vehicle | G13: Tengiz | H13: 1YR6110BKND530294 | I13: 1YR6110BKND530294 | J13: 20850 | K13: =IFERROR(VLOOKUP(J13,'CC directory'!A:B,2,),"") -> ACTIVE | L13: =IFERROR(VLOOKUP(J13,'CC directory'!A:D,4,),"") -> 200 | M13: =VLOOKUP(J13,'CC directory'!A:I,9,) -> Maintenance Shared Services | N13: =IFERROR(VLOOKUP(J13,'CC directory'!A:C,3,),"") -> Operations | O13: =IFERROR(VLOOKUP(J13,'CC directory'!A:F,6,),"") -> 207 | P13: =IFERROR(VLOOKUP(J13,'CC directory'!A:E,5,),"") -> Production Operations | Q13: =IFERROR(VLOOKUP(J13,'CC directory'!A:H,8,),"") -> 705 | R13: =IFERROR(VLOOKUP(J13,'CC directory'!A:G,7,),"") -> Maintenance | S13: Maintenance | T13: Maintenance Shared Services | U13: 527 | V13: Tengiz fleet | Z13: Non-Critical | AA13: JOHN DEERE | AB13: 6110B | AC13: KZT | AD13: 35497050 | AE13: 2022 | AF13: 1 | AH13: PE4045N034602 | AI13: 44868 | AJ13: АТБ000570 | AK13: 44955 | AL13: 10 | AM13: 44852 | AO13: 5 | AP13: 5 | AQ13: 51.00 mh#1 | AR13: 380/85R24 | AS13: 420/85R38 | AT13: CONTW 008 | AU13: 371202 | AV13: 2032 | AW13: 2032 | AZ13: 528 | BD13: =IF((BE13+BG13+BI13)>0, "YES", "NO") -> YES | BE13: 1 | BF13: John Deere E140 ACD TCO110014 | BG13: 0 | BI13: 0 | BK13: Plant KTL/Завод КТЛ | BL13: Self-propelled motorized (HDV/HDE) - Wheeled | BM13: =VLOOKUP(BL13,'directory all'!C:D,2,) -> Mileage, engine hours, GPS | BN13: Road construction and cleaning equipment | BO13: Shared with conditions | BQ13: N/A | BR13: N/A | BS13: N/A | BT13: N/A | BU13: N/A | BV13: N/A | BW13: N/A | BX13: N/A | BY13: TCO SCM Logistics | BZ13: 200-4410 | CA13: msslte@tengizchevroil.com | CB13: YES | CC13: 18.279 | CD13: 7.236 | CG13: Maintenance: Assylbek Amangaliyev / Yerkin Dauletov
A14: 110015 | B14: Active | C14: E139ACD | D14: TRACTOR WHEELED 6110B | E14: TMF1 | F14: HDV Heavy Duty Vehicle | G14: Tengiz | H14: 1YR6110BCND530296 | I14: 1YR6110BCND530296 | J14: 20850 | K14: =IFERROR(VLOOKUP(J14,'CC directory'!A:B,2,),"") -> ACTIVE | L14: =IFERROR(VLOOKUP(J14,'CC directory'!A:D,4,),"") -> 200 | M14: =VLOOKUP(J14,'CC directory'!A:I,9,) -> Maintenance Shared Services | N14: =IFERROR(VLOOKUP(J14,'CC directory'!A:C,3,),"") -> Operations | O14: =IFERROR(VLOOKUP(J14,'CC directory'!A:F,6,),"") -> 207 | P14: =IFERROR(VLOOKUP(J14,'CC directory'!A:E,5,),"") -> Production Operations | Q14: =IFERROR(VLOOKUP(J14,'CC directory'!A:H,8,),"") -> 705 | R14: =IFERROR(VLOOKUP(J14,'CC directory'!A:G,7,),"") -> Maintenance | S14: Maintenance | T14: Maintenance Shared Services | U14: 528 | V14: Tengiz fleet | Z14: Non-Critical | AA14: JOHN DEERE | AB14: 6110B | AC14: KZT | AD14: 35497050 | AE14: 2022 | AF14: 1 | AH14: PE4045N034398 | AI14: 44868 | AJ14: АТБ000569 | AK14: 44967 | AL14: 10 | AM14: 44852 | AO14: 5 | AP14: 5 | AQ14: 78.00 mh#1 | AR14: 380/85R24 | AS14: 420/85R38 | AT14: CONTW 008 | AU14: 371202 | AV14: 2032 | AW14: 2032 | AZ14: 529 | BD14: =IF((BE14+BG14+BI14)>0, "YES", "NO") -> YES | BE14: 1 | BF14: John Deere E139 ACD TCO 110015 | BG14: 0 | BI14: 0 | BK14: Plant KTL/Завод КТЛ | BL14: Self-propelled motorized (HDV/HDE) - Wheeled | BM14: =VLOOKUP(BL14,'directory all'!C:D,2,) -> Mileage, engine hours, GPS | BN14: Road construction and cleaning equipment | BO14: Shared with conditions | BQ14: N/A | BR14: N/A | BS14: N/A | BT14: N/A | BU14: N/A | BV14: N/A | BW14: N/A | BX14: N/A | BY14: TCO SCM Logistics | BZ14: 200-4410 | CA14: msslte@tengizchevroil.com | CB14: YES | CC14: 18.279 | CD14: 7.236 | CG14: Maintenance: Assylbek Amangaliyev / Yerkin Dauletov
A15: 111012 | B15: Active | C15: H032206 | D15: TRUCK HD CHEMICAL 3000 GAL KENWORTH T370 | E15: TMF1 | F15: HDV Heavy Duty Vehicle | G15: Tengiz | H15: 2NKHLZ9X8DM354323 | I15: 2NKHLZ9X8DM354323 | J15: 13780 | K15: =IFERROR(VLOOKUP(J15,'CC directory'!A:B,2,),"") -> ACTIVE | L15: =IFERROR(VLOOKUP(J15,'CC directory'!A:D,4,),"") -> 200 | M15: =VLOOKUP(J15,'CC directory'!A:I,9,) -> Heavy Equipment Operations | N15: =IFERROR(VLOOKUP(J15,'CC directory'!A:C,3,),"") -> Operations | O15: =IFERROR(VLOOKUP(J15,'CC directory'!A:F,6,),"") -> 209 | P15: =IFERROR(VLOOKUP(J15,'CC directory'!A:E,5,),"") -> Supply Chain Management | Q15: =IFERROR(VLOOKUP(J15,'CC directory'!A:H,8,),"") -> 322 | R15: =IFERROR(VLOOKUP(J15,'CC directory'!A:G,7,),"") -> Tengiz Ground Transportation | S15: SCM Logistics | T15: Heavy Equipment Operations | U15: 529 | V15: Tengiz fleet | Z15: Critical | AA15: KENWORTH | AB15: T370 | AC15: USD | AD15: 172300 | AE15: 2012 | AF15: 10 | AH15: 73399913 | AJ15: ED00013282 | AK15: 41314 | AL15: 15 | AM15: 41331 | AO15: 137132 | AP15: 137132 | AR15: 11R22.5 | AS15: 11R22.5 | AT15: TRKKEN 006 | AU15: 168690 | AV15: 2023 | AW15: 2028 | AY15: YES | AZ15: 530 | BA15: IN-LINE 6 | BB15: FSO6406A | BD15: =IF((BE15+BG15+BI15)>0, "YES", "NO") -> YES | BE15: 1 | BF15: KENWORTH H 0322 06 (ТШО 111012) | BG15: 1 | BH15: H 032206 | BI15: 0 | BK15: Industrial Base | BL15: Self-propelled motorized (HDV/HDE) - Wheeled | BM15: =VLOOKUP(BL15,'directory all'!C:D,2,) -> Mileage, engine hours, GPS | BN15: Chemical truck | BO15: Shared without conditions | BQ15: N/A | BR15: 10 | BS15: N/A | BT15: N/A | BU15: N/A | BV15: N/A | BW15: N/A | BX15: N/A | BY15: TCO SCM Logistics | BZ15: 3148 | CB15: YES | CC15: 40 | CD15: 1.5 | CG15: SCM Logistics: Yerbol Nauryzbay / Yerlan Yeshmagambetov
A16: 111013 | B16: Active | C16: H032106 | D16: TRUCK HD CHEMICAL 3000 GAL KENWORTH T370 | E16: TMF1 | F16: HDV Heavy Duty Vehicle | G16: Tengiz | H16: 2NKHLZ9XXDM354324 | I16: 2NKHLZ9XXDM354324 | J16: 13780 | K16: =IFERROR(VLOOKUP(J16,'CC directory'!A:B,2,),"") -> ACTIVE | L16: =IFERROR(VLOOKUP(J16,'CC directory'!A:D,4,),"") -> 200 | M16: =VLOOKUP(J16,'CC directory'!A:I,9,) -> Heavy Equipment Operations | N16: =IFERROR(VLOOKUP(J16,'CC directory'!A:C,3,),"") -> Operations | O16: =IFERROR(VLOOKUP(J16,'CC directory'!A:F,6,),"") -> 209 | P16: =IFERROR(VLOOKUP(J16,'CC directory'!A:E,5,),"") -> Supply Chain Management | Q16: =IFERROR(VLOOKUP(J16,'CC directory'!A:H,8,),"") -> 322 | R16: =IFERROR(VLOOKUP(J16,'CC directory'!A:G,7,),"") -> Tengiz Ground Transportation | S16: SCM Logistics | T16: Heavy Equipment Operations | U16: 530 | V16: Tengiz fleet | Z16: Critical | AA16: KENWORTH | AB16: T370 | AC16: USD | AD16: 172300 | AE16: 2012 | AF16: 10 | AH16: 73399914 | AJ16: ED00013281 | AK16: 41314 | AL16: 15 | AM16: 41331 | AO16: 139094 | AP16: 139094 | AR16: 11R22.5 | AS16: 11R22.5 | AT16: TRKKEN 006 | AU16: 168690 | AV16: 2023 | AW16: 2028 | AY16: YES | AZ16: 531 | BA16: IN-LINE 6 | BB16: FSO6406A | BD16: =IF((BE16+BG16+BI16)>0, "YES", "NO") -> YES | BE16: 1 | BF16: KENWORTH H 032106 (ТШО 111013) | BG16: 1 | BH16: H 032106 | BI16: 0 | BK16: Industrial Base | BL16: Self-propelled motorized (HDV/HDE) - Wheeled | BM16: =VLOOKUP(BL16,'directory all'!C:D,2,) -> Mileage, engine hours, GPS | BN16: Chemical truck | BO16: Shared without conditions | BQ16: N/A | BR16: 10 | BS16: N/A | BT16: N/A | BU16: N/A | BV16: N/A | BW16: N/A | BX16: N/A | BY16: TCO SCM Logistics | BZ16: 3336 / 7068 | CB16: YES | CC16: 40 | CD16: 1.5 | CG16: SCM Logistics: Yerbol Nauryzbay / Yerlan Yeshmagambetov
A17: 111015 | B17: Reserved | C17: H531506 | D17: TRUCK HD CHEMICAL 20 TONN HINO 67443C | E17: TMF1 | F17: HDV Heavy Duty Vehicle | G17: TENGIZ | H17: JHDFS1EUU00010086 | I17: MX967443CP0021173 | J17: 20850 | K17: =IFERROR(VLOOKUP(J17,'CC directory'!A:B,2,),"") -> ACTIVE | L17: =IFERROR(VLOOKUP(J17,'CC directory'!A:D,4,),"") -> 200 | M17: =VLOOKUP(J17,'CC directory'!A:I,9,) -> Maintenance Shared Services | N17: =IFERROR(VLOOKUP(J17,'CC directory'!A:C,3,),"") -> Operations | O17: =IFERROR(VLOOKUP(J17,'CC directory'!A:F,6,),"") -> 207 | P17: =IFERROR(VLOOKUP(J17,'CC directory'!A:E,5,),"") -> Production Operations | Q17: =IFERROR(VLOOKUP(J17,'CC directory'!A:H,8,),"") -> 705 | R17: =IFERROR(VLOOKUP(J17,'CC directory'!A:G,7,),"") -> Maintenance | S17: Maintenance | T17: Maintenance Shared Services | U17: 2183 | V17: Tengiz Fleet | Y17: 45237 | Z17: Critical | AA17: HINO | AB17: 67443C | AC17: KZT | AD17: 1.4817747e+08 | AE17: 2023 | AI17: 45268 | AJ17: EW00013960 | AK17: 45237 | AL17: 10 | AM17: 45237 | AP17: 30 | AU17: 376020 | AV17: 2033 | AW17: 2033 | AZ17: 2390 | BB17: HINO, NX07 | BC17: 06.01.2024-sutz: The status was changed to "Reserved", according to the e-mail from Registration Department with confirmed by TCO Transportation Team Lead as of 16.12.2023. (Inbox-Registration Department as of 18.12.2023) It is direct order from the customer. Assigned to CC 20850 - Maintenance Shared Services. (Inbox-Registration Dept as of 11.11.2023) | BD17: =IF((BE17+BG17+BI17)>0, "YES", "NO") -> YES | BE17: 1 | BF17: HINO H531506 ТШО 111015 | BG17: 1 | BH17: H 531506 | BI17: 0 | BK17: TFM/АРП | BL17: Self-propelled motorized (HDV/HDE) - Wheeled | BM17: =VLOOKUP(BL17,'directory all'!C:D,2,) -> Mileage, engine hours, GPS | BN17: Chemical truck | BO17: Shared with conditions | BQ17: 20000 | BR17: N/A | BS17: N/A | BT17: N/A | BU17: N/A | BV17: N/A | BW17: N/A | BX17: N/A | BY17: TCO SCM Logistics | BZ17: 200-4401 | CA17: mssls@tengizchevroil.com | CB17: YES | CC17: 18.279 | CD17: 1.257 | CG17: Maintenance: Assylbek Amangaliyev / Yerkin Dauletov
A18: 115015 | B18: Active | C18: H724244 | D18: TRUCK HD LUBE KENWORTH T800 | E18: TMF1 | F18: HDV Heavy Duty Vehicle | G18: Tengiz | H18: 1NKDL40X3AJ272775 | I18: 1NKDL40X3AJ272775 | J18: 13780 | K18: =IFERROR(VLOOKUP(J18,'CC directory'!A:B,2,),"") -> ACTIVE | L18: =IFERROR(VLOOKUP(J18,'CC directory'!A:D,4,),"") -> 200 | M18: =VLOOKUP(J18,'CC directory'!A:I,9,) -> Heavy Equipment Operations | N18: =IFERROR(VLOOKUP(J18,'CC directory'!A:C,3,),"") -> Operations | O18: =IFERROR(VLOOKUP(J18,'CC directory'!A:F,6,),"") -> 209 | P18: =IFERROR(VLOOKUP(J18,'CC directory'!A:E,5,),"") -> Supply Chain Management | Q18: =IFERROR(VLOOKUP(J18,'CC directory'!A:H,8,),"") -> 322 | R18: =IFERROR(VLOOKUP(J18,'CC directory'!A:G,7,),"") -> Tengiz Ground Transportation | S18: SCM Logistics | T18: Heavy Equipment Operations | U18: 585 | V18: Tengiz fleet | Z18: Non-Critical | AA18: KENWORTH | AB18: T800 | AC18: USD | AD18: 279445 | AE18: 2009 | AF18: 13 | AH18: 79395703 | AJ18: ED00010973 | AK18: 40231 | AL18: 15 | AM18: 40255 | AO18: 241165 | AP18: 241165 | AR18: 425/65R22.5 | AS18: 11R24 | AT18: TRKKEN 002 | AU18: 135773 | AV18: 2022 | AW18: 2025 | AY18: YES | AZ18: 586 | BD18: =IF((BE18+BG18+BI18)>0, "YES", "NO") -> YES | BE18: 1 | BF18: KENWORTH H 724244 (ТШО 115015) | BG18: 1 | BH18: H 724244 | BI18: 0 | BK18: Industrial Base | BL18: Self-propelled motorized (HDV/HDE) - Wheeled | BM18: =VLOOKUP(BL18,'directory all'!C:D,2,) -> Mileage, engine hours, GPS | BN18: Recovery/service truck | BO18: Shared without conditions | BQ18: 8850 | BR18: N/A | BS18: N/A | BT18: N/A | BU18: N/A | BV18: N/A | BW18: N/A | BX18: N/A | BY18: TCO SCM Logistics | BZ18: 7514 | CB18: YES | CC18: 30 | CG18: SCM Logistics: Yerbol Nauryzbay / Yerlan Yeshmagambetov
A19: 116014 | B19: Active | C19: 229EAD | D19: TRACTOR AIRCRAFT TOW (TUG) AWD | E19: TMF1 | F19: HDV Heavy Duty Vehicle | G19: Tengiz | H19: 6182 | I19: 6182 | J19: 13727 | K19: =IFERROR(VLOOKUP(J19,'CC directory'!A:B,2,),"") -> ACTIVE | L19: =IFERROR(VLOOKUP(J19,'CC directory'!A:D,4,),"") -> 200 | M19: =VLOOKUP(J19,'CC directory'!A:I,9,) -> Flight Ops & Charters | N19: =IFERROR(VLOOKUP(J19,'CC directory'!A:C,3,),"") -> Operations | O19: =IFERROR(VLOOKUP(J19,'CC directory'!A:F,6,),"") -> 209 | P19: =IFERROR(VLOOKUP(J19,'CC directory'!A:E,5,),"") -> Supply Chain Management | Q19: =IFERROR(VLOOKUP(J19,'CC directory'!A:H,8,),"") -> 321 | R19: =IFERROR(VLOOKUP(J19,'CC directory'!A:G,7,),"") -> Aviation & Logistics | S19: SCM Logistics | T19: AVIATION OPERATIONS | U19: 587 | V19: Tengiz fleet | Z19: Critical | AA19: EAGLE | AB19: TT-6D | AC19: USD | AD19: 55575 | AE19: 2012 | AF19: 10 | AH19: L6822 | AJ19: KGI095084 | AK19: 41331 | AL19: 15 | AM19: 41335 | AO19: 1314 | AP19: 1314 | AQ19: 1234.00 mh#1 | AR19: R8.75-16.5 | AS19: R8.75-16.5 | AT19: TUG 001 | AU19: 172729 | AV19: 2023 | AW19: 2028 | AZ19: 588 | BA19: INLINE 4 | BD19: =IF((BE19+BG19+BI19)>0, "YES", "NO") -> NO | BE19: 0 | BG19: 0 | BI19: 0 | BK19: Aerodrome | BL19: Self-propelled motorized (HDV/HDE) - Wheeled | BM19: =VLOOKUP(BL19,'directory all'!C:D,2,) -> Mileage, engine hours, GPS | BN19: HD truck (tractor) | BO19: Assigned | BP19: Aerdrodrome purpose | BQ19: 3765 | BS19: 12 | BT19: 100 - 120 Ah | BU19: 80 A | BW19: Hydraulic | BY19: TCO SCM Logistics | BZ19: 3370 | CA19: opstng@tengizchevroil.com | CG19: SCM Aviation: Nurzat Khairolla / Zhandos Ospankulov
A20: 117018 | B20: Sent to BP | C20: H176506 | D20: TRUCK HD TRACTOR HYUNDAI HD-1000 | E20: N-COCR | F20: HDV Heavy Duty Vehicle | G20: Tengiz | H20: KMEFG18SPAC046237 | I20: KMEFG18SPAC046237 | J20: 20850 | K20: =IFERROR(VLOOKUP(J20,'CC directory'!A:B,2,),"") -> ACTIVE | L20: =IFERROR(VLOOKUP(J20,'CC directory'!A:D,4,),"") -> 200 | M20: =VLOOKUP(J20,'CC directory'!A:I,9,) -> Maintenance Shared Services | N20: =IFERROR(VLOOKUP(J20,'CC directory'!A:C,3,),"") -> Operations | O20: =IFERROR(VLOOKUP(J20,'CC directory'!A:F,6,),"") -> 207 | P20: =IFERROR(VLOOKUP(J20,'CC directory'!A:E,5,),"") -> Production Operations | Q20: =IFERROR(VLOOKUP(J20,'CC directory'!A:H,8,),"") -> 705 | R20: =IFERROR(VLOOKUP(J20,'CC directory'!A:G,7,),"") -> Maintenance | S20: Maintenance | T20: Maintenance Shared Services | U20: 1462 | V20: Tengiz Fleet | Z20: Critical | AA20: HYUNDAI | AB20: HD-1000 | AC20: USD | AD20: 96619 | AE20: 2010 | AF20: 13 | AI20: 1 | AJ20: ED00015573 | AK20: 40277 | AL20: 15 | AM20: 40491 | AO20: 22725 | AP20: 22725 | AR20: 12R22,5 | AS20: 12R22,5 | AT20: TRKHUI 002 | AU20: 142062 | AV20: 2022 | AW20: 2025 | AY20: YES | AZ20: 1668 | BA20: 6 | BB20: ZF165151 | BC20: 06.10.23-sutz: CC was changed from 13780 - Heavy Equipment Operations to 20850 - Maintenance Shared Services, according to the e-mail from TCO Transportation Team Lead’s Erbol with confirmed as of 03.10.2023 (Inbox - CC Change). COCR will no longer provide maintenance, and the OTTO department will now carry out repairs, therefore not registered in E-MAINT and Fleet Management Tool systems. | BD20: =IF((BE20+BG20+BI20)>0, "YES", "NO") -> YES | BE20: 1 | BF20: HYUNDAI H176506 (ТШО 117018) | BG20: 1 | BH20: H 176506 | BI20: 0 | BK20: Plant KTL/Завод КТЛ | BL20: Self-propelled motorized (HDV/HDE) - Wheeled | BM20: =VLOOKUP(BL20,'directory all'!C:D,2,) -> Mileage, engine hours, GPS | BN20: HD truck (tractor) | BO20: Shared with conditions | BQ20: N/A | BR20: N/A | BS20: N/A | BT20: N/A | BU20: N/A | BV20: N/A | BW20: N/A | BX20: N/A | BY20: TCO MSS BP | BZ20: 200-4401 | CA20: mssls@tengizchevroil.com | CB20: YES | CC20: 18.279 | CD20: 2.359 | CG20: Maintenance: Assylbek Amangaliyev / Yerkin Dauletov
A21: 117019 | B21: Active | C21: H725109 | D21: TRUCK HD TRACTOR HYUNDAI HD-1000 | E21: TMF1 | F21: HDV Heavy Duty Vehicle | G21: Tengiz | H21: KMEFG18SPAC046236 | I21: KMEFG18SPAC046236 | J21: 13780 | K21: =IFERROR(VLOOKUP(J21,'CC directory'!A:B,2,),"") -> ACTIVE | L21: =IFERROR(VLOOKUP(J21,'CC directory'!A:D,4,),"") -> 200 | M21: =VLOOKUP(J21,'CC directory'!A:I,9,) -> Heavy Equipment Operations | N21: =IFERROR(VLOOKUP(J21,'CC directory'!A:C,3,),"") -> Operations | O21: =IFERROR(VLOOKUP(J21,'CC directory'!A:F,6,),"") -> 209 | P21: =IFERROR(VLOOKUP(J21,'CC directory'!A:E,5,),"") -> Supply Chain Management | Q21: =IFERROR(VLOOKUP(J21,'CC directory'!A:H,8,),"") -> 322 | R21: =IFERROR(VLOOKUP(J21,'CC directory'!A:G,7,),"") -> Tengiz Ground Transportation | S21: SCM Logistics | T21: Heavy Equipment Operations | U21: 588 | V21: Tengiz fleet | Z21: Critical | AA21: HYUNDAI | AB21: HD-1000 | AC21: USD | AD21: 96619 | AE21: 2010 | AF21: 13 | AJ21: ED00011313 | AK21: 40425 | AL21: 15 | AM21: 40432 | AO21: 281702 | AP21: 200426 | AR21: 12R22,5 | AS21: 12R22,5 | AT21: TRKHUI 002 | AU21: 142062 | AV21: 2022 | AW21: 2025 | AY21: YES | AZ21: 590 | BA21: 6 | BB21: ZF165151 | BD21: =IF((BE21+BG21+BI21)>0, "YES", "NO") -> YES | BE21: 1 | BF21: HYUNDAI H725109 (ТШО 117019) | BG21: 1 | BH21: H 725109 | BI21: 0 | BK21: Industrial Base | BL21: Self-propelled motorized (HDV/HDE) - Wheeled | BM21: =VLOOKUP(BL21,'directory all'!C:D,2,) -> Mileage, engine hours, GPS | BN21: HD truck (tractor) | BO21: Shared without conditions | BQ21: N/A | BR21: N/A | BS21: N/A | BT21: N/A | BU21: N/A | BV21: N/A | BW21: N/A | BX21: N/A | BY21: TCO SCM Logistics | BZ21: 5158 | CB21: YES | CC21: 40 | CE21: In preservation | CF21: Long downtime time, decision for write off is pending | CG21: SCM Logistics: Yerbol Nauryzbay / Yerlan Yeshmagambetov
A22: 117020 | B22: Active | C22: H494106 | D22: TRUCK HD MAN TGS-41.400 | E22: TMF1 | F22: HDV Heavy Duty Vehicle | G22: Tengiz | H22: WMA39WZZ3CP033399 | I22: WMA39WZZ3CP033399 | J22: 20850 | K22: =IFERROR(VLOOKUP(J22,'CC directory'!A:B,2,),"") -> ACTIVE | L22: =IFERROR(VLOOKUP(J22,'CC directory'!A:D,4,),"") -> 200 | M22: =VLOOKUP(J22,'CC directory'!A:I,9,) -> Maintenance Shared Services | N22: =IFERROR(VLOOKUP(J22,'CC directory'!A:C,3,),"") -> Operations | O22: =IFERROR(VLOOKUP(J22,'CC directory'!A:F,6,),"") -> 207 | P22: =IFERROR(VLOOKUP(J22,'CC directory'!A:E,5,),"") -> Production Operations | Q22: =IFERROR(VLOOKUP(J22,'CC directory'!A:H,8,),"") -> 705 | R22: =IFERROR(VLOOKUP(J22,'CC directory'!A:G,7,),"") -> Maintenance | S22: Maintenance | T22: Maintenance Shared Services | U22: 589 | V22: Tengiz fleet | Z22: Non-Critical | AA22: MAN | AB22: TGS-41.400 | AC22: GBP | AD22: 104330.7 | AE22: 2011 | AF22: 11 | AH22: 5.05301E+13 | AI22: 45565 | AJ22: ED99999853 | AK22: 40986 | AL22: 15 | AM22: 40995 | AO22: 99353 | AP22: 99353 | AR22: 315/80R22.5 | AS22: 315/80R22.5 | AT22: TRKHUI 003 | AU22: 158544 | AV22: 2024 | AW22: 2027 | AZ22: 591 | BB22: ZF16 S | BC22: 01.10.2024 xeza: License plate and technical passport was changed according to the e-mail from Registration Dept as of 01.10.24. (Inbox-Registration Dept). 12.02.24-sutz: CC was changed to 20850 - Maintenance Shared Services, according to the e-mail from Registration Dept with confirmed by Fleet maintenance and inspection Team Lead as of 07.02.2024 (Inbox - CC Change) | BD22: =IF((BE22+BG22+BI22)>0, "YES", "NO") -> YES | BE22: 1 | BF22: МАN Н725768 (ТШО 117020) | BG22: 1 | BH22: H 494106 | BI22: 0 | BK22: Plant KTL/Завод КТЛ | BL22: Self-propelled motorized (HDV/HDE) - Wheeled | BM22: =VLOOKUP(BL22,'directory all'!C:D,2,) -> Mileage, engine hours, GPS | BN22: HD truck (tractor) | BO22: Shared with conditions | BQ22: N/A | BR22: N/A | BS22: N/A | BT22: N/A | BU22: N/A | BV22: N/A | BW22: N/A | BX22: N/A | BY22: TCO SCM Logistics | BZ22: 200-4401 | CA22: mssls@tengizchevroil.com | CB22: YES | CC22: 189.9744 | CG22: Maintenance: Assylbek Amangaliyev / Yerkin Dauletov
A23: 117021 | B23: Active | C23: H497706 | D23: TRUCK HD MAN TGS-41.400 | E23: TMF1 | F23: HDV Heavy Duty Vehicle | G23: Tengiz | H23: WMA39WZZ8CP033897 | I23: WMA39WZZ8CP033897 | J23: 20850 | K23: =IFERROR(VLOOKUP(J23,'CC directory'!A:B,2,),"") -> ACTIVE | L23: =IFERROR(VLOOKUP(J23,'CC directory'!A:D,4,),"") -> 200 | M23: =VLOOKUP(J23,'CC directory'!A:I,9,) -> Maintenance Shared Services | N23: =IFERROR(VLOOKUP(J23,'CC directory'!A:C,3,),"") -> Operations | O23: =IFERROR(VLOOKUP(J23,'CC directory'!A:F,6,),"") -> 207 | P23: =IFERROR(VLOOKUP(J23,'CC directory'!A:E,5,),"") -> Production Operations | Q23: =IFERROR(VLOOKUP(J23,'CC directory'!A:H,8,),"") -> 705 | R23: =IFERROR(VLOOKUP(J23,'CC directory'!A:G,7,),"") -> Maintenance | S23: Maintenance | T23: Maintenance Shared Services | U23: 590 | V23: Tengiz fleet | Z23: Non-Critical | AA23: MAN | AB23: TGS-41.400 | AC23: GBP | AD23: 104330.7 | AE23: 2011 | AF23: 11 | AH23: 5.05303E+13 | AI23: 45593 | AJ23: ED99999829 | AK23: 40986 | AL23: 15 | AM23: 40995 | AO23: 64042 | AP23: 64042 | AR23: 315/80R22.5 | AS23: 315/80R22.5 | AT23: TRKHUI 003 | AU23: 158544 | AV23: 2024 | AW23: 2027 | AZ23: 592 | BB23: ZF16 S | BC23: 29.10.24-sutz: Because the old license plate H725767 of the vehicle was damaged and invalid, a new license plate & technical passport was received, according to the e-mail from Registration department as of 29.10.24. (Inbox-Registration Dept) 16.02.24-sutz: CC was changed to 20850 - Maintenance Shared Services, according to the e-mail from Registration Dept with confirmed by Fleet maintenance and inspection Team Lead as of 07.02.2024 (Inbox - CC Change) | BD23: =IF((BE23+BG23+BI23)>0, "YES", "NO") -> YES | BE23: 1 | BF23: МАN Н497706 (ТШО 117021) | BG23: 1 | BH23: H 497706 | BI23: 0 | BK23: Plant KTL/Завод КТЛ | BL23: Self-propelled motorized (HDV/HDE) - Wheeled | BM23: =VLOOKUP(BL23,'directory all'!C:D,2,) -> Mileage, engine hours, GPS | BN23: HD truck (tractor) | BO23: Shared with conditions | BQ23: N/A | BR23: N/A | BS23: N/A | BT23: N/A | BU23: N/A | BV23: N/A | BW23: N/A | BX23: N/A | BY23: TCO SCM Logistics | BZ23: 200-4401 | CA23: mssls@tengizchevroil.com | CB23: YES | CC23: 42.294 | CD23: 2.359 | CG23: Maintenance: Assylbek Amangaliyev / Yerkin Dauletov
A24: 117022 | B24: Active | C24: H209306 | D24: TRUCK HD FRAC TANK TRACTOR W/WINCH KENWO | E24: TMF1 | F24: HDV Heavy Duty Vehicle | G24: Tengiz | H24: 1XDD40X2FR467214 | I24: 1XDD40X2FR467214 | J24: 20850 | K24: =IFERROR(VLOOKUP(J24,'CC directory'!A:B,2,),"") -> ACTIVE | L24: =IFERROR(VLOOKUP(J24,'CC directory'!A:D,4,),"") -> 200 | M24: =VLOOKUP(J24,'CC directory'!A:I,9,) -> Maintenance Shared Services | N24: =IFERROR(VLOOKUP(J24,'CC directory'!A:C,3,),"") -> Operations | O24: =IFERROR(VLOOKUP(J24,'CC directory'!A:F,6,),"") -> 207 | P24: =IFERROR(VLOOKUP(J24,'CC directory'!A:E,5,),"") -> Production Operations | Q24: =IFERROR(VLOOKUP(J24,'CC directory'!A:H,8,),"") -> 705 | R24: =IFERROR(VLOOKUP(J24,'CC directory'!A:G,7,),"") -> Maintenance | S24: Maintenance | T24: Maintenance Shared Services | U24: 591 | V24: Tengiz fleet | Z24: Non-Critical | AA24: KENWORTH | AB24: T800 | AC24: USD | AD24: 204296 | AE24: 2014 | AF24: 8 | AH24: 79789562 | AI24: 42948 | AJ24: ED00016106 | AL24: 15 | AM24: 42185 | AO24: 51489 | AP24: 51489 | AR24: 315/80R22.5 | AS24: 315/80R22.5 | AT24: TRKKEN 007 | AU24: 215308 | AV24: 2027 | AW24: 2030 | AY24: YES | AZ24: 593 | BC24: 14.02.24-sutz: CC was changed to 20850 - Maintenance Shared Services, according to the e-mail from Registration Dept with confirmed by Fleet maintenance and inspection Team Lead as of 07.02.2024 (Inbox - CC Change) | BD24: =IF((BE24+BG24+BI24)>0, "YES", "NO") -> YES | BE24: 1 | BF24: KENWORTH Н209306 (ТШО 117022) | BG24: 1 | BH24: H 209306 | BI24: 0 | BK24: Plant KTL/Завод КТЛ | BL24: Self-propelled motorized (HDV/HDE) - Wheeled | BM24: =VLOOKUP(BL24,'directory all'!C:D,2,) -> Mileage, engine hours, GPS | BN24: HD truck (tractor) | BO24: Shared with conditions | BQ24: 52000 | BR24: N/A | BS24: N/A | BT24: N/A | BU24: N/A | BV24: N/A | BW24: N/A | BX24: N/A | BY24: TCO SCM Logistics | BZ24: 200-4410 | CA24: msslte@tengizchevroil.com | CB24: YES | CC24: 18.279 | CD24: 4.668 | CG24: Maintenance: Assylbek Amangaliyev / Yerkin Dauletov
A25: 117023 | B25: Active | C25: H176206 | D25: TRUCK KAMAZ-65201 MULTILIFT HOOK LOADER | E25: TMF1 | F25: HDV Heavy Duty Vehicle | G25: Tengiz | H25: Z9L780425G0000001 | I25: XTC652014G1333206 | J25: 20850 | K25: =IFERROR(VLOOKUP(J25,'CC directory'!A:B,2,),"") -> ACTIVE | L25: =IFERROR(VLOOKUP(J25,'CC directory'!A:D,4,),"") -> 200 | M25: =VLOOKUP(J25,'CC directory'!A:I,9,) -> Maintenance Shared Services | N25: =IFERROR(VLOOKUP(J25,'CC directory'!A:C,3,),"") -> Operations | O25: =IFERROR(VLOOKUP(J25,'CC directory'!A:F,6,),"") -> 207 | P25: =IFERROR(VLOOKUP(J25,'CC directory'!A:E,5,),"") -> Production Operations | Q25: =IFERROR(VLOOKUP(J25,'CC directory'!A:H,8,),"") -> 705 | R25: =IFERROR(VLOOKUP(J25,'CC directory'!A:G,7,),"") -> Maintenance | S25: Maintenance | T25: Maintenance Shared Services | U25: 592 | V25: Tengiz fleet | Z25: Non-Critical | AA25: KAMAZ-65201 | AB25: 780425 | AC25: KZT | AD25: 40421931 | AE25: 2016 | AF25: 7 | AG25: 2416532 | AI25: 42606 | AJ25: ED00015556 | AL25: 15 | AM25: 42567 | AO25: 9601 | AP25: 9601 | AR25: 315/80R22.5 | AS25: 315/80R22.5 | AT25: TRKHUI | AU25: 249668 | AV25: 2026 | AW25: 2031 | AY25: YES | AZ25: 594 | BC25: 16.02.24-sutz: CC was changed to 20850 - Maintenance Shared Services, according to the e-mail from Registration Dept with confirmed by Fleet maintenance and inspection Team Lead as of 07.02.2024 (Inbox - CC Change) | BD25: =IF((BE25+BG25+BI25)>0, "YES", "NO") -> YES | BE25: 1 | BF25: KAMAZ H176206 (ТШО 117023) | BG25: 1 | BH25: H 176206 | BI25: 0 | BK25: TFM/АРП | BL25: Self-propelled motorized (HDV/HDE) - Wheeled | BM25: =VLOOKUP(BL25,'directory all'!C:D,2,) -> Mileage, engine hours, GPS | BN25: Dump truck | BO25: Shared with conditions | BQ25: 25500 | BR25: N/A | BS25: N/A | BT25: N/A | BU25: N/A | BV25: N/A | BW25: N/A | BX25: N/A | BY25: TCO SCM Logistics | BZ25: 200-4401 | CA25: mssls@tengizchevroil.com | CB25: YES | CC25: 18.279 | CD25: 2.359 | CE25: Seasonal (SGP TA) | CG25: Maintenance: Assylbek Amangaliyev / Yerkin Dauletov
A26: 117024 | B26: Active | C26: H190606 | D26: TRUCK KAMAZ-65201 MULTILIFT HOOK LOADER | E26: TMF1 | F26: HDV Heavy Duty Vehicle | G26: Tengiz | H26: XTC652014G1343353 | I26: XTC652014G1343353 | J26: 20850 | K26: =IFERROR(VLOOKUP(J26,'CC directory'!A:B,2,),"") -> ACTIVE | L26: =IFERROR(VLOOKUP(J26,'CC directory'!A:D,4,),"") -> 200 | M26: =VLOOKUP(J26,'CC directory'!A:I,9,) -> Maintenance Shared Services | N26: =IFERROR(VLOOKUP(J26,'CC directory'!A:C,3,),"") -> Operations | O26: =IFERROR(VLOOKUP(J26,'CC directory'!A:F,6,),"") -> 207 | P26: =IFERROR(VLOOKUP(J26,'CC directory'!A:E,5,),"") -> Production Operations | Q26: =IFERROR(VLOOKUP(J26,'CC directory'!A:H,8,),"") -> 705 | R26: =IFERROR(VLOOKUP(J26,'CC directory'!A:G,7,),"") -> Maintenance | S26: Maintenance | T26: Maintenance Shared Services | U26: 593 | V26: Tengiz fleet | Z26: Non-Critical | AA26: KAMAZ | AB26: 65201 | AC26: KZT | AD26: 45070872 | AE26: 2016 | AF26: 6 | AG26: 2436044 | AH26: 78572250 | AI26: 42798 | AJ26: ED00015855 | AL26: 15 | AM26: 42720 | AO26: 11448 | AP26: 11448 | AR26: 315/80R22,5 | AS26: 315/80R22,5 | AT26: TRKHUI001 | AU26: 252800 | AV26: 2026 | AW26: 2031 | AY26: YES | AZ26: 595 | BC26: 16.02.24-sutz: CC was changed to 20850 - Maintenance Shared Services, according to the e-mail from Registration Dept with confirmed by Fleet maintenance and inspection Team Lead as of 07.02.2024 (Inbox - CC Change) | BD26: =IF((BE26+BG26+BI26)>0, "YES", "NO") -> YES | BE26: 1 | BF26: КАМАЗ H190606 (ТШО 117024) | BG26: 1 | BH26: H 190606 | BI26: 0 | BK26: TFM/АРП | BL26: Self-propelled motorized (HDV/HDE) - Wheeled | BM26: =VLOOKUP(BL26,'directory all'!C:D,2,) -> Mileage, engine hours, GPS | BN26: Dump truck | BO26: Shared with conditions | BQ26: 25500 | BR26: N/A | BS26: N/A | BT26: N/A | BU26: N/A | BV26: N/A | BW26: N/A | BX26: N/A | BY26: TCO SCM Logistics | BZ26: 200-4401 | CA26: mssls@tengizchevroil.com | CB26: YES | CC26: 18.279 | CD26: 2.359 | CE26: Seasonal (SGP TA) | CG26: Maintenance: Assylbek Amangaliyev / Yerkin Dauletov
A27: 117025 | B27: Sent to BP | C27: H192506 | D27: TRUCK HD HOOK LOADER KENWORTH T800 | E27: N-COCR | F27: HDV Heavy Duty Vehicle | G27: Tengiz | H27: 1NKDX4TX1HR166014 | I27: 1NKDX4TX1HR166014 | J27: 9601120346 | K27: =IFERROR(VLOOKUP(J27,'CC directory'!A:B,2,),"") -> ACTIVE | L27: =IFERROR(VLOOKUP(J27,'CC directory'!A:D,4,),"") -> 200 | M27: =VLOOKUP(J27,'CC directory'!A:I,9,) -> SpecAccum-Drilling Support Srv | N27: =IFERROR(VLOOKUP(J27,'CC directory'!A:C,3,),"") -> Operations | O27: =IFERROR(VLOOKUP(J27,'CC directory'!A:F,6,),"") -> 203 | P27: =IFERROR(VLOOKUP(J27,'CC directory'!A:E,5,),"") -> Drilling | Q27: =IFERROR(VLOOKUP(J27,'CC directory'!A:H,8,),"") -> 500 | R27: =IFERROR(VLOOKUP(J27,'CC directory'!A:G,7,),"") -> Drilling | S27: Drilling | T27: SpecAccum-Drilling Support Srv | U27: 1463 | V27: Tengiz Fleet | Z27: Non-Critical | AA27: Kenworth | AB27: T800 | AC27: KZT | AD27: 79593919 | AE27: 2016 | AF27: 6 | AH27: 79939873 | AI27: 43105 | AJ27: ED00015957 | AK27: 43051 | AL27: 15 | AM27: 43225 | AO27: 50 | AP27: 50 | AR27: 315/80 R22.5 | AS27: 315/80 R22.5 | AT27: TRKHUI002 | AU27: 253584 | AV27: 2027 | AW27: 2032 | AY27: NO | AZ27: 1669 | BD27: =IF((BE27+BG27+BI27)>0, "YES", "NO") -> YES | BE27: 0 | BG27: 1 | BH27: H 192506 | BI27: 0 | BK27: Unassigned | BL27: Self-propelled motorized (HDV/HDE) - Wheeled | BM27: =VLOOKUP(BL27,'directory all'!C:D,2,) -> Mileage, engine hours, GPS | BN27: Hook loader truck | BO27: Shared with conditions | BP27: Wells primary use | BQ27: 33309 | BR27: 14 | BS27: N/A | BT27: N/A | BU27: N/A | BV27: N/A | BW27: N/A | BX27: N/A | BY27: AGI | BZ27: 933-4124 | CA27: jr-ops-mgr@arctic-group.com | CB27: YES | CD27: 12 | CG27: Drilling: Kyle Harrelson / Joseph Bothner
A28: 117026 | B28: Sent to BP | C28: H205106 | D28: TRUCK HD HOOK LOADER KENWORTH T800 | E28: N-COCR | F28: HDV Heavy Duty Vehicle | G28: Tengiz | H28: 1NKDX4TX3HR166015 | I28: 1NKDX4TX3HR166015 | J28: 9601120346 | K28: =IFERROR(VLOOKUP(J28,'CC directory'!A:B,2,),"") -> ACTIVE | L28: =IFERROR(VLOOKUP(J28,'CC directory'!A:D,4,),"") -> 200 | M28: =VLOOKUP(J28,'CC directory'!A:I,9,) -> SpecAccum-Drilling Support Srv | N28: =IFERROR(VLOOKUP(J28,'CC directory'!A:C,3,),"") -> Operations | O28: =IFERROR(VLOOKUP(J28,'CC directory'!A:F,6,),"") -> 203 | P28: =IFERROR(VLOOKUP(J28,'CC directory'!A:E,5,),"") -> Drilling | Q28: =IFERROR(VLOOKUP(J28,'CC directory'!A:H,8,),"") -> 500 | R28: =IFERROR(VLOOKUP(J28,'CC directory'!A:G,7,),"") -> Drilling | S28: Drilling | T28: SpecAccum-Drilling Support Srv | U28: 1464 | V28: Tengiz Fleet | Z28: Non-Critical | AA28: Kenworth | AB28: T800 | AC28: KZT | AD28: 79593919 | AE28: 2016 | AF28: 6 | AH28: 79939874 | AI28: 43105 | AJ28: ED00015958 | AK28: 43051 | AL28: 15 | AM28: 43225 | AO28: 0 | AP28: 0 | AR28: 315/80 R22.5 | AS28: 315/80 R22.5 | AT28: TRKHUI002 | AU28: 253584 | AV28: 2027 | AW28: 2032 | AY28: NO | AZ28: 1670 | BD28: =IF((BE28+BG28+BI28)>0, "YES", "NO") -> YES | BE28: 0 | BG28: 1 | BH28: H 205106 | BI28: 0 | BK28: Unassigned | BL28: Self-propelled motorized (HDV/HDE) - Wheeled | BM28: =VLOOKUP(BL28,'directory all'!C:D,2,) -> Mileage, engine hours, GPS | BN28: Hook loader truck | BO28: Shared with conditions | BP28: Wells primary use | BQ28: 33309 | BR28: 14 | BS28: N/A | BT28: N/A | BU28: N/A | BV28: N/A | BW28: N/A | BX28: N/A | BY28: AGI | BZ28: 933-4124 | CA28: jr-ops-mgr@arctic-group.com | CB28: YES | CD28: 12 | CG28: Drilling: Kyle Harrelson / Joseph Bothner
A29: 117027 | B29: Sent to BP | C29: H205206 | D29: TRUCK HD HOOK LOADER KENWORTH T800 | E29: N-COCR | F29: HDV Heavy Duty Vehicle | G29: Tengiz | H29: 1NKDX4TX5HR166016 | I29: 1NKDX4TX5HR166016 | J29: 9601120346 | K29: =IFERROR(VLOOKUP(J29,'CC directory'!A:B,2,),"") -> ACTIVE | L29: =IFERROR(VLOOKUP(J29,'CC directory'!A:D,4,),"") -> 200 | M29: =VLOOKUP(J29,'CC directory'!A:I,9,) -> SpecAccum-Drilling Support Srv | N29: =IFERROR(VLOOKUP(J29,'CC directory'!A:C,3,),"") -> Operations | O29: =IFERROR(VLOOKUP(J29,'CC directory'!A:F,6,),"") -> 203 | P29: =IFERROR(VLOOKUP(J29,'CC directory'!A:E,5,),"") -> Drilling | Q29: =IFERROR(VLOOKUP(J29,'CC directory'!A:H,8,),"") -> 500 | R29: =IFERROR(VLOOKUP(J29,'CC directory'!A:G,7,),"") -> Drilling | S29: Drilling | T29: SpecAccum-Drilling Support Srv | U29: 1465 | V29: Tengiz Fleet | Z29: Non-Critical | AA29: Kenworth | AB29: T800 | AC29: KZT | AD29: 79593919 | AE29: 2016 | AF29: 6 | AH29: 79939382 | AI29: 43105 | AJ29: ED00015959 | AK29: 43051 | AL29: 15 | AM29: 43225 | AO29: 0 | AP29: 0 | AR29: 315/80 R22.5 | AS29: 315/80 R22.5 | AT29: TRKHUI002 | AU29: 253584 | AV29: 2027 | AW29: 2032 | AY29: NO | AZ29: 1671 | BD29: =IF((BE29+BG29+BI29)>0, "YES", "NO") -> YES | BE29: 0 | BG29: 1 | BH29: H 205206 | BI29: 0 | BK29: Unassigned | BL29: Self-propelled motorized (HDV/HDE) - Wheeled | BM29: =VLOOKUP(BL29,'directory all'!C:D,2,) -> Mileage, engine hours, GPS | BN29: Hook loader truck | BO29: Shared with conditions | BP29: Wells primary use | BQ29: 33309 | BR29: N/A | BS29: N/A | BT29: N/A | BU29: N/A | BV29: N/A | BW29: N/A | BX29: N/A | BY29: AGI | BZ29: 933-4124 | CA29: jr-ops-mgr@arctic-group.com | CB29: YES | CD29: 12 | CG29: Drilling: Kyle Harrelson / Joseph Bothner
A30: 117028 | B30: Sent to BP | C30: H205506 | D30: TRUCK HD HOOK LOADER KENWORTH T800 | E30: N-COCR | F30: HDV Heavy Duty Vehicle | G30: Tengiz | H30: 1NKDX4TX7HR166017 | I30: 1NKDX4TX7HR166017 | J30: 9601120346 | K30: =IFERROR(VLOOKUP(J30,'CC directory'!A:B,2,),"") -> ACTIVE | L30: =IFERROR(VLOOKUP(J30,'CC directory'!A:D,4,),"") -> 200 | M30: =VLOOKUP(J30,'CC directory'!A:I,9,) -> SpecAccum-Drilling Support Srv | N30: =IFERROR(VLOOKUP(J30,'CC directory'!A:C,3,),"") -> Operations | O30: =IFERROR(VLOOKUP(J30,'CC directory'!A:F,6,),"") -> 203 | P30: =IFERROR(VLOOKUP(J30,'CC directory'!A:E,5,),"") -> Drilling | Q30: =IFERROR(VLOOKUP(J30,'CC directory'!A:H,8,),"") -> 500 | R30: =IFERROR(VLOOKUP(J30,'CC directory'!A:G,7,),"") -> Drilling | S30: Drilling | T30: SpecAccum-Drilling Support Srv | U30: 1466 | V30: Tengiz Fleet | Z30: Non-Critical | AA30: Kenworth | AB30: T800 | AC30: KZT | AD30: 79593919 | AE30: 2016 | AF30: 6 | AH30: 79939381 | AI30: 43105 | AJ30: ED00015962 | AK30: 43051 | AL30: 15 | AM30: 43225 | AO30: 0 | AP30: 0 | AR30: 315/80 R22.5 | AS30: 315/80 R22.5 | AT30: TRKHUI002 | AU30: 253584 | AV30: 2027 | AW30: 2032 | AY30: NO | AZ30: 1672 | BD30: =IF((BE30+BG30+BI30)>0, "YES", "NO") -> YES | BE30: 0 | BG30: 1 | BH30: H 205506 | BI30: 0 | BK30: Unassigned | BL30: Self-propelled motorized (HDV/HDE) - Wheeled | BM30: =VLOOKUP(BL30,'directory all'!C:D,2,) -> Mileage, engine hours, GPS | BN30: Hook loader truck | BO30: Shared with conditions | BP30: Wells primary use | BQ30: 30000 | BR30: 15 | BS30: N/A | BT30: N/A | BU30: N/A | BV30: N/A | BW30: N/A | BX30: N/A | BY30: AGI | BZ30: 933-4124 | CA30: jr-ops-mgr@arctic-group.com | CB30: YES | CD30: 12 | CG30: Drilling: Kyle Harrelson / Joseph Bothner
A31: 117029 | B31: Sent to BP | C31: H205406 | D31: TRUCK HD HOOK LOADER KENWORTH T800 | E31: N-COCR | F31: HDV Heavy Duty Vehicle | G31: Tengiz | H31: 1NKDX4TX9HR166018 | I31: 1NKDX4TX9HR166018 | J31: 9601120346 | K31: =IFERROR(VLOOKUP(J31,'CC directory'!A:B,2,),"") -> ACTIVE | L31: =IFERROR(VLOOKUP(J31,'CC directory'!A:D,4,),"") -> 200 | M31: =VLOOKUP(J31,'CC directory'!A:I,9,) -> SpecAccum-Drilling Support Srv | N31: =IFERROR(VLOOKUP(J31,'CC directory'!A:C,3,),"") -> Operations | O31: =IFERROR(VLOOKUP(J31,'CC directory'!A:F,6,),"") -> 203 | P31: =IFERROR(VLOOKUP(J31,'CC directory'!A:E,5,),"") -> Drilling | Q31: =IFERROR(VLOOKUP(J31,'CC directory'!A:H,8,),"") -> 500 | R31: =IFERROR(VLOOKUP(J31,'CC directory'!A:G,7,),"") -> Drilling | S31: Drilling | T31: SpecAccum-Drilling Support Srv | U31: 1467 | V31: Tengiz Fleet | Z31: Non-Critical | AA31: Kenworth | AB31: T800 | AC31: KZT | AD31: 79593919 | AE31: 2016 | AF31: 6 | AH31: 79940351 | AI31: 43105 | AJ31: ED00015961 | AK31: 43051 | AL31: 15 | AM31: 43225 | AO31: 0 | AP31: 0 | AR31: 315/80 R22.5 | AS31: 315/80 R22.5 | AT31: TRKHUI002 | AU31: 253584 | AV31: 2027 | AW31: 2032 | AY31: NO | AZ31: 1673 | BD31: =IF((BE31+BG31+BI31)>0, "YES", "NO") -> YES | BE31: 0 | BG31: 1 | BH31: H 205406 | BI31: 0 | BK31: Unassigned | BL31: Self-propelled motorized (HDV/HDE) - Wheeled | BM31: =VLOOKUP(BL31,'directory all'!C:D,2,) -> Mileage, engine hours, GPS | BN31: Hook loader truck | BO31: Shared with conditions | BP31: Wells primary use | BQ31: 33309 | BR31: 14 | BS31: N/A | BT31: N/A | BU31: N/A | BV31: N/A | BW31: N/A | BX31: N/A | BY31: AGI | BZ31: 933-4124 | CA31: jr-ops-mgr@arctic-group.com | CB31: YES | CD31: 12 | CG31: Drilling: Kyle Harrelson / Joseph Bothner
A32: 117030 | B32: Sent to BP | C32: H205306 | D32: TRUCK HD HOOK LOADER KENWORTH T800 | E32: N-COCR | F32: HDV Heavy Duty Vehicle | G32: Tengiz | H32: 1NKDX4TX0HR166019 | I32: 1NKDX4TX0HR166019 | J32: 9601120346 | K32: =IFERROR(VLOOKUP(J32,'CC directory'!A:B,2,),"") -> ACTIVE | L32: =IFERROR(VLOOKUP(J32,'CC directory'!A:D,4,),"") -> 200 | M32: =VLOOKUP(J32,'CC directory'!A:I,9,) -> SpecAccum-Drilling Support Srv | N32: =IFERROR(VLOOKUP(J32,'CC directory'!A:C,3,),"") -> Operations | O32: =IFERROR(VLOOKUP(J32,'CC directory'!A:F,6,),"") -> 203 | P32: =IFERROR(VLOOKUP(J32,'CC directory'!A:E,5,),"") -> Drilling | Q32: =IFERROR(VLOOKUP(J32,'CC directory'!A:H,8,),"") -> 500 | R32: =IFERROR(VLOOKUP(J32,'CC directory'!A:G,7,),"") -> Drilling | S32: Drilling | T32: SpecAccum-Drilling Support Srv | U32: 1468 | V32: Tengiz Fleet | Z32: Non-Critical | AA32: Kenworth | AB32: T800 | AC32: KZT | AD32: 79593919 | AE32: 2016 | AF32: 6 | AH32: 79940350 | AI32: 43105 | AJ32: ED00015960 | AK32: 43051 | AL32: 15 | AM32: 43225 | AO32: 0 | AP32: 0 | AR32: 315/80 R22.5 | AS32: 315/80 R22.5 | AT32: TRKHUI002 | AU32: 253584 | AV32: 2027 | AW32: 2032 | AY32: NO | AZ32: 1674 | BD32: =IF((BE32+BG32+BI32)>0, "YES", "NO") -> YES | BE32: 0 | BG32: 1 | BH32: H 205306 | BI32: 0 | BK32: Unassigned | BL32: Self-propelled motorized (HDV/HDE) - Wheeled | BM32: =VLOOKUP(BL32,'directory all'!C:D,2,) -> Mileage, engine hours, GPS | BN32: Hook loader truck | BO32: Shared with conditions | BP32: Wells primary use | BQ32: 30000 | BR32: 15 | BS32: N/A | BT32: N/A | BU32: N/A | BV32: N/A | BW32: N/A | BX32: N/A | BY32: AGI | BZ32: 933-4124 | CA32: jr-ops-mgr@arctic-group.com | CB32: YES | CD32: 12 | CG32: Drilling: Kyle Harrelson / Joseph Bothner
A33: 117032 | B33: Active | C33: H550506 | D33: TRUCK HD MAN TGX 18.400 | E33: TMF1 | F33: HDV Heavy Duty Vehicle | G33: Tengiz | H33: WMA06KZZ2RM941681 | I33: WMA06KZZ2RM941681 | J33: 20850 | K33: =IFERROR(VLOOKUP(J33,'CC directory'!A:B,2,),"") -> ACTIVE | L33: =IFERROR(VLOOKUP(J33,'CC directory'!A:D,4,),"") -> 200 | M33: =VLOOKUP(J33,'CC directory'!A:I,9,) -> Maintenance Shared Services | N33: =IFERROR(VLOOKUP(J33,'CC directory'!A:C,3,),"") -> Operations | O33: =IFERROR(VLOOKUP(J33,'CC directory'!A:F,6,),"") -> 207 | P33: =IFERROR(VLOOKUP(J33,'CC directory'!A:E,5,),"") -> Production Operations | Q33: =IFERROR(VLOOKUP(J33,'CC directory'!A:H,8,),"") -> 705 | R33: =IFERROR(VLOOKUP(J33,'CC directory'!A:G,7,),"") -> Maintenance | S33: Maintenance | T33: Maintenance Shared Services | U33: 2199 | V33: Tengiz Fleet | Y33: 45356 | Z33: Critical | AA33: MAN | AB33: TGX 18.400 4x2 BL SA | AC33: KZT | AD33: 78585000 | AE33: 2023 | AH33: 50568330706834 | AI33: 45416 | AJ33: EW00014812 | AK33: 45356 | AL33: 10 | AM33: 45356 | AT33: TRKHUI004 | AU33: 0060071487-001 | AV33: 2034 | AZ33: 2409 | BC33: 16.05.24-pmlt: Issued from Registration Dept. to 20850 - MSS according to the acceptance act as of 15.05.24 and the e-mail from Registration Department as of 16.05.24. (Inbox - CC Change) | BD33: =IF((BE33+BG33+BI33)>0, "YES", "NO") -> YES | BE33: 1 | BF33: MAN H550506 (ТШО 117032) | BG33: 1 | BH33: H 550506 | BI33: 0 | BK33: TFM/АРП | BL33: Self-propelled motorized (HDV/HDE) - Wheeled | BM33: =VLOOKUP(BL33,'directory all'!C:D,2,) -> Mileage, engine hours, GPS | BN33: HD truck (tractor) | BO33: Shared with conditions | BQ33: N/A | BR33: N/A | BS33: N/A | BT33: N/A | BU33: N/A | BV33: N/A | BW33: N/A | BX33: N/A | BY33: TCO SCM Logistics | BZ33: 200-4401 | CA33: mssls@tengizchevroil.com | CB33: YES | CC33: 18.279 | CD33: 2.359 | CG33: Maintenance: Assylbek Amangaliyev / Yerkin Dauletov
A34: 117033 | B34: Active | C34: H550206 | D34: TRUCK HD MAN TGX 41.640 | E34: N-COCR | F34: HDV Heavy Duty Vehicle | G34: Tengiz | H34: WMA86KZZ8RL078927 | J34: 20850 | K34: =IFERROR(VLOOKUP(J34,'CC directory'!A:B,2,),"") -> ACTIVE | L34: =IFERROR(VLOOKUP(J34,'CC directory'!A:D,4,),"") -> 200 | M34: =VLOOKUP(J34,'CC directory'!A:I,9,) -> Maintenance Shared Services | N34: =IFERROR(VLOOKUP(J34,'CC directory'!A:C,3,),"") -> Operations | O34: =IFERROR(VLOOKUP(J34,'CC directory'!A:F,6,),"") -> 207 | P34: =IFERROR(VLOOKUP(J34,'CC directory'!A:E,5,),"") -> Production Operations | Q34: =IFERROR(VLOOKUP(J34,'CC directory'!A:H,8,),"") -> 705 | R34: =IFERROR(VLOOKUP(J34,'CC directory'!A:G,7,),"") -> Maintenance | S34: Maintenance | T34: Maintenance Shared Services | U34: 2202 | V34: Tengiz Fleet | Y34: 45386 | Z34: Non-Critical | AA34: MAN | AB34: TGX 41.640 8x 4/4 BB SA | AC34: KZT | AD34: 232000000 | AE34: 2023 | AF34: 0 | AH34: 56567081736711 | AI34: 45425 | AJ34: EW00014824 | AL34: 10 | AM34: 45386 | AR34: 385/80 R22.5 | AS34: 315/80 R22.5 | AT34: TRKHUI004 | AU34: 0060074231-001 | AW34: 2034 | AZ34: 2412 | BA34: INLINE 6 | BB34: MAN TipMatic | BC34: 08.10.24-xeza: Issued to 20850-MSS according to the acceptance act as of 07.10.24 and the e-mail from Reg.Dept (Inbox-CC Change) | BD34: =IF((BE34+BG34+BI34)>0, "YES", "NO") -> YES | BE34: 1 | BF34: MAN H550206 (ТШО 117033) | BG34: 0 | BI34: 0 | BK34: Plant SGP/Завод ЗВП | BL34: Self-propelled motorized (HDV/HDE) - Wheeled | BM34: =VLOOKUP(BL34,'directory all'!C:D,2,) -> Mileage, engine hours, GPS | BN34: HD truck (tractor) | BO34: Shared with conditions | BQ34: N/A | BR34: N/A | BS34: N/A | BT34: N/A | BU34: N/A | BV34: N/A | BW34: N/A | BX34: N/A | BY34: TCO MSS BP | BZ34: 200-4401 | CA34: mssls@tengizchevroil.com | CB34: YES | CC34: 18.279 | CD34: 2.359 | CG34: Maintenance: Assylbek Amangaliyev / Yerkin Dauletov
A35: 117034 | B35: Active | C35: H519206 | D35: TRUCK HD KAMAZ 54901-70014СА | E35: TMF1 | F35: HDV Heavy Duty Vehicle | G35: Tengiz | H35: XTC549015Р2592858 | I35: XTC549015Р2592858 | J35: 13780 | K35: =IFERROR(VLOOKUP(J35,'CC directory'!A:B,2,),"") -> ACTIVE | L35: =IFERROR(VLOOKUP(J35,'CC directory'!A:D,4,),"") -> 200 | M35: =VLOOKUP(J35,'CC directory'!A:I,9,) -> Heavy Equipment Operations | N35: =IFERROR(VLOOKUP(J35,'CC directory'!A:C,3,),"") -> Operations | O35: =IFERROR(VLOOKUP(J35,'CC directory'!A:F,6,),"") -> 209 | P35: =IFERROR(VLOOKUP(J35,'CC directory'!A:E,5,),"") -> Supply Chain Management | Q35: =IFERROR(VLOOKUP(J35,'CC directory'!A:H,8,),"") -> 322 | R35: =IFERROR(VLOOKUP(J35,'CC directory'!A:G,7,),"") -> Tengiz Ground Transportation | S35: SCM Logistics | T35: Heavy Equipment Operations | U35: 2210 | V35: Tengiz Fleet | Y35: 45531 | Z35: Critical | AA35: KAMAZ | AB35: 54901-70014СА | AC35: KZT | AD35: 38500000 | AE35: 2023 | AH35: 910.10-1002 | AI35: 45545 | AJ35: ED99999859 | AK35: 45517 | AL35: 10 | AM35: 45529 | AO35: 1680 | AP35: 1680 | AR35: 315/70 | AS35: 315/70 | AT35: HDT 003 | AU35: 61028786 | AV35: 2034 | AY35: YES | AZ35: 2420 | BA35: КАМАЗ-910.52-460 (Евро-5) | BC35: 26.11.24-sutz: The new truck was issued to CC: 13780 - Heavy Equipment Operations from CC: 13780 - Registration Department, according to the act of acceptance and e-mail from Registration Department as of 26.11.2024 with approval by Fleet maintenance and inspection Team Lead. (Inbox - CC change) Data was added in 12-2024 Assigned Equipments Report. 11.09.24-sutz: Technical passport with license plate number for truck was received, according to the e-mail from Registration Dep.as of 11.09.2024. (Inbox-Registration Dep) | BD35: =IF((BE35+BG35+BI35)>0, "YES", "NO") -> YES | BE35: 1 | BF35: KAMAZ H519206 (ТШО 117034) | BG35: 1 | BH35: H 519206 | BI35: 0 | BK35: Industrial Base | BL35: Self-propelled motorized (HDV/HDE) - Wheeled | BM35: =VLOOKUP(BL35,'directory all'!C:D,2,) -> Mileage, engine hours, GPS | BN35: HD truck (tractor) | BO35: Shared without conditions | BQ35: 10350 | BR35: N/A | BS35: N/A | BT35: N/A | BU35: N/A | BV35: N/A | BW35: N/A | BX35: N/A | BY35: TCO SCM Logistics | BZ35: 4559 | CB35: YES | CC35: 40 | CG35: SCM Logistics: Yerbol Nauryzbay / Yerlan Yeshmagambetov
A36: 117035 | B36: Active | C36: H499406 | D36: TRUCK HD MAN TGS 26.440 | E36: TMF1 | F36: HDV Heavy Duty Vehicle | G36: Tengiz | H36: WMA30KZZ4RP284539 | I36: WMA30KZZ4RP284539 | J36: 13780 | K36: =IFERROR(VLOOKUP(J36,'CC directory'!A:B,2,),"") -> ACTIVE | L36: =IFERROR(VLOOKUP(J36,'CC directory'!A:D,4,),"") -> 200 | M36: =VLOOKUP(J36,'CC directory'!A:I,9,) -> Heavy Equipment Operations | N36: =IFERROR(VLOOKUP(J36,'CC directory'!A:C,3,),"") -> Operations | O36: =IFERROR(VLOOKUP(J36,'CC directory'!A:F,6,),"") -> 209 | P36: =IFERROR(VLOOKUP(J36,'CC directory'!A:E,5,),"") -> Supply Chain Management | Q36: =IFERROR(VLOOKUP(J36,'CC directory'!A:H,8,),"") -> 322 | R36: =IFERROR(VLOOKUP(J36,'CC directory'!A:G,7,),"") -> Tengiz Ground Transportation | S36: SCM Logistics | T36: Heavy Equipment Operations | U36: 2212 | V36: Tengiz Fleet | Z36: Non-Critical | AA36: MAN | AB36: MAN TGS 26.440 6x4 BL SA | AC36: KZT | AD36: 90000000 | AE36: 2024 | AH36: 50570020356999 | AI36: 45604 | AJ36: ED99889812 | AK36: 45573 | AL36: 10 | AM36: 45578 | AO36: 8740 | AP36: 8740 | AR36: 315/80 | AS36: 315/80 | AT36: HDT 003 | AU36: 0060910380 | AV36: 2034 | AW36: 2034 | AY36: YES | AZ36: 2422 | BC36: 24.11.24-sutz: The new truck was issued to CC: 13780 - Heavy Equipment Operations from CC: 13780 - Registration Department, according to the act of acceptance and e-mail from Registration Department as of 22.11.2024 with approval by Fleet maintenance and inspection Team Lead. (Inbox - CC change) Data was added in 12-2024 Assigned Equipments Report. 10.11.24-sutz: License plate and technical passport number was accepted for the equipment, according to the e-mail from the Registration department as of 09.11.24. (Inbox-Registration Dept) | BD36: =IF((BE36+BG36+BI36)>0, "YES", "NO") -> YES | BE36: 1 | BF36: MAN (ТШО 117035) | BG36: 1 | BH36: H 499406 | BI36: 0 | BK36: Industrial Base | BL36: Self-propelled motorized (HDV/HDE) - Wheeled | BM36: =VLOOKUP(BL36,'directory all'!C:D,2,) -> Mileage, engine hours, GPS | BN36: HD truck (tractor) | BO36: Shared without conditions | BQ36: 17000 | BR36: N/A | BS36: N/A | BT36: N/A | BU36: N/A | BV36: N/A | BW36: N/A | BX36: N/A | BY36: TCO SCM Logistics | BZ36: 3336 / 7068 | CB36: YES | CC36: 40 | CD36: 1.5 | CG36: SCM Logistics: Yerbol Nauryzbay / Yerlan Yeshmagambetov
A37: 123021 | B37: Active | C37: H726309 | D37: TRUCK DUMP KAMAZ 8X4 65201-011 | E37: TMF1 | F37: HDV Heavy Duty Vehicle | G37: Tengiz | H37: XTC652010C1250926 | I37: XTC652010C1250926 | J37: 13780 | K37: =IFERROR(VLOOKUP(J37,'CC directory'!A:B,2,),"") -> ACTIVE | L37: =IFERROR(VLOOKUP(J37,'CC directory'!A:D,4,),"") -> 200 | M37: =VLOOKUP(J37,'CC directory'!A:I,9,) -> Heavy Equipment Operations | N37: =IFERROR(VLOOKUP(J37,'CC directory'!A:C,3,),"") -> Operations | O37: =IFERROR(VLOOKUP(J37,'CC directory'!A:F,6,),"") -> 209 | P37: =IFERROR(VLOOKUP(J37,'CC directory'!A:E,5,),"") -> Supply Chain Management | Q37: =IFERROR(VLOOKUP(J37,'CC directory'!A:H,8,),"") -> 322 | R37: =IFERROR(VLOOKUP(J37,'CC directory'!A:G,7,),"") -> Tengiz Ground Transportation | S37: SCM Logistics | T37: Heavy Equipment Operations | U37: 676 | V37: Tengiz fleet | Z37: Non-Critical | AA37: KAMAZ | AB37: 65201-011 | AC37: KZT | AD37: 12366071 | AE37: 2012 | AF37: 11 | AH37: C2626867 | AJ37: ED00012798 | AK37: 41191 | AL37: 15 | AM37: 41206 | AO37: 57244 | AP37: 57244 | AR37: 315/80R22.5 | AS37: 315/80R22.5 | AT37: HDT 002 | AU37: 176556 | AV37: 2024 | AW37: 2027 | AZ37: 678 | BA37: V-8 | BB37: 16S151 | BD37: =IF((BE37+BG37+BI37)>0, "YES", "NO") -> YES | BE37: 1 | BF37: КамАЗ H726309 (ТШО 123021) | BG37: 1 | BH37: H 726309 | BI37: 0 | BK37: Industrial Base | BL37: Self-propelled motorized (HDV/HDE) - Wheeled | BM37: =VLOOKUP(BL37,'directory all'!C:D,2,) -> Mileage, engine hours, GPS | BN37: Dump truck | BO37: Shared without conditions | BQ37: 26000 | BR37: N/A | BS37: N/A | BT37: N/A | BU37: N/A | BV37: N/A | BW37: N/A | BX37: N/A | BY37: TCO SCM Logistics | BZ37: 7667 | CB37: YES | CC37: 40 | CG37: SCM Logistics: Yerbol Nauryzbay / Yerlan Yeshmagambetov
A38: 123022 | B38: Active | C38: H726307 | D38: TRUCK DUMP KAMAZ 8X4 65201-011 | E38: TMF1 | F38: HDV Heavy Duty Vehicle | G38: Tengiz | H38: XTC652010C1250938 | I38: XTC652010C1250938 | J38: 13780 | K38: =IFERROR(VLOOKUP(J38,'CC directory'!A:B,2,),"") -> ACTIVE | L38: =IFERROR(VLOOKUP(J38,'CC directory'!A:D,4,),"") -> 200 | M38: =VLOOKUP(J38,'CC directory'!A:I,9,) -> Heavy Equipment Operations | N38: =IFERROR(VLOOKUP(J38,'CC directory'!A:C,3,),"") -> Operations | O38: =IFERROR(VLOOKUP(J38,'CC directory'!A:F,6,),"") -> 209 | P38: =IFERROR(VLOOKUP(J38,'CC directory'!A:E,5,),"") -> Supply Chain Management | Q38: =IFERROR(VLOOKUP(J38,'CC directory'!A:H,8,),"") -> 322 | R38: =IFERROR(VLOOKUP(J38,'CC directory'!A:G,7,),"") -> Tengiz Ground Transportation | S38: SCM Logistics | T38: Heavy Equipment Operations | U38: 677 | V38: Tengiz fleet | Z38: Non-Critical | AA38: KAMAZ | AB38: 65201-011 | AC38: KZT | AD38: 12366071 | AE38: 2012 | AF38: 11 | AH38: C2669266 | AJ38: ED00012797 | AK38: 41191 | AL38: 15 | AM38: 41206 | AO38: 48664 | AP38: 48664 | AR38: 315/80R22.5 | AS38: 315/80R22.5 | AT38: HDT 002 | AU38: 176556 | AV38: 2024 | AW38: 2027 | AZ38: 679 | BA38: V-8 | BB38: 16S151 | BD38: =IF((BE38+BG38+BI38)>0, "YES", "NO") -> YES | BE38: 1 | BF38: КамАЗ H726307 (ТШО 123022) | BG38: 1 | BH38: H 726307 | BI38: 0 | BK38: Industrial Base | BL38: Self-propelled motorized (HDV/HDE) - Wheeled | BM38: =VLOOKUP(BL38,'directory all'!C:D,2,) -> Mileage, engine hours, GPS | BN38: Dump truck | BO38: Shared without conditions | BQ38: 26000 | BR38: N/A | BS38: N/A | BT38: N/A | BU38: N/A | BV38: N/A | BW38: N/A | BX38: N/A | BY38: TCO SCM Logistics | BZ38: 7240 | CB38: YES | CC38: 40 | CG38: SCM Logistics: Yerbol Nauryzbay / Yerlan Yeshmagambetov
A39: 123023 | B39: Active | C39: H550906 | D39: TRUCK DUMP KAMAZ 65201-7080-49 | E39: TMF1 | F39: HDV Heavy Duty Vehicle | G39: Tengiz | H39: XTC652015R2602350 | I39: XTC652015R2602350 | J39: 20850 | K39: =IFERROR(VLOOKUP(J39,'CC directory'!A:B,2,),"") -> ACTIVE | L39: =IFERROR(VLOOKUP(J39,'CC directory'!A:D,4,),"") -> 200 | M39: =VLOOKUP(J39,'CC directory'!A:I,9,) -> Maintenance Shared Services | N39: =IFERROR(VLOOKUP(J39,'CC directory'!A:C,3,),"") -> Operations | O39: =IFERROR(VLOOKUP(J39,'CC directory'!A:F,6,),"") -> 207 | P39: =IFERROR(VLOOKUP(J39,'CC directory'!A:E,5,),"") -> Production Operations | Q39: =IFERROR(VLOOKUP(J39,'CC directory'!A:H,8,),"") -> 705 | R39: =IFERROR(VLOOKUP(J39,'CC directory'!A:G,7,),"") -> Maintenance | S39: Maintenance | T39: Heavy Equipment Operations | U39: 2203 | V39: Tengiz Fleet | Y39: 45410 | Z39: Non-Critical | AA39: KAMAZ | AB39: 65201-7080-49 | AE39: 2024 | AI39: 45429 | AJ39: EW00014837 | AK39: 45400 | AL39: 10 | AM39: 45410 | AR39: 315/80 | AS39: 315/80 | AT39: HDT 003 | AU39: 60910380 | AV39: 2034 | AZ39: 2413 | BA39: KAMAZ-689.510-400 | BB39: ZF KAMA 1825TO | BC39: 19.07.24-pmlt: Issued from Registration Department to 13780 - Heavy Equipment Operations according to the acceptance act as of 19.07.24 and the e-mail form Reg.Dept as of 19.07.24 (Inbox- CC Change) | BD39: =IF((BE39+BG39+BI39)>0, "YES", "NO") -> YES | BE39: 1 | BF39: KAMAZ H550906 (ТШО 123023) | BG39: 1 | BH39: H 550906 | BI39: 0 | BK39: Plant KTL/Завод КТЛ | BL39: Self-propelled motorized (HDV/HDE) - Wheeled | BM39: =VLOOKUP(BL39,'directory all'!C:D,2,) -> Mileage, engine hours, GPS | BN39: Dump truck | BO39: Shared with conditions | BQ39: 25000 | BR39: N/A | BS39: N/A | BT39: N/A | BU39: N/A | BV39: N/A | BW39: N/A | BX39: N/A | BY39: TCO SCM Logistics | BZ39: 200-4401 | CA39: mssls@tengizchevroil.com | CB39: YES | CC39: 42.294 | CD39: 2.359 | CG39: Maintenance: Assylbek Amangaliyev / Yerkin Dauletov
A40: 126029 | B40: Active | C40: H190806 | D40: TRUCK HD BOOM FORD CARGO 2533 HR | E40: TMF1 | F40: HDV Heavy Duty Vehicle | G40: Tengiz | H40: NM0LKXTP6LGS91315 | J40: 13780 | K40: =IFERROR(VLOOKUP(J40,'CC directory'!A:B,2,),"") -> ACTIVE | L40: =IFERROR(VLOOKUP(J40,'CC directory'!A:D,4,),"") -> 200 | M40: =VLOOKUP(J40,'CC directory'!A:I,9,) -> Heavy Equipment Operations | N40: =IFERROR(VLOOKUP(J40,'CC directory'!A:C,3,),"") -> Operations | O40: =IFERROR(VLOOKUP(J40,'CC directory'!A:F,6,),"") -> 209 | P40: =IFERROR(VLOOKUP(J40,'CC directory'!A:E,5,),"") -> Supply Chain Management | Q40: =IFERROR(VLOOKUP(J40,'CC directory'!A:H,8,),"") -> 322 | R40: =IFERROR(VLOOKUP(J40,'CC directory'!A:G,7,),"") -> Tengiz Ground Transportation | S40: SCM Logistics | T40: Heavy Equipment Operations | U40: 679 | V40: Tengiz fleet | Z40: Non-Critical | AA40: FORD | AB40: CARGO 2533 HR | AC40: KZT | AD40: 46696482 | AE40: 2016 | AF40: 6 | AH40: GS91315 | AI40: 42798 | AJ40: ED00015858 | AL40: 15 | AM40: 42744 | AO40: 130501 | AP40: 130501 | AR40: 315/80R22,5 | AS40: 315/80R22,5 | AT40: TRKFDBM 001 | AU40: 255301 | AV40: 2029 | AW40: 2032 | AY40: YES | AZ40: 681 | BD40: =IF((BE40+BG40+BI40)>0, "YES", "NO") -> YES | BE40: 1 | BF40: Ford Cargo H190806 (ТШО 126029) | BG40: 1 | BH40: H 190806 | BI40: 0 | BK40: Industrial Base | BL40: Self-propelled motorized (HDV/HDE) - Wheeled | BM40: =VLOOKUP(BL40,'directory all'!C:D,2,) -> Mileage, engine hours, GPS | BN40: Flatbed/boom truck (do not use) | BO40: Shared without conditions | BQ40: 14000 | BR40: N/A | BS40: N/A | BT40: N/A | BU40: N/A | BV40: N/A | BW40: N/A | BX40: N/A | BY40: TCO SCM Logistics | BZ40: 7240 | CB40: YES | CC40: 40 | CG40: SCM Logistics: Yerbol Nauryzbay / Yerlan Yeshmagambetov
A41: 126030 | B41: Active | C41: H315706 | D41: TRUCK HD KAMAZ FLATBED | E41: TMF1 | F41: HDV Heavy Duty Vehicle | G41: Tengiz | H41: XTC430805J1390495 | I41: XTC430805J1390495 | J41: 13780 | K41: =IFERROR(VLOOKUP(J41,'CC directory'!A:B,2,),"") -> ACTIVE | L41: =IFERROR(VLOOKUP(J41,'CC directory'!A:D,4,),"") -> 200 | M41: =VLOOKUP(J41,'CC directory'!A:I,9,) -> Heavy Equipment Operations | N41: =IFERROR(VLOOKUP(J41,'CC directory'!A:C,3,),"") -> Operations | O41: =IFERROR(VLOOKUP(J41,'CC directory'!A:F,6,),"") -> 209 | P41: =IFERROR(VLOOKUP(J41,'CC directory'!A:E,5,),"") -> Supply Chain Management | Q41: =IFERROR(VLOOKUP(J41,'CC directory'!A:H,8,),"") -> 322 | R41: =IFERROR(VLOOKUP(J41,'CC directory'!A:G,7,),"") -> Tengiz Ground Transportation | S41: SCM Logistics | T41: Heavy Equipment Operations | U41: 680 | V41: Tengiz fleet | Z41: Critical | AA41: KAMAZ | AB41: 4308-6063-69 | AC41: KZT | AD41: 72899999 | AE41: 2018 | AF41: 4 | AH41: 86067428 | AI41: 43447 | AJ41: ED00017145 | AK41: 43434 | AL41: 15 | AM41: 43448 | AO41: 134426 | AP41: 134426 | AR41: 245/70 R19,5 | AS41: 245/70 R19,5 | AT41: TRKKAM 013 | AU41: 289934 | AV41: 2028 | AW41: 2033 | AY41: YES | AZ41: 682 | BD41: =IF((BE41+BG41+BI41)>0, "YES", "NO") -> YES | BE41: 1 | BF41: KAMAZ H315706 (ТШО 126030) | BG41: 1 | BH41: H 315706 | BI41: 0 | BK41: Industrial Base | BL41: Self-propelled motorized (HDV/HDE) - Wheeled | BM41: =VLOOKUP(BL41,'directory all'!C:D,2,) -> Mileage, engine hours, GPS | BN41: Flatbed/boom truck (do not use) | BO41: Shared without conditions | BQ41: 5200 | BR41: N/A | BS41: N/A | BT41: N/A | BU41: N/A | BV41: N/A | BW41: N/A | BX41: N/A | BY41: TCO SCM Logistics | BZ41: 4559 | CB41: YES | CC41: 40 | CD41: 1.5 | CG41: SCM Logistics: Yerbol Nauryzbay / Yerlan Yeshmagambetov
A42: 126031 | B42: Active | C42: H512706 | D42: TRUCK HD HINO-700 BOOM PALFINGER | E42: N-COCR | F42: HDV Heavy Duty Vehicle | G42: Tengiz | H42: MX967443FP0021171 | I42: JHDFS1EUU00010095 | J42: 20850 | K42: =IFERROR(VLOOKUP(J42,'CC directory'!A:B,2,),"") -> ACTIVE | L42: =IFERROR(VLOOKUP(J42,'CC directory'!A:D,4,),"") -> 200 | M42: =VLOOKUP(J42,'CC directory'!A:I,9,) -> Maintenance Shared Services | N42: =IFERROR(VLOOKUP(J42,'CC directory'!A:C,3,),"") -> Operations | O42: =IFERROR(VLOOKUP(J42,'CC directory'!A:F,6,),"") -> 207 | P42: =IFERROR(VLOOKUP(J42,'CC directory'!A:E,5,),"") -> Production Operations | Q42: =IFERROR(VLOOKUP(J42,'CC directory'!A:H,8,),"") -> 705 | R42: =IFERROR(VLOOKUP(J42,'CC directory'!A:G,7,),"") -> Maintenance | S42: Maintenance | T42: Maintenance Shared Services | U42: 681 | V42: Tengiz fleet | Z42: Non-Critical | AA42: HINO Motors Kazakhstan | AB42: FS1EUUA-QPR 67443F | AC42: KZT | AD42: 36080000 | AE42: 2023 | AF42: 0 | AH42: 20219 | AI42: 45086 | AJ42: ED00018639 | AK42: 45052 | AL42: 10 | AM42: 45052 | AO42: 0 | AP42: 0 | AR42: 295/80R22,5 | AS42: 295/80R22,5 | AT42: TRKHNBM 001 | AU42: 374749 | AV42: 2033 | AW42: 2033 | AZ42: 683 | BC42: Added License Number. 24.12.2023-sutz: The status was changed to N-COCR as we will not be maintenance further, the reason BP Bisengali Crane will be serviced for repairs, according to an email from Fleet Maintenance and Inspection Coordinator 2 with confirmation from the TCO Transport Team Leader as of 26.11.2023. (Inbox-New equipment 2023) | BD42: =IF((BE42+BG42+BI42)>0, "YES", "NO") -> YES | BE42: 1 | BF42: HINO H512706 (ТШО 126031) | BG42: 1 | BH42: H 512706 | BI42: 0 | BK42: Plant 3GP/Завод ЗТП | BL42: Self-propelled motorized (HDV/HDE) - Wheeled | BM42: =VLOOKUP(BL42,'directory all'!C:D,2,) -> Mileage, engine hours, GPS | BN42: Hook loader truck | BO42: Shared with conditions | BQ42: 6000 | BR42: N/A | BS42: N/A | BT42: N/A | BU42: N/A | BV42: N/A | BW42: N/A | BX42: N/A | BY42: TCO MSS BP | BZ42: 200-3681 | CA42: msslr@tengizchevroil.com | CB42: YES | CC42: 42.294 | CD42: 2.359 | CG42: Maintenance: Assylbek Amangaliyev / Yerkin Dauletov
A43: 126032 | B43: Active | C43: H520406 | D43: TRUCK HD KAMAZ FLATBED | E43: TMF1 | F43: HDV Heavy Duty Vehicle | G43: Tengiz | H43: XTC430805P1498021 | I43: XTC430805P1498021 | J43: 13780 | K43: =IFERROR(VLOOKUP(J43,'CC directory'!A:B,2,),"") -> ACTIVE | L43: =IFERROR(VLOOKUP(J43,'CC directory'!A:D,4,),"") -> 200 | M43: =VLOOKUP(J43,'CC directory'!A:I,9,) -> Heavy Equipment Operations | N43: =IFERROR(VLOOKUP(J43,'CC directory'!A:C,3,),"") -> Operations | O43: =IFERROR(VLOOKUP(J43,'CC directory'!A:F,6,),"") -> 209 | P43: =IFERROR(VLOOKUP(J43,'CC directory'!A:E,5,),"") -> Supply Chain Management | Q43: =IFERROR(VLOOKUP(J43,'CC directory'!A:H,8,),"") -> 322 | R43: =IFERROR(VLOOKUP(J43,'CC directory'!A:G,7,),"") -> Tengiz Ground Transportation | S43: SCM Logistics | T43: Heavy Equipment Operations | U43: 1442 | V43: Tengiz Fleet | Y43: 45172 | Z43: Critical | AA43: KAMAZ | AB43: 4308-6084-69 | AC43: KZT | AD43: 133750000 | AE43: 2023 | AI43: 45180 | AJ43: ED00018755 | AK43: 45169 | AL43: 10 | AM43: 45172 | AO43: 2950 | AT43: TRKKAMFT 002 | AU43: 383361 | AV43: 2033 | AZ43: 1467 | BC43: New Kamaz was added in Fleet Management Tool system. The new equipment was issued from CC 13780 - Registration Department to СС 13780 - Heavy Equipment Operations, according to the acceptance act as of 03.10.2023 and e-mail from Registration Department as of 07.10.2023. (Inbox-CC change). Additional to the fleet. | BD43: =IF((BE43+BG43+BI43)>0, "YES", "NO") -> YES | BE43: 1 | BF43: Камаз H520406 ТШО126032 | BG43: 1 | BH43: H 520406 | BI43: 0 | BK43: Industrial Base | BL43: Self-propelled motorized (HDV/HDE) - Wheeled | BM43: =VLOOKUP(BL43,'directory all'!C:D,2,) -> Mileage, engine hours, GPS | BN43: Flatbed/boom truck (do not use) | BO43: Shared without conditions | BQ43: 5200 | BR43: N/A | BS43: N/A | BT43: N/A | BU43: N/A | BV43: N/A | BW43: N/A | BX43: N/A | BY43: TCO SCM Logistics | BZ43: 4559 / 5113 | CB43: YES | CC43: 40 | CD43: 1.5 | CG43: SCM Logistics: Yerbol Nauryzbay / Yerlan Yeshmagambetov
A44: 126033 | B44: Active | C44: H496006 | D44: TRUCK HD HINO 37630C FLATBED | E44: TMF1 | F44: HDV Heavy Duty Vehicle | G44: Tengiz | H44: MX937630CP0021112 | I44: MX937630CP0021112 | J44: 20850 | K44: =IFERROR(VLOOKUP(J44,'CC directory'!A:B,2,),"") -> ACTIVE | L44: =IFERROR(VLOOKUP(J44,'CC directory'!A:D,4,),"") -> 200 | M44: =VLOOKUP(J44,'CC directory'!A:I,9,) -> Maintenance Shared Services | N44: =IFERROR(VLOOKUP(J44,'CC directory'!A:C,3,),"") -> Operations | O44: =IFERROR(VLOOKUP(J44,'CC directory'!A:F,6,),"") -> 207 | P44: =IFERROR(VLOOKUP(J44,'CC directory'!A:E,5,),"") -> Production Operations | Q44: =IFERROR(VLOOKUP(J44,'CC directory'!A:H,8,),"") -> 705 | R44: =IFERROR(VLOOKUP(J44,'CC directory'!A:G,7,),"") -> Maintenance | S44: Maintenance | T44: Maintenance Shared Services | U44: 1433 | V44: Tengiz Fleet | Y44: 45145 | Z44: Non-Critical | AA44: HINO | AB44: 37630C | AC44: KZT | AD44: 36080000 | AE44: 2023 | AI44: 45212 | AJ44: ED00018788 | AK44: 45145 | AL44: 10 | AM44: 45209 | AT44: TRKHNFL 001 | AU44: 374744 | AV44: 2033 | AZ44: 1458 | BC44: New Hino was added in E-Maint & Fleet Management Tool systems, according to the e-mail from Registration Department as of 10.10.2023 with approval by Fleet maintenance and inspection Team Lead. (Inbox-New equipment 2023) The customer ordered directly, as additional. Assigned to CC 20850 - Maintenance Shared Services. | BD44: =IF((BE44+BG44+BI44)>0, "YES", "NO") -> YES | BE44: 1 | BF44: HINO H496006 ТШО 126033 | BG44: 1 | BH44: H 496006 | BI44: 0 | BK44: Plant KTL/Завод КТЛ | BL44: Self-propelled motorized (HDV/HDE) - Wheeled | BM44: =VLOOKUP(BL44,'directory all'!C:D,2,) -> Mileage, engine hours, GPS | BN44: Flatbed/boom truck (do not use) | BO44: Shared with conditions | BQ44: 13930 | BR44: N/A | BS44: N/A | BT44: N/A | BU44: N/A | BV44: N/A | BW44: N/A | BX44: N/A | BY44: TCO SCM Logistics | BZ44: 200-4401 | CA44: mssls@tengizchevroil.com | CB44: YES | CC44: 42.294 | CD44: 2.359 | CG44: Maintenance: Assylbek Amangaliyev / Yerkin Dauletov
A45: 126034 | B45: Active | C45: H495306 | D45: TRUCK HD HINO 37630C FLATBED | E45: TMF1 | F45: HDV Heavy Duty Vehicle | G45: Tengiz | H45: MX937630CP0021113 | I45: MX937630CP0021113 | J45: 20850 | K45: =IFERROR(VLOOKUP(J45,'CC directory'!A:B,2,),"") -> ACTIVE | L45: =IFERROR(VLOOKUP(J45,'CC directory'!A:D,4,),"") -> 200 | M45: =VLOOKUP(J45,'CC directory'!A:I,9,) -> Maintenance Shared Services | N45: =IFERROR(VLOOKUP(J45,'CC directory'!A:C,3,),"") -> Operations | O45: =IFERROR(VLOOKUP(J45,'CC directory'!A:F,6,),"") -> 207 | P45: =IFERROR(VLOOKUP(J45,'CC directory'!A:E,5,),"") -> Production Operations | Q45: =IFERROR(VLOOKUP(J45,'CC directory'!A:H,8,),"") -> 705 | R45: =IFERROR(VLOOKUP(J45,'CC directory'!A:G,7,),"") -> Maintenance | S45: Maintenance | T45: Maintenance Shop&Support | U45: 1434 | V45: Tengiz Fleet | Y45: 45209 | Z45: Non-Critical | AA45: HINO | AB45: 37630C | AC45: KZT | AD45: 36080000 | AE45: 2023 | AI45: 45212 | AJ45: ED00018783 | AK45: 45145 | AL45: 10 | AM45: 45209 | AT45: TRKHNFL 001 | AU45: 374744 | AV45: 2033 | AZ45: 1459 | BC45: New Hino was added in E-Maint & Fleet Management Tool systems, according to the e-mail from Registration Department as of 10.10.2023 with approval by Fleet maintenance and inspection Team Lead. (Inbox-New equipment 2023) The customer ordered directly, as additional. Assigned to CC 20835 - Maintenance Shop&Support. | BD45: =IF((BE45+BG45+BI45)>0, "YES", "NO") -> YES | BE45: 1 | BF45: HINO Н495306 ТШО 126034 | BG45: 1 | BH45: H 495306 | BI45: 0 | BK45: NewCentralTOOL/ Склад CTR | BL45: Self-propelled motorized (HDV/HDE) - Wheeled | BM45: =VLOOKUP(BL45,'directory all'!C:D,2,) -> Mileage, engine hours, GPS | BN45: Flatbed/boom truck (do not use) | BO45: Shared with conditions | BQ45: 13930 | BR45: N/A | BS45: N/A | BT45: N/A | BU45: N/A | BV45: N/A | BW45: N/A | BX45: N/A | BY45: TCO SCM Logistics | BZ45: 200-4401 | CA45: mssls@tengizchevroil.com | CB45: YES | CC45: 42.294 | CD45: 2.359 | CG45: Maintenance: Assylbek Amangaliyev / Yerkin Dauletov
A46: 126035 | B46: Active | C46: H523906 | D46: TRUCK HD HINO-700 BOOM PALFINGER | E46: N-COCR | F46: HDV Heavy Duty Vehicle | G46: Tengiz | H46: MX967443FP0021172 | I46: JHDFS1EUU00010087 | J46: 20850 | K46: =IFERROR(VLOOKUP(J46,'CC directory'!A:B,2,),"") -> ACTIVE | L46: =IFERROR(VLOOKUP(J46,'CC directory'!A:D,4,),"") -> 200 | M46: =VLOOKUP(J46,'CC directory'!A:I,9,) -> Maintenance Shared Services | N46: =IFERROR(VLOOKUP(J46,'CC directory'!A:C,3,),"") -> Operations | O46: =IFERROR(VLOOKUP(J46,'CC directory'!A:F,6,),"") -> 207 | P46: =IFERROR(VLOOKUP(J46,'CC directory'!A:E,5,),"") -> Production Operations | Q46: =IFERROR(VLOOKUP(J46,'CC directory'!A:H,8,),"") -> 705 | R46: =IFERROR(VLOOKUP(J46,'CC directory'!A:G,7,),"") -> Maintenance | S46: Maintenance | T46: Maintenance Shared Services | U46: 2184 | V46: Tengiz Fleet | Y46: 45236 | Z46: Non-Critical | AA46: HINO Motors Kazakhstan | AB46: HINO 67443F | AC46: KZT | AD46: 36080000 | AE46: 2023 | AI46: 45268 | AJ46: EW00013959 | AK46: 45222 | AL46: 10 | AM46: 45236 | AR46: 295/80R22,5 | AS46: 295/80R22,5 | AT46: TRKHNBM 001 | AU46: 374749 | AV46: 2033 | AZ46: 2391 | BA46: HINO, E13CWR | BB46: HINO, HX07 | BC46: sutz: New Hino was added in E-Maint & Fleet Management Tool systems, according to the e-mail from Contract Coordinator as of 17.11.2023 with confirmed by Fleet maintenance and inspection Team Lead. (Inbox-New equipment 2023) The customer ordered directly, as additional. Assigned to CC 20850 - Maintenance Shared Services. 24.12.2023-sutz: The status was changed to N-COCR as we will not be maintenance further, the reason BP Bisengali Crane will be serviced for repairs, according to an email from Fleet Maintenance and Inspection Coordinator 2 with confirmation from the TCO Transport Team Leader as of 26.11.2023. (Inbox-New equipment 2023) | BD46: =IF((BE46+BG46+BI46)>0, "YES", "NO") -> YES | BE46: 1 | BF46: HINO-700 H523906 TCO 126035 | BG46: 1 | BH46: H 523906 | BI46: 0 | BK46: Plant KTL/Завод КТЛ | BL46: Self-propelled motorized (HDV/HDE) - Wheeled | BM46: =VLOOKUP(BL46,'directory all'!C:D,2,) -> Mileage, engine hours, GPS | BN46: Hook loader truck | BO46: Shared with conditions | BQ46: 5000 | BR46: N/A | BS46: N/A | BT46: N/A | BU46: N/A | BV46: N/A | BW46: N/A | BX46: N/A | BY46: TCO MSS BP | BZ46: 200-3681 | CA46: msslr@tengizchevroil.com | CB46: YES | CC46: 42.294 | CD46: 2.359 | CG46: Maintenance: Assylbek Amangaliyev / Yerkin Dauletov
A47: 126036 | B47: Active | C47: H499706 | D47: TRUCK HD KAMAZ 5325-1002-69 | E47: TMF1 | F47: HDV Heavy Duty Vehicle | G47: Tengiz | H47: XWC532505M0016581 | I47: XWC532505M0016581 | J47: 13780 | K47: =IFERROR(VLOOKUP(J47,'CC directory'!A:B,2,),"") -> ACTIVE | L47: =IFERROR(VLOOKUP(J47,'CC directory'!A:D,4,),"") -> 200 | M47: =VLOOKUP(J47,'CC directory'!A:I,9,) -> Heavy Equipment Operations | N47: =IFERROR(VLOOKUP(J47,'CC directory'!A:C,3,),"") -> Operations | O47: =IFERROR(VLOOKUP(J47,'CC directory'!A:F,6,),"") -> 209 | P47: =IFERROR(VLOOKUP(J47,'CC directory'!A:E,5,),"") -> Supply Chain Management | Q47: =IFERROR(VLOOKUP(J47,'CC directory'!A:H,8,),"") -> 322 | R47: =IFERROR(VLOOKUP(J47,'CC directory'!A:G,7,),"") -> Tengiz Ground Transportation | S47: SCM Logistics | T47: Heavy Equipment Operations | U47: 2213 | V47: Tengiz Fleet | Y47: 45600 | Z47: Non-Critical | AA47: KAMAZ | AB47: 5325-1002-69 | AC47: KZT | AD47: 34561000 | AE47: 2024 | AH47: 86097653 | AI47: 45608 | AJ47: ED99889806 | AK47: 45588 | AL47: 10 | AM47: 45593 | AO47: 1956 | AP47: 1956 | AR47: 315/80 | AS47: 315/80 | AT47: HDT 003 | AU47: 60910624 | AV47: 2034 | AZ47: 2423 | BA47: cummins, isb6.7е5250 | BC47: 30.01.25-sutz: The new truck was issued from СС 13780 - Registration Dept to CC 13780 - Heavy Equipment Operations, according to the acceptance act and e-mail from Registration Dept.as of 28.01.2025 with confirmed by TCO Transportation Team Lead. (Inbox-CC change). Added data in 02-2025 Assigned Equipment Report. 27.01.25 smkl: status changed from Received to Active according to the mail from Contract Manager with approval by TCO Logistics Superintendent as of 27.01.25 (Inbox New Equipment 2025 14.11.24-xeza: License plate and technical passport number was accepted for the equipment, according to the e-mail from the Registration department as of 13.11.24. (Inbox-Registration Dept) | BD47: =IF((BE47+BG47+BI47)>0, "YES", "NO") -> YES | BE47: 1 | BF47: КАМАЗ H499706 (ТШО 126036) | BG47: 1 | BH47: H 499706 | BI47: 0 | BK47: Industrial Base | BL47: Self-propelled motorized (HDV/HDE) - Wheeled | BM47: =VLOOKUP(BL47,'directory all'!C:D,2,) -> Mileage, engine hours, GPS | BN47: Flatbed/boom truck (do not use) | BO47: Shared without conditions | BQ47: 11000 | BR47: N/A | BS47: N/A | BT47: N/A | BU47: N/A | BV47: N/A | BW47: N/A | BX47: N/A | BY47: TCO SCM Logistics | BZ47: 5604 | CB47: YES | CC47: 40 | CG47: SCM Logistics: Yerbol Nauryzbay / Yerlan Yeshmagambetov
A48: 128022 | B48: Active | C48: H286606 | D48: TRUCK HD BOX HINO 338 | E48: TMF1 | F48: HDV Heavy Duty Vehicle | G48: Tengiz | H48: 5PVNV8JV9F4S54792 | I48: 5PVNV8JV9F4S54792 | J48: 20850 | K48: =IFERROR(VLOOKUP(J48,'CC directory'!A:B,2,),"") -> ACTIVE | L48: =IFERROR(VLOOKUP(J48,'CC directory'!A:D,4,),"") -> 200 | M48: =VLOOKUP(J48,'CC directory'!A:I,9,) -> Maintenance Shared Services | N48: =IFERROR(VLOOKUP(J48,'CC directory'!A:C,3,),"") -> Operations | O48: =IFERROR(VLOOKUP(J48,'CC directory'!A:F,6,),"") -> 207 | P48: =IFERROR(VLOOKUP(J48,'CC directory'!A:E,5,),"") -> Production Operations | Q48: =IFERROR(VLOOKUP(J48,'CC directory'!A:H,8,),"") -> 705 | R48: =IFERROR(VLOOKUP(J48,'CC directory'!A:G,7,),"") -> Maintenance | S48: Maintenance | T48: Catering | U48: 682 | V48: Tengiz fleet | Z48: Non-Critical | AA48: HINO | AB48: ILT 33 | AC48: USD | AD48: 116500 | AE48: 2014 | AF48: 8 | AH48: 19689 | AI48: 43363 | AJ48: EB00054485 | AK48: 42154 | AL48: 15 | AM48: 42216 | AO48: 60489 | AP48: 60489 | AR48: 11R 22.5 | AS48: 11R 22.5 | AT48: TRKHNBX 001 | AU48: 216376 | AV48: 2027 | AW48: 2030 | AY48: YES | AZ48: 684 | BC48: 13.10.24-sutz: The truck was issued from CC 13780 - Registration Department to CC 13551 - Catering, according to the act of acceptance as of 10.10.24 and e-mail from Registration Department with confirmed by Transportation Team Lead. (Inbox-CC Change on 10.10.24) CC was updated in 10-2024 Assigned Equipments Report. 07.09.2024-sutz: Returned from AFE 9422116179 - MEJ 2024 TA – KTL to CC 13780 - Registration Department, according to the acceptance act as of 06.09.2024 and the e-mail from Registration Dept as of 06.09.2024 (Inbox - CC Change). 21.03.24-sutz: Issued temporarily for used till 31.10.2024 from CC 13780 - Registration Department to AFE# 9422116179 - MEJ 2024 TA – KTL, according to the acceptance act as of 20.03.24 and the e-mail from Registration Dep with approval by TCO Transportation Team Lead as of 18.01.2024. (Inbox - CC Change as of 20.03.24) 06.02.24-sutz: The status was changed to "Reserved", according to the e-mail from Fleet maint and inspec coordinator 2 as of 01.02.2024. (Inbox-Fleet maint and inspec coordinator 2) sutz: The truck was returned from CC 13551 - Catering (only) to СС 13780 - Registration Department, according to the acceptance act as of 31.12.2023 and the e-mail from Registration Dept. as of 31.12.2023 (Inbox – CC Change) 07.11.23-pmlt: Issued from 13778 to 13551 - Catering according to the acceptance act as of 07.11.23. 21.10.23-pmlt: Returned from AFE 9421115684 - MEJ 2023 TA-KTL to 13778 - Registration Department according to the acceptance act as of 19.10.23 and the e-mail from Registration Department as of 21.10.23 (Inbox-CC Change) | BD48: =IF((BE48+BG48+BI48)>0, "YES", "NO") -> YES | BE48: 1 | BF48: HINO H286606 (ТШО 128022) | BG48: 1 | BH48: H 286606 | BI48: 0 | BK48: TFM/АРП | BL48: Self-propelled motorized (HDV/HDE) - Wheeled | BM48: =VLOOKUP(BL48,'directory all'!C:D,2,) -> Mileage, engine hours, GPS | BN48: Food truck | BO48: Shared with conditions | BQ48: 15000 | BR48: 51.5 | BS48: N/A | BT48: N/A | BU48: N/A | BV48: N/A | BW48: N/A | BX48: N/A | BY48: TCO SCM Logistics | BZ48: 200-5158 | CA48: essibcum@tengizchevroil.com | CB48: YES | CC48: 42.294 | CD48: 2.359 | CE48: Sesonal (TA or the main food service vehicle is undergoing repairs) | CG48: Maintenance: Assylbek Amangaliyev / Yerkin Dauletov
A49: 128023 | B49: Active | C49: H286506 | D49: TRUCK HD BOX HINO 338 | E49: TMF1 | F49: HDV Heavy Duty Vehicle | G49: Tengiz | H49: 5PVNV8JV8F4S54797 | I49: 5PVNV8JV8F4S54797 | J49: 13551 | K49: =IFERROR(VLOOKUP(J49,'CC directory'!A:B,2,),"") -> ACTIVE | L49: =IFERROR(VLOOKUP(J49,'CC directory'!A:D,4,),"") -> 200 | M49: =VLOOKUP(J49,'CC directory'!A:I,9,) -> Catering (only) | N49: =IFERROR(VLOOKUP(J49,'CC directory'!A:C,3,),"") -> Operations | O49: =IFERROR(VLOOKUP(J49,'CC directory'!A:F,6,),"") -> 209 | P49: =IFERROR(VLOOKUP(J49,'CC directory'!A:E,5,),"") -> Supply Chain Management | Q49: =IFERROR(VLOOKUP(J49,'CC directory'!A:H,8,),"") -> 300 | R49: =IFERROR(VLOOKUP(J49,'CC directory'!A:G,7,),"") -> Services Management | S49: SCM Tengiz Services | T49: Catering (only) | U49: 683 | V49: Tengiz fleet | Z49: Non-Critical | AA49: HINO | AB49: ILT 33 | AC49: USD | AD49: 116500 | AE49: 2014 | AF49: 8 | AH49: 19698 | AI49: 43363 | AJ49: EB00054484 | AK49: 42154 | AL49: 15 | AM49: 42217 | AO49: 72771 | AP49: 72771 | AR49: 11 R22,5 | AS49: 11 R22,5 | AT49: TRKHNBX 001 | AU49: 216376 | AV49: 2027 | AW49: 2030 | AY49: YES | AZ49: 685 | BD49: =IF((BE49+BG49+BI49)>0, "YES", "NO") -> YES | BE49: 1 | BF49: HINO H286506 (ТШО 128023) | BG49: 1 | BH49: H 286506 | BI49: 0 | BK49: IB MOA Dastarkhan | BL49: Self-propelled motorized (HDV/HDE) - Wheeled | BM49: =VLOOKUP(BL49,'directory all'!C:D,2,) -> Mileage, engine hours, GPS | BN49: Food truck | BO49: Assigned | BP49: Food and Material delivery | BQ49: 4810 | BR49: 14999 | BS49: N/A | BT49: N/A | BU49: N/A | BV49: N/A | BW49: N/A | BX49: N/A | BY49: TCO SCM Logistics | BZ49: 200-5158 | CA49: essibcum@tengizchevroil.com | CB49: YES | CC49: 82.9 | CD49: 6.2833 | CG49: SCM Operations & Services Management: Sagyndyk Adilbekov / Nurbol Akhtanov
A50: 128024 | B50: Active | C50: H289406 | D50: TRUCK HD BOX HINO 338 | E50: TMF1 | F50: HDV Heavy Duty Vehicle | G50: Tengiz | H50: 5PVNV8JV4F4S54800 | I50: 5PVNV8JV4F4S54800 | J50: 13583 | K50: =IFERROR(VLOOKUP(J50,'CC directory'!A:B,2,),"") -> ACTIVE | L50: =IFERROR(VLOOKUP(J50,'CC directory'!A:D,4,),"") -> 200 | M50: =VLOOKUP(J50,'CC directory'!A:I,9,) -> FMA & Butchery Services | N50: =IFERROR(VLOOKUP(J50,'CC directory'!A:C,3,),"") -> Operations | O50: =IFERROR(VLOOKUP(J50,'CC directory'!A:F,6,),"") -> 209 | P50: =IFERROR(VLOOKUP(J50,'CC directory'!A:E,5,),"") -> Supply Chain Management | Q50: =IFERROR(VLOOKUP(J50,'CC directory'!A:H,8,),"") -> 301 | R50: =IFERROR(VLOOKUP(J50,'CC directory'!A:G,7,),"") -> SCM Operations | S50: SCM Tengiz Services | T50: ASJV Administrative Overhead | U50: 684 | V50: Tengiz fleet | Z50: Non-Critical | AA50: HINO | AB50: ILT 33 | AC50: USD | AD50: 116500 | AE50: 2014 | AF50: 8 | AH50: 19705 | AI50: 43318 | AJ50: EB00054190 | AK50: 42154 | AL50: 15 | AM50: 42217 | AO50: 73066 | AP50: 73066 | AR50: 11 R22,5 | AS50: 11 R22,5 | AT50: TRKHNBX 001 | AU50: 216376 | AV50: 2027 | AW50: 2030 | AY50: YES | AZ50: 686 | BD50: =IF((BE50+BG50+BI50)>0, "YES", "NO") -> YES | BE50: 1 | BF50: HINO H289406 (ТШО 128024) | BG50: 1 | BH50: H 289406 | BI50: 0 | BK50: IB TCO | BL50: Self-propelled motorized (HDV/HDE) - Wheeled | BM50: =VLOOKUP(BL50,'directory all'!C:D,2,) -> Mileage, engine hours, GPS | BN50: Food truck | BO50: Assigned | BP50: Food and Material delivery | BQ50: 4810 | BR50: 14969 | BS50: N/A | BT50: N/A | BU50: N/A | BV50: N/A | BW50: N/A | BX50: N/A | BY50: TCO SCM Logistics | BZ50: 200-4593 | CA50: ersswpm@tengizchevroil.com> | CB50: YES | CC50: 86.8 | CD50: 4.6333 | CG50: SCM Operations & Services Management: Sagyndyk Adilbekov / Nurbol Akhtanov
A51: 128025 | B51: Active | C51: H286706 | D51: TRUCK HD BOX HINO 338 | E51: TMF1 | F51: HDV Heavy Duty Vehicle | G51: Tengiz | H51: 5PVNV8JVXF4S54803 | I51: 5PVNV8JVXF4S54803 | J51: 13551 | K51: =IFERROR(VLOOKUP(J51,'CC directory'!A:B,2,),"") -> ACTIVE | L51: =IFERROR(VLOOKUP(J51,'CC directory'!A:D,4,),"") -> 200 | M51: =VLOOKUP(J51,'CC directory'!A:I,9,) -> Catering (only) | N51: =IFERROR(VLOOKUP(J51,'CC directory'!A:C,3,),"") -> Operations | O51: =IFERROR(VLOOKUP(J51,'CC directory'!A:F,6,),"") -> 209 | P51: =IFERROR(VLOOKUP(J51,'CC directory'!A:E,5,),"") -> Supply Chain Management | Q51: =IFERROR(VLOOKUP(J51,'CC directory'!A:H,8,),"") -> 300 | R51: =IFERROR(VLOOKUP(J51,'CC directory'!A:G,7,),"") -> Services Management | S51: SCM Tengiz Services | T51: Catering (only) | U51: 685 | V51: Tengiz fleet | Z51: Non-Critical | AA51: HINO | AB51: ILT 33 | AC51: USD | AD51: 116500 | AE51: 2014 | AF51: 8 | AH51: 19710 | AI51: 43363 | AJ51: EB00054486 | AK51: 42154 | AL51: 15 | AM51: 42217 | AO51: 30,484 | AP51: 30,484 | AR51: 11 R22,5 | AS51: 11 R22,5 | AT51: TRKHNBX 001 | AU51: 216376 | AV51: 2027 | AW51: 2030 | AY51: YES | AZ51: 687 | BC51: 06.01.2025-sutz: The truck was issued temporarily from CC 13780 - Registration Department to CC 13551 - Catering (only), according to the act of acceptance and e-mail from Registration Department as of 06.01.2025 with approval by TCO Transportation Team Lead. (Inbox - CC Change) 04.01.2025-sutz: The truck was returned from AFE: 9422116179 - MEJ 2024 TA – KTL to CC: 13780 - Registration Department, according to the act of acceptance and e-mail from Registration Department as of 31.12.2024. (Inbox - CC Change) 01.08.24-sutz: Issued temporarily from СС 13780 - Registration Department to AFE 9422116179 - MEJ 2024 TA - KTL, according to the act of acceptance and e-mail from Registration Dept with confirmed by TCO Transportation Team Lead as of 31.07.24 (Inbox - CC Change) 16.07.24-pmlt: Returned from 13551-Catering to 13780-Registration Department according to the acceptance act as of 16.07.24 and the e-mail from Reg.Dept (Inbox - CC Change) 26.06.24-pmlt: Issued from 13780-Reg.Dept. to 13551 - Catering according to the acceptance act as of 26.06.24 and the e-mail. (Inbox-CC Change as of 26.06.24) 16.06.24-sutz: The truck was returned from AFE 9422116179 - MEJ 2024 TA – KTL to CC 13780 - Registration Department, according to the acceptance act as of 15.06.24 and the e-mail from Registration Dept. The status will be as “Reserved” (Inbox - CC Change as of 15.06.24) Updated in 06-2024 Assigned Equipments Report. 14.06.24-sutz: Issued temporarily from CC 13780 - Registration Department to AFE 9422116179 - MEJ 2024 TA – KTL, the reason: replaced on Hino H286606 truck was damaged and was under repair for a long time, according to the acceptance act as of 12.06.24 and the e-mail from Registration Dep with approval by TCO Transportation Team Lead as of 13.06.2024. (Inbox - CC Change) 24.05.24-pmlt: Returned from AFE 9422116179 - MEJ 2024 TA – KTL to 13780 - Registration Department according to the acceptance act as of 24.05.24 (Inbox - CC Change as of 24.05.24) 23.03.24-sutz: Issued temporarily till 31.10.2024 from CC 13780 - Registration Department to AFE 9422116179 - MEJ 2024 TA – KTL, according to the acceptance act as of 23.03.24 and the e-mail from Registration Dep with approval by TCO Transportation Team Lead as of 18.01.2024. (Inbox - CC Change as of 23.03.24) 06.02.24-sutz: The status was changed to "Reserved", according to the e-mail from Fleet maint and inspec coordinator 2 as of 01.02.2024. (Inbox-Fleet maint and inspec coordinator 2) 13.12.23-pmlt: Returned to 13780 - Registration Department according to the acceptance act as of 13.12.23 01.12.23-pmlt: Temporarily issued from 13780-Registration Dept. to 13549 - ASJV Administrative Overhead according to the acceptance act as of 01.12.23 The vehicle was returned from AFE 9421115684 - MEJ 2023 TA - KTL to CC 13780 - Registration Department, according to the acceptance act as of 05.09.2023 and the e-mail from Registration Dept. as of 06.09.2023. (Inbox - CC change) | BD51: =IF((BE51+BG51+BI51)>0, "YES", "NO") -> YES | BE51: 1 | BF51: HINO H286706 (ТШО 128025) | BG51: 1 | BH51: H 286706 | BI51: 0 | BK51: IB MOA Dastarkhan | BL51: Self-propelled motorized (HDV/HDE) - Wheeled | BM51: =VLOOKUP(BL51,'directory all'!C:D,2,) -> Mileage, engine hours, GPS | BN51: Food truck | BO51: Assigned | BP51: Food and Material delivery | BQ51: 4810 | BR51: 14969 | BS51: N/A | BT51: N/A | BU51: N/A | BV51: N/A | BW51: N/A | BX51: N/A | BY51: TCO SCM Logistics | BZ51: 200-5158 | CA51: essibcum@tengizchevroil.com | CB51: YES | CC51: 158.9 | CD51: 7.1333 | CG51: SCM Operations & Services Management: Sagyndyk Adilbekov / Nurbol Akhtanov
A52: 128026 | B52: Active | C52: H286806 | D52: TRUCK HD BOX HINO 338 | E52: TMF1 | F52: HDV Heavy Duty Vehicle | G52: Tengiz | H52: 5PVNV8JV9F4S54808 | I52: 5PVNV8JV9F4S54808 | J52: 20850 | K52: =IFERROR(VLOOKUP(J52,'CC directory'!A:B,2,),"") -> ACTIVE | L52: =IFERROR(VLOOKUP(J52,'CC directory'!A:D,4,),"") -> 200 | M52: =VLOOKUP(J52,'CC directory'!A:I,9,) -> Maintenance Shared Services | N52: =IFERROR(VLOOKUP(J52,'CC directory'!A:C,3,),"") -> Operations | O52: =IFERROR(VLOOKUP(J52,'CC directory'!A:F,6,),"") -> 207 | P52: =IFERROR(VLOOKUP(J52,'CC directory'!A:E,5,),"") -> Production Operations | Q52: =IFERROR(VLOOKUP(J52,'CC directory'!A:H,8,),"") -> 705 | R52: =IFERROR(VLOOKUP(J52,'CC directory'!A:G,7,),"") -> Maintenance | S52: Maintenance | T52: FMA & Butchery Services | U52: 686 | V52: Tengiz fleet | Z52: Non-Critical | AA52: HINO | AB52: ILT 33 | AC52: USD | AD52: 116500 | AE52: 2014 | AF52: 8 | AH52: 19720 | AI52: 43363 | AJ52: EB00054487 | AK52: 42154 | AL52: 15 | AM52: 42217 | AO52: 36,982 | AP52: 36,982 | AR52: 11 R22,5 | AS52: 11 R22,5 | AT52: TRKHNBX 001 | AU52: 216376 | AV52: 2027 | AW52: 2030 | AY52: YES | AZ52: 688 | BC52: 30.03.25-sutz: Temporarily was issued from СС 13780 - Registration Department to CC 13584 - FMA & Butchery Services, according to the e-mail from Registration Dep. with confirmed by TCO Transportation Team Lead and act of acceptance on dated 13.03.25. (Inbox - CC change as of 13.03.25) 26.02.25-sutz: Returned from CC 13583 - FMA & Butchery Services to CC 13780 - Registration Department, according to the acceptance act as of 25.02.2025 and the e-mail from Registration Dept. as of 26.02.2025. (Inbox - CC Change) 21.10.24-sutz: Temporarily issued from СС 13780 - Registration Department to CC 13583 - FMA & Butchery Services, according to the act of acceptance on dated 21.10.24 and email dated 21.10.24. (Inbox - CC change) CC was updated in 10-2024 Assigned Equipments Report. 25.09.24-xeza: Returned from AFE 9422116179 - MEJ 2024 TA – KTL to CC 13780 - Registration Department, according to the acceptance act as of 23.09.2024 and the e-mail from Registration Dept. as of 25.09.2024 (Inbox - CC Change). 24.05.24-pmlt: Issued from 13780 - Registration Department to 9422116179 - MEJ 2024 TA - KTL according to the act as of 02.05.24 and the e-mail as of 24.05.24. (Inbox - CC Change) 06.02.24-sutz: The status was changed to "Reserved", according to the e-mail from Fleet maint and inspec coordinator 2 as of 01.02.2024. (Inbox-Fleet maint and inspec coordinator 2) The heavy vehicle was returned from AFE 9421115684 - MEJ 2023 TA – KTL to 13780 - Registration Department, according to the e-mail from Registration Department as of 18.10.2023 and acceptance act as of 17.10.2023. (Inbox-CC change) | BD52: =IF((BE52+BG52+BI52)>0, "YES", "NO") -> YES | BE52: 1 | BF52: HINO H286806 (ТШО 128026) | BG52: 1 | BH52: H 286806 | BI52: 0 | BK52: TFM/АРП | BL52: Self-propelled motorized (HDV/HDE) - Wheeled | BM52: =VLOOKUP(BL52,'directory all'!C:D,2,) -> Mileage, engine hours, GPS | BN52: Food truck | BO52: Shared with conditions | BQ52: 15000 | BR52: 51.5 | BS52: N/A | BT52: N/A | BU52: N/A | BV52: N/A | BW52: N/A | BX52: N/A | BY52: TCO SCM Logistics | BZ52: 200-4401 | CA52: mssls@tengizchevroil.com | CB52: YES | CC52: 42.294 | CD52: 2.359 | CE52: Sesonal (TA or the main food service vehicle is undergoing repairs) | CG52: Maintenance: Assylbek Amangaliyev / Yerkin Dauletov
A53: 128027 | B53: Reserved | C53: H286906 | D53: TRUCK HD BOX HINO 338 | E53: TMF1 | F53: HDV Heavy Duty Vehicle | G53: Tengiz | H53: 5PVNV8JV7F4S54807 | I53: 5PVNV8JV7F4S54807 | J53: 13780 | K53: =IFERROR(VLOOKUP(J53,'CC directory'!A:B,2,),"") -> ACTIVE | L53: =IFERROR(VLOOKUP(J53,'CC directory'!A:D,4,),"") -> 200 | M53: =VLOOKUP(J53,'CC directory'!A:I,9,) -> Heavy Equipment Operations | N53: =IFERROR(VLOOKUP(J53,'CC directory'!A:C,3,),"") -> Operations | O53: =IFERROR(VLOOKUP(J53,'CC directory'!A:F,6,),"") -> 209 | P53: =IFERROR(VLOOKUP(J53,'CC directory'!A:E,5,),"") -> Supply Chain Management | Q53: =IFERROR(VLOOKUP(J53,'CC directory'!A:H,8,),"") -> 322 | R53: =IFERROR(VLOOKUP(J53,'CC directory'!A:G,7,),"") -> Tengiz Ground Transportation | S53: SCM Logistics | T53: Registration Department | U53: 687 | V53: Tengiz fleet | Z53: Non-Critical | AA53: HINO | AB53: ILT 33 | AC53: USD | AD53: 116500 | AE53: 2014 | AF53: 8 | AH53: 19719 | AI53: 43363 | AJ53: EB00054488 | AK53: 42154 | AL53: 15 | AM53: 42217 | AO53: 933 | AP53: 933 | AR53: 11 R22,5 | AS53: 11 R22,5 | AT53: TRKHNBX 001 | AU53: 216376 | AV53: 2027 | AW53: 2030 | AY53: YES | AZ53: 689 | BC53: 06.02.24-sutz: The status was changed to "Reserved", according to the e-mail from Fleet maint and inspec coordinator 2 as of 01.02.2024. (Inbox-Fleet maint and inspec coordinator 2) The truck was returned from CC 13551 - Catering to CC 13780 - Registration Department, according to the acceptance act as of 11.10.2023 and the e-mail from Registration Dept. as of 12.10.2023. (Inbox - CC change) CC was changed from 13778 - Registration Department to 13551 - Catering according to the acceptance act as of 31.07.2023 & e-mail from Registration Department as of 01.08.2023. (Inbox-CC change) | BD53: =IF((BE53+BG53+BI53)>0, "YES", "NO") -> YES | BE53: 1 | BF53: HINO H286906 (ТШО 128027) | BG53: 1 | BH53: H 286906 | BI53: 0 | BK53: Industrial Base | BL53: Self-propelled motorized (HDV/HDE) - Wheeled | BM53: =VLOOKUP(BL53,'directory all'!C:D,2,) -> Mileage, engine hours, GPS | BN53: Food truck | BO53: Assigned | BP53: everyday use for meal, food transportation in Tengiz | BQ53: 10000 | BR53: N/A | BS53: N/A | BT53: N/A | BU53: N/A | BV53: N/A | BW53: N/A | BX53: N/A | BY53: TCO SCM Logistics | BZ53: 7240 | CB53: YES | CC53: 40 | CD53: 1.5 | CE53: In preservation | CG53: SCM Logistics: Yerbol Nauryzbay / Yerlan Yeshmagambetov
A54: 128028 | B54: Reserved | C54: H287306 | D54: TRUCK HD BOX HINO 338 | E54: TMF1 | F54: HDV Heavy Duty Vehicle | G54: Tengiz | H54: 5PVNV8JV5F4S54840 | I54: 5PVNV8JV5F4S54840 | J54: 13780 | K54: =IFERROR(VLOOKUP(J54,'CC directory'!A:B,2,),"") -> ACTIVE | L54: =IFERROR(VLOOKUP(J54,'CC directory'!A:D,4,),"") -> 200 | M54: =VLOOKUP(J54,'CC directory'!A:I,9,) -> Heavy Equipment Operations | N54: =IFERROR(VLOOKUP(J54,'CC directory'!A:C,3,),"") -> Operations | O54: =IFERROR(VLOOKUP(J54,'CC directory'!A:F,6,),"") -> 209 | P54: =IFERROR(VLOOKUP(J54,'CC directory'!A:E,5,),"") -> Supply Chain Management | Q54: =IFERROR(VLOOKUP(J54,'CC directory'!A:H,8,),"") -> 322 | R54: =IFERROR(VLOOKUP(J54,'CC directory'!A:G,7,),"") -> Tengiz Ground Transportation | S54: SCM Logistics | T54: Registration Department | U54: 688 | V54: Tengiz fleet | Z54: Non-Critical | AA54: HINO | AB54: ILT 33 | AC54: USD | AD54: 116500 | AE54: 2014 | AF54: 8 | AH54: 19774 | AI54: 43363 | AJ54: EB00054492 | AK54: 42154 | AL54: 15 | AM54: 42217 | AO54: 11978 | AP54: 11978 | AR54: 11 R22,5 | AS54: 11 R22,5 | AT54: TRKHNBX 001 | AU54: 216376 | AV54: 2027 | AW54: 2030 | AZ54: 690 | BC54: 07.10.24-xeza: The status was changed to "Reserved", according to the e-mail from Transportation Team Lead as of 07.10.2024. (Inbox-Transportation Team Lead) 06.10.24-xeza: Returned from СС – 13583 - FMA & Butchery Services to CC 13780 - Registration Department, according to the acceptance act as of 05.10.2024 and the e-mail from Registration Dept. as of 05.10.2024. (Inbox - CC Change). 03.04.24-pmlt: Issued from 13778 - Registration Department to 13583 - FMA & Butchery Services according to the acceptance act as of 03.04.24 and the e-mail from Registration Department..(Inbox - CC Change) 06.02.24-sutz: The status was changed to "Reserved", according to the e-mail from Fleet maint and inspec coordinator 2 as of 01.02.2024. (Inbox-Fleet maint and inspec coordinator 2) Was returned from CC 13549 - FMA WHSE IB to CC 13780 - Registration Department according to the acceptance act as of 20.09.23 and e-mail from Registration Department as of 20.09.23 (Inbox – CC Change) The heavy vehicle was issued temporarily from CC 13778- Registration Department to CC 13549 - FMA WHSE IB, according to the act of acceptance and e-mail from Registration Department as of 23.07.2023 with confirmed by TR Contracts Manager. (Inbox-CC change) The reason: Temporarily issued Hino until the repair is out of repair H209606. | BD54: =IF((BE54+BG54+BI54)>0, "YES", "NO") -> YES | BE54: 1 | BF54: HINO H287306 (ТШО128028) | BG54: 1 | BH54: H 287306 | BI54: 0 | BK54: Industrial Base | BL54: Self-propelled motorized (HDV/HDE) - Wheeled | BM54: =VLOOKUP(BL54,'directory all'!C:D,2,) -> Mileage, engine hours, GPS | BN54: Food truck | BO54: Assigned | BP54: everyday use for meal, food transportation in Tengiz | BQ54: 10000 | BR54: N/A | BS54: N/A | BT54: N/A | BU54: N/A | BV54: N/A | BW54: N/A | BX54: N/A | BY54: TCO SCM Logistics | BZ54: 7667 | CB54: YES | CC54: 40 | CD54: 1.5 | CE54: In preservation | CG54: SCM Logistics: Yerbol Nauryzbay / Yerlan Yeshmagambetov
A55: 128029 | B55: Active | C55: H287006 | D55: TRUCK HD BOX REFRIGERATED HINO 338 | E55: TMF1 | F55: HDV Heavy Duty Vehicle | G55: Tengiz | H55: 5PVNV8JV8F4S54783 | I55: 5PVNV8JV8F4S54783 | J55: 13583 | K55: =IFERROR(VLOOKUP(J55,'CC directory'!A:B,2,),"") -> ACTIVE | L55: =IFERROR(VLOOKUP(J55,'CC directory'!A:D,4,),"") -> 200 | M55: =VLOOKUP(J55,'CC directory'!A:I,9,) -> FMA & Butchery Services | N55: =IFERROR(VLOOKUP(J55,'CC directory'!A:C,3,),"") -> Operations | O55: =IFERROR(VLOOKUP(J55,'CC directory'!A:F,6,),"") -> 209 | P55: =IFERROR(VLOOKUP(J55,'CC directory'!A:E,5,),"") -> Supply Chain Management | Q55: =IFERROR(VLOOKUP(J55,'CC directory'!A:H,8,),"") -> 301 | R55: =IFERROR(VLOOKUP(J55,'CC directory'!A:G,7,),"") -> SCM Operations | S55: SCM Tengiz Services | T55: ASJV Administrative Overhead | U55: 689 | V55: Tengiz fleet | Z55: Non-Critical | AA55: HINO | AB55: ILT 33 | AC55: USD | AD55: 125000 | AE55: 2014 | AF55: 8 | AH55: 19671 | AI55: 43363 | AJ55: EB00054489 | AK55: 42154 | AL55: 15 | AM55: 42217 | AO55: 67568 | AP55: 67568 | AR55: 11 R22,5 | AS55: 11 R22,5 | AT55: TRKHNBX 001 | AU55: 216376 | AV55: 2027 | AW55: 2030 | AY55: YES | AZ55: 691 | BD55: =IF((BE55+BG55+BI55)>0, "YES", "NO") -> YES | BE55: 1 | BF55: HINO H287006 (ТШО 128029) | BG55: 1 | BH55: H 287006 | BI55: 0 | BK55: IB TCO | BL55: Self-propelled motorized (HDV/HDE) - Wheeled | BM55: =VLOOKUP(BL55,'directory all'!C:D,2,) -> Mileage, engine hours, GPS | BN55: Food truck | BO55: Assigned | BP55: Food delivery | BQ55: 4810 | BR55: 14969 | BS55: N/A | BT55: N/A | BU55: N/A | BV55: N/A | BW55: N/A | BX55: N/A | BY55: TCO SCM Logistics | BZ55: 200-4593 | CA55: ersswpm@tengizchevroil.com> | CB55: YES | CC55: 158.9 | CD55: 5 | CG55: SCM Operations & Services Management: Sagyndyk Adilbekov / Nurbol Akhtanov
A56: 128030 | B56: Active | C56: H287106 | D56: TRUCK HD BOX REFRIGERATED HINO 338 | E56: TMF1 | F56: HDV Heavy Duty Vehicle | G56: Tengiz | H56: 5PVNV8JV7F4S54788 | I56: 5PVNV8JV7F4S54788 | J56: 13583 | K56: =IFERROR(VLOOKUP(J56,'CC directory'!A:B,2,),"") -> ACTIVE | L56: =IFERROR(VLOOKUP(J56,'CC directory'!A:D,4,),"") -> 200 | M56: =VLOOKUP(J56,'CC directory'!A:I,9,) -> FMA & Butchery Services | N56: =IFERROR(VLOOKUP(J56,'CC directory'!A:C,3,),"") -> Operations | O56: =IFERROR(VLOOKUP(J56,'CC directory'!A:F,6,),"") -> 209 | P56: =IFERROR(VLOOKUP(J56,'CC directory'!A:E,5,),"") -> Supply Chain Management | Q56: =IFERROR(VLOOKUP(J56,'CC directory'!A:H,8,),"") -> 301 | R56: =IFERROR(VLOOKUP(J56,'CC directory'!A:G,7,),"") -> SCM Operations | S56: SCM Tengiz Services | T56: ASJV Administrative Overhead | U56: 690 | V56: Tengiz fleet | Z56: Non-Critical | AA56: HINO | AB56: ILT 33 | AC56: USD | AD56: 125000 | AE56: 2014 | AF56: 8 | AH56: 19678 | AI56: 43363 | AJ56: EB00054490 | AK56: 42154 | AL56: 15 | AM56: 42217 | AO56: 58888 | AP56: 58888 | AR56: 11 R22,5 | AS56: 11 R22,5 | AT56: TRKHNBX 001 | AU56: 216376 | AV56: 2027 | AW56: 2030 | AY56: YES | AZ56: 692 | BD56: =IF((BE56+BG56+BI56)>0, "YES", "NO") -> YES | BE56: 1 | BF56: HINO H287106 (ТШО 128030) | BG56: 1 | BH56: H 287106 | BI56: 0 | BK56: IB TCO | BL56: Self-propelled motorized (HDV/HDE) - Wheeled | BM56: =VLOOKUP(BL56,'directory all'!C:D,2,) -> Mileage, engine hours, GPS | BN56: Food truck | BO56: Assigned | BP56: Food delivery | BQ56: 4810 | BR56: 14969 | BS56: N/A | BT56: N/A | BU56: N/A | BV56: N/A | BW56: N/A | BX56: N/A | BY56: TCO SCM Logistics | BZ56: 200-4593 | CA56: ersswpm@tengizchevroil.com> | CB56: YES | CC56: 82.4 | CD56: 4.8666 | CG56: SCM Operations & Services Management: Sagyndyk Adilbekov / Nurbol Akhtanov
A57: 128031 | B57: Active | C57: H287206 | D57: TRUCK HD BOX REFRIGERATED HINO 338 | E57: TMF1 | F57: HDV Heavy Duty Vehicle | G57: Tengiz | H57: 5PVNV8JV7F4S54791 | I57: 5PVNV8JV7F4S54791 | J57: 13551 | K57: =IFERROR(VLOOKUP(J57,'CC directory'!A:B,2,),"") -> ACTIVE | L57: =IFERROR(VLOOKUP(J57,'CC directory'!A:D,4,),"") -> 200 | M57: =VLOOKUP(J57,'CC directory'!A:I,9,) -> Catering (only) | N57: =IFERROR(VLOOKUP(J57,'CC directory'!A:C,3,),"") -> Operations | O57: =IFERROR(VLOOKUP(J57,'CC directory'!A:F,6,),"") -> 209 | P57: =IFERROR(VLOOKUP(J57,'CC directory'!A:E,5,),"") -> Supply Chain Management | Q57: =IFERROR(VLOOKUP(J57,'CC directory'!A:H,8,),"") -> 300 | R57: =IFERROR(VLOOKUP(J57,'CC directory'!A:G,7,),"") -> Services Management | S57: SCM Tengiz Services | T57: Catering (only) | U57: 691 | V57: Tengiz fleet | Z57: Non-Critical | AA57: HINO | AB57: ILT 33 | AC57: USD | AD57: 125000 | AE57: 2014 | AF57: 8 | AH57: 19686 | AI57: 43363 | AJ57: EB00054491 | AK57: 42154 | AL57: 15 | AM57: 42216 | AO57: 65981 | AP57: 65981 | AR57: 11R 22.5 | AS57: 11R 22.5 | AT57: TRKHNBX 001 | AU57: 216376 | AV57: 2027 | AW57: 2030 | AY57: YES | AZ57: 693 | BD57: =IF((BE57+BG57+BI57)>0, "YES", "NO") -> YES | BE57: 1 | BF57: HINO H287206 (ТШО 128031) | BG57: 1 | BH57: H 287206 | BI57: 0 | BK57: IB MOA Dastarkhan | BL57: Self-propelled motorized (HDV/HDE) - Wheeled | BM57: =VLOOKUP(BL57,'directory all'!C:D,2,) -> Mileage, engine hours, GPS | BN57: Food truck | BO57: Assigned | BP57: Food delivery | BQ57: 5100 | BR57: 12000 | BS57: N/A | BT57: N/A | BU57: N/A | BV57: N/A | BW57: N/A | BX57: N/A | BY57: TCO SCM Logistics | BZ57: 200-5158 | CA57: essibcum@tengizchevroil.com | CB57: YES | CC57: 64.2 | CD57: 3.3 | CG57: SCM Operations & Services Management: Sagyndyk Adilbekov / Nurbol Akhtanov
A58: 128032 | B58: Active | C58: H124106 | D58: TRUCK HD FLATBED W/CANOPY 6312B9-420-010 | E58: TMF1 | F58: HDV Heavy Duty Vehicle | G58: Tengiz | H58: Y3M6312B9E0000737 | I58: Y3M6312B9¿0000737 | J58: 20530 | K58: =IFERROR(VLOOKUP(J58,'CC directory'!A:B,2,),"") -> ACTIVE | L58: =IFERROR(VLOOKUP(J58,'CC directory'!A:D,4,),"") -> 150 | M58: =VLOOKUP(J58,'CC directory'!A:I,9,) -> ERT - Base | N58: =IFERROR(VLOOKUP(J58,'CC directory'!A:C,3,),"") -> OE/HSE | O58: =IFERROR(VLOOKUP(J58,'CC directory'!A:F,6,),"") -> 205 | P58: =IFERROR(VLOOKUP(J58,'CC directory'!A:E,5,),"") -> OE/HSE | Q58: =IFERROR(VLOOKUP(J58,'CC directory'!A:H,8,),"") -> 607 | R58: =IFERROR(VLOOKUP(J58,'CC directory'!A:G,7,),"") -> Tengiz OE/HSE | S58: Tengiz OE/HSE | T58: ERT - Base | U58: 692 | V58: Tengiz fleet | Z58: Non-Critical | AA58: MAZ | AB58: 6312890-420-010 | AC58: KZT | AD58: 14188000 | AE58: 2014 | AF58: 8 | AJ58: ED00014992 | AK58: 42186 | AL58: 15 | AM58: 42301 | AO58: 104991 | AP58: 87933 | AR58: 315/80R22.5 | AS58: 315/80R22.5 | AT58: TRKMAZ 10 | AU58: 232161 | AV58: 2027 | AW58: 2030 | AY58: YES | AZ58: 694 | BD58: =IF((BE58+BG58+BI58)>0, "YES", "NO") -> YES | BE58: 1 | BF58: МАЗ Н124106 (ТШО 128032) | BG58: 1 | BH58: H 124106 | BI58: 0 | BL58: Self-propelled motorized (HDV/HDE) - Wheeled | BM58: =VLOOKUP(BL58,'directory all'!C:D,2,) -> Mileage, engine hours, GPS | BN58: Flatbed/boom truck (do not use) | BO58: Assigned | BP58: Emergency | BR58: N/A | BS58: N/A | BT58: N/A | BU58: N/A | BV58: N/A | BW58: N/A | BX58: N/A | BY58: TCO SCM Logistics | BZ58: 3448 | CB58: YES | CD58: 0.5 | CE58: Emergency | CF58: Removed from data gathering scope | CG58: ERT Base: Azamat Tatcheyev / Said Dosmukhanbetov
A59: 128033 | B59: Active | C59: H166806 | D59: TRUCK HD BOX INSULATED FORD 2526 HR | E59: TMF1 | F59: HDV Heavy Duty Vehicle | G59: Tengiz | H59: NM0LKXTP6LEG94435 | I59: NM0LKXTP6LEG94435 | J59: 13551 | K59: =IFERROR(VLOOKUP(J59,'CC directory'!A:B,2,),"") -> ACTIVE | L59: =IFERROR(VLOOKUP(J59,'CC directory'!A:D,4,),"") -> 200 | M59: =VLOOKUP(J59,'CC directory'!A:I,9,) -> Catering (only) | N59: =IFERROR(VLOOKUP(J59,'CC directory'!A:C,3,),"") -> Operations | O59: =IFERROR(VLOOKUP(J59,'CC directory'!A:F,6,),"") -> 209 | P59: =IFERROR(VLOOKUP(J59,'CC directory'!A:E,5,),"") -> Supply Chain Management | Q59: =IFERROR(VLOOKUP(J59,'CC directory'!A:H,8,),"") -> 300 | R59: =IFERROR(VLOOKUP(J59,'CC directory'!A:G,7,),"") -> Services Management | S59: SCM Tengiz Services | T59: Catering, IBMOA | U59: 693 | V59: Tengiz fleet | Z59: Non-Critical | AA59: FORD | AB59: FORD CARGO 2526 | AC59: KZT | AD59: 30380000 | AE59: 2014 | AF59: 7 | AH59: EG 94435 | AI59: 42515 | AJ59: ED00015392 | AK59: 42443 | AL59: 15 | AM59: 42464 | AO59: 212456 | AP59: 212456 | AR59: 315 /60R22,5 | AS59: 315 /60R22,5 | AT59: TRKFDBX 001 | AU59: 242986 | AV59: 2028 | AW59: 2031 | AY59: YES | AZ59: 695 | BA59: 6 | BD59: =IF((BE59+BG59+BI59)>0, "YES", "NO") -> YES | BE59: 1 | BF59: FORD Н166806 (ТШО 128033) | BG59: 1 | BH59: H 166806 | BI59: 0 | BK59: IB MOA Dastarkhan | BL59: Self-propelled motorized (HDV/HDE) - Wheeled | BM59: =VLOOKUP(BL59,'directory all'!C:D,2,) -> Mileage, engine hours, GPS | BN59: Food truck | BO59: Assigned | BP59: Food delivery | BQ59: 9980 | BR59: 34980 | BS59: N/A | BT59: N/A | BU59: N/A | BV59: N/A | BW59: N/A | BX59: N/A | BY59: TCO SCM Logistics | BZ59: 200-5158 | CA59: essibcum@tengizchevroil.com | CB59: YES | CC59: 59.4 | CD59: 4.7833 | CG59: SCM Operations & Services Management: Sagyndyk Adilbekov / Nurbol Akhtanov
A60: 128034 | B60: Active | C60: H166906 | D60: TRUCK HD BOX INSULATED FORD 2526 HR | E60: TMF1 | F60: HDV Heavy Duty Vehicle | G60: Tengiz | H60: NM0LKXTP6LEG94434 | I60: NM0LKXTP6LEG94434 | J60: 13583 | K60: =IFERROR(VLOOKUP(J60,'CC directory'!A:B,2,),"") -> ACTIVE | L60: =IFERROR(VLOOKUP(J60,'CC directory'!A:D,4,),"") -> 200 | M60: =VLOOKUP(J60,'CC directory'!A:I,9,) -> FMA & Butchery Services | N60: =IFERROR(VLOOKUP(J60,'CC directory'!A:C,3,),"") -> Operations | O60: =IFERROR(VLOOKUP(J60,'CC directory'!A:F,6,),"") -> 209 | P60: =IFERROR(VLOOKUP(J60,'CC directory'!A:E,5,),"") -> Supply Chain Management | Q60: =IFERROR(VLOOKUP(J60,'CC directory'!A:H,8,),"") -> 301 | R60: =IFERROR(VLOOKUP(J60,'CC directory'!A:G,7,),"") -> SCM Operations | S60: SCM Tengiz Services | T60: FMA WHSE IB | U60: 694 | V60: Tengiz fleet | Z60: Non-Critical | AA60: FORD | AB60: FORD CARGO 2526 | AC60: KZT | AD60: 32182850 | AE60: 2014 | AF60: 7 | AH60: EG 94434 | AI60: 42515 | AJ60: ED00015393 | AK60: 42443 | AL60: 15 | AM60: 42464 | AO60: 162325 | AP60: 162325 | AR60: 315 /60R22,5 | AS60: 315 /60R22,5 | AT60: TRKFDBX 001 | AU60: 242985 | AV60: 2028 | AW60: 2031 | AY60: YES | AZ60: 696 | BA60: 6 | BD60: =IF((BE60+BG60+BI60)>0, "YES", "NO") -> YES | BE60: 1 | BF60: FORD Н166906 (ТШО 128034) | BG60: 1 | BH60: H 166906 | BI60: 0 | BK60: IB TCO | BL60: Self-propelled motorized (HDV/HDE) - Wheeled | BM60: =VLOOKUP(BL60,'directory all'!C:D,2,) -> Mileage, engine hours, GPS | BN60: Food truck | BO60: Assigned | BP60: Food delivery | BQ60: 9980 | BR60: 34980 | BS60: N/A | BT60: N/A | BU60: N/A | BV60: N/A | BW60: N/A | BX60: N/A | BY60: TCO SCM Logistics | BZ60: 200-4593 | CA60: ersswpm@tengizchevroil.com> | CB60: YES | CC60: 70 | CD60: 3.3166 | CG60: SCM Operations & Services Management: Sagyndyk Adilbekov / Nurbol Akhtanov
A61: 128036 | B61: Active | C61: H168206 | D61: TRUCK HD BOX INSULATED FORD 1826 DC | E61: TMF1 | F61: HDV Heavy Duty Vehicle | G61: Tengiz | H61: NM0LKXTP6LEG94509 | I61: NM0LKXTP6LEG94509 | J61: 13551 | K61: =IFERROR(VLOOKUP(J61,'CC directory'!A:B,2,),"") -> ACTIVE | L61: =IFERROR(VLOOKUP(J61,'CC directory'!A:D,4,),"") -> 200 | M61: =VLOOKUP(J61,'CC directory'!A:I,9,) -> Catering (only) | N61: =IFERROR(VLOOKUP(J61,'CC directory'!A:C,3,),"") -> Operations | O61: =IFERROR(VLOOKUP(J61,'CC directory'!A:F,6,),"") -> 209 | P61: =IFERROR(VLOOKUP(J61,'CC directory'!A:E,5,),"") -> Supply Chain Management | Q61: =IFERROR(VLOOKUP(J61,'CC directory'!A:H,8,),"") -> 300 | R61: =IFERROR(VLOOKUP(J61,'CC directory'!A:G,7,),"") -> Services Management | S61: SCM Tengiz Services | T61: Catering, IBMOA | U61: 696 | V61: Tengiz fleet | Z61: Critical | AA61: FORD | AB61: FORD CARGO 1826 | AC61: KZT | AD61: 28770840 | AE61: 2014 | AF61: 7 | AH61: EG 94509 | AI61: 42538 | AJ61: ED00015446 | AL61: 15 | AM61: 42533 | AO61: 117733 | AP61: 117733 | AT61: TRKFDBX 002 | AU61: 246377 | AV61: 2028 | AW61: 2031 | AY61: YES | AZ61: 698 | BA61: 6 | BB61: ZF 9S75 | BD61: =IF((BE61+BG61+BI61)>0, "YES", "NO") -> YES | BE61: 1 | BF61: FORD Н168206 (ТШО 128036) | BG61: 1 | BH61: H 168206 | BI61: 0 | BK61: IB MOA Dastarkhan | BL61: Self-propelled motorized (HDV/HDE) - Wheeled | BM61: =VLOOKUP(BL61,'directory all'!C:D,2,) -> Mileage, engine hours, GPS | BN61: Food truck | BO61: Assigned | BP61: Food delivery | BQ61: 9980 | BR61: 34980 | BS61: N/A | BT61: N/A | BU61: N/A | BV61: N/A | BW61: N/A | BX61: N/A | BY61: TCO SCM Logistics | BZ61: 200-5158 | CA61: essibcum@tengizchevroil.com | CB61: YES | CC61: 46.1 | CD61: 3.65 | CG61: SCM Operations & Services Management: Sagyndyk Adilbekov / Nurbol Akhtanov
A62: 128037 | B62: Active | C62: H168106 | D62: TRUCK HD BOX INSULATED FORD 1826 DC | E62: TMF1 | F62: HDV Heavy Duty Vehicle | G62: Tengiz | H62: NM0LKXTP6LEG94447 | I62: NM0LKXTP6LEG94447 | J62: 13551 | K62: =IFERROR(VLOOKUP(J62,'CC directory'!A:B,2,),"") -> ACTIVE | L62: =IFERROR(VLOOKUP(J62,'CC directory'!A:D,4,),"") -> 200 | M62: =VLOOKUP(J62,'CC directory'!A:I,9,) -> Catering (only) | N62: =IFERROR(VLOOKUP(J62,'CC directory'!A:C,3,),"") -> Operations | O62: =IFERROR(VLOOKUP(J62,'CC directory'!A:F,6,),"") -> 209 | P62: =IFERROR(VLOOKUP(J62,'CC directory'!A:E,5,),"") -> Supply Chain Management | Q62: =IFERROR(VLOOKUP(J62,'CC directory'!A:H,8,),"") -> 300 | R62: =IFERROR(VLOOKUP(J62,'CC directory'!A:G,7,),"") -> Services Management | S62: SCM Tengiz Services | T62: Catering, IBMOA | U62: 697 | V62: Tengiz fleet | Z62: Critical | AA62: FORD | AB62: FORD CARGO 1826 | AC62: KZT | AD62: 28770840 | AE62: 2014 | AF62: 7 | AH62: EG 94447 | AI62: 42538 | AJ62: ED00015445 | AL62: 15 | AM62: 42533 | AO62: 149578 | AP62: 149578 | AT62: TRKFDBX 002 | AU62: 246377 | AV62: 2028 | AW62: 2031 | AY62: YES | AZ62: 699 | BA62: 6 | BB62: ZF 9S75 | BD62: =IF((BE62+BG62+BI62)>0, "YES", "NO") -> YES | BE62: 1 | BF62: FORD Н168106 (ТШО 128037) | BG62: 1 | BH62: H 168106 | BI62: 0 | BK62: IB MOA Dastarkhan | BL62: Self-propelled motorized (HDV/HDE) - Wheeled | BM62: =VLOOKUP(BL62,'directory all'!C:D,2,) -> Mileage, engine hours, GPS | BN62: Food truck | BO62: Assigned | BP62: Food delivery | BQ62: 9980 | BR62: 34980 | BS62: N/A | BT62: N/A | BU62: N/A | BV62: N/A | BW62: N/A | BX62: N/A | BY62: TCO SCM Logistics | BZ62: 200-5158 | CA62: essibcum@tengizchevroil.com | CB62: YES | CC62: 58.2 | CD62: 3.85 | CG62: SCM Operations & Services Management: Sagyndyk Adilbekov / Nurbol Akhtanov
A63: 128038 | B63: Reserved | C63: H176106 | D63: TRUCK HD BOX REFRIGERATED HINO 500 MTA | E63: TMF1 | F63: HDV Heavy Duty Vehicle | G63: Tengiz | H63: JHDGD8JLT00010786 | I63: X5J57656CF0000016 | J63: 13780 | K63: =IFERROR(VLOOKUP(J63,'CC directory'!A:B,2,),"") -> ACTIVE | L63: =IFERROR(VLOOKUP(J63,'CC directory'!A:D,4,),"") -> 200 | M63: =VLOOKUP(J63,'CC directory'!A:I,9,) -> Heavy Equipment Operations | N63: =IFERROR(VLOOKUP(J63,'CC directory'!A:C,3,),"") -> Operations | O63: =IFERROR(VLOOKUP(J63,'CC directory'!A:F,6,),"") -> 209 | P63: =IFERROR(VLOOKUP(J63,'CC directory'!A:E,5,),"") -> Supply Chain Management | Q63: =IFERROR(VLOOKUP(J63,'CC directory'!A:H,8,),"") -> 322 | R63: =IFERROR(VLOOKUP(J63,'CC directory'!A:G,7,),"") -> Tengiz Ground Transportation | S63: SCM Logistics | T63: Registration Department | U63: 698 | V63: Tengiz fleet | Z63: Critical | AA63: HINO | AB63: 57656 | AC63: KZT | AD63: 23550000 | AE63: 2015 | AF63: 7 | AH63: J08E-UR (EURO-4) | AI63: 42598 | AJ63: ED00015552 | AK63: 42544 | AL63: 15 | AM63: 42554 | AO63: 203,323 | AP63: 203,323 | AR63: 265/70 R 19.5 ( | AS63: 265/70 R 19.5 ( | AT63: TRKHNBX 002 | AU63: 249961 | AV63: 2028 | AW63: 2031 | AY63: YES | AZ63: 700 | BC63: 25.11.2024-sutz: The truck was returned from CC 13780 – TMF1 Workshop to CC 13780 - Registration Department, according to the act of acceptance and e-mail from Registration Dept.as of 25.11.2024 with approval by Fleet maintenance and inspection Team Lead. The status was changed to “Reserved” (Inbox - CC Change) | BD63: =IF((BE63+BG63+BI63)>0, "YES", "NO") -> YES | BE63: 1 | BF63: HINO H176106 (ТШО 128038) | BG63: 0 | BI63: 0 | BK63: Industrial Base | BL63: Self-propelled motorized (HDV/HDE) - Wheeled | BM63: =VLOOKUP(BL63,'directory all'!C:D,2,) -> Mileage, engine hours, GPS | BN63: HD truck (tractor) | BO63: Assigned | BP63: everyday use for meal, food transportation in Tengiz | BQ63: 5900 | BR63: N/A | BS63: N/A | BT63: N/A | BU63: N/A | BV63: N/A | BW63: N/A | BX63: N/A | BY63: TCO SCM Logistics | BZ63: 3310 / 3370 | CB63: YES | CC63: 40 | CE63: In preservation | CG63: SCM Logistics: Yerbol Nauryzbay / Yerlan Yeshmagambetov
A64: 128039 | B64: Active | C64: H209506 | D64: TRUCK HD BOX REFRIGERATED HINO 500 | E64: TMF1 | F64: HDV Heavy Duty Vehicle | G64: Tengiz | H64: JHDGD8JLT00010961 | I64: JHDGD8JLT00010961 | J64: 13551 | K64: =IFERROR(VLOOKUP(J64,'CC directory'!A:B,2,),"") -> ACTIVE | L64: =IFERROR(VLOOKUP(J64,'CC directory'!A:D,4,),"") -> 200 | M64: =VLOOKUP(J64,'CC directory'!A:I,9,) -> Catering (only) | N64: =IFERROR(VLOOKUP(J64,'CC directory'!A:C,3,),"") -> Operations | O64: =IFERROR(VLOOKUP(J64,'CC directory'!A:F,6,),"") -> 209 | P64: =IFERROR(VLOOKUP(J64,'CC directory'!A:E,5,),"") -> Supply Chain Management | Q64: =IFERROR(VLOOKUP(J64,'CC directory'!A:H,8,),"") -> 300 | R64: =IFERROR(VLOOKUP(J64,'CC directory'!A:G,7,),"") -> Services Management | S64: SCM Tengiz Services | T64: Catering (only) | U64: 699 | V64: Tengiz fleet | Z64: Critical | AA64: HINO | AB64: 438971 | AC64: KZT | AD64: 32857143 | AE64: 2017 | AF64: 6 | AI64: 43011 | AJ64: ED00016184 | AK64: 42993 | AL64: 15 | AM64: 43012 | AO64: 168665 | AP64: 168665 | AR64: 265/70 R 19.5( | AS64: 265/70 R 19.5( | AT64: TRKHNBX 003 | AU64: 270440 | AV64: 2029 | AW64: 2032 | AY64: YES | AZ64: 701 | BD64: =IF((BE64+BG64+BI64)>0, "YES", "NO") -> YES | BE64: 1 | BF64: HINO H209506 (ТШО 128039) | BG64: 1 | BH64: H 209506 | BI64: 0 | BK64: IB MOA Dastarkhan | BL64: Self-propelled motorized (HDV/HDE) - Wheeled | BM64: =VLOOKUP(BL64,'directory all'!C:D,2,) -> Mileage, engine hours, GPS | BN64: Food truck | BO64: Assigned | BP64: Food delivery | BQ64: 5100 | BR64: 12000 | BS64: N/A | BT64: N/A | BU64: N/A | BV64: N/A | BW64: N/A | BX64: N/A | BY64: TCO SCM Logistics | BZ64: 200-5158 | CA64: essibcum@tengizchevroil.com | CB64: YES | CC64: 79.8 | CD64: 3.8333 | CG64: SCM Operations & Services Management: Sagyndyk Adilbekov / Nurbol Akhtanov
A65: 128040 | B65: Active | C65: H209606 | D65: TRUCK HD BOX REFRIGERATED HINO 500 | E65: TMF1 | F65: HDV Heavy Duty Vehicle | G65: Tengiz | H65: JHDGD8JLT00010962 | I65: JHDGD8JLT00010962 | J65: 13583 | K65: =IFERROR(VLOOKUP(J65,'CC directory'!A:B,2,),"") -> ACTIVE | L65: =IFERROR(VLOOKUP(J65,'CC directory'!A:D,4,),"") -> 200 | M65: =VLOOKUP(J65,'CC directory'!A:I,9,) -> FMA & Butchery Services | N65: =IFERROR(VLOOKUP(J65,'CC directory'!A:C,3,),"") -> Operations | O65: =IFERROR(VLOOKUP(J65,'CC directory'!A:F,6,),"") -> 209 | P65: =IFERROR(VLOOKUP(J65,'CC directory'!A:E,5,),"") -> Supply Chain Management | Q65: =IFERROR(VLOOKUP(J65,'CC directory'!A:H,8,),"") -> 301 | R65: =IFERROR(VLOOKUP(J65,'CC directory'!A:G,7,),"") -> SCM Operations | S65: SCM Tengiz Services | T65: ASJV Administrative Overhead | U65: 700 | V65: Tengiz fleet | Z65: Critical | AA65: HINO | AB65: 438971 | AC65: KZT | AD65: 32857143 | AE65: 2017 | AF65: 6 | AI65: 43011 | AJ65: ED00016185 | AK65: 42993 | AL65: 15 | AM65: 43012 | AO65: 156701 | AP65: 156701 | AR65: 265/70 R 19.5( | AS65: 265/70 R 19.5( | AT65: TRKHNBX 003 | AU65: 270440 | AV65: 2029 | AW65: 2032 | AY65: YES | AZ65: 702 | BD65: =IF((BE65+BG65+BI65)>0, "YES", "NO") -> YES | BE65: 1 | BF65: HINO H209606 (ТШО 128040) | BG65: 1 | BH65: H 209606 | BI65: 0 | BK65: IB TCO | BL65: Self-propelled motorized (HDV/HDE) - Wheeled | BM65: =VLOOKUP(BL65,'directory all'!C:D,2,) -> Mileage, engine hours, GPS | BN65: Food truck | BO65: Assigned | BP65: Food delivery | BQ65: 5100 | BR65: 12000 | BS65: N/A | BT65: N/A | BU65: N/A | BV65: N/A | BW65: N/A | BX65: N/A | BY65: TCO SCM Logistics | BZ65: 200-4593 | CA65: ersswpm@tengizchevroil.com> | CB65: YES | CC65: 63.6 | CD65: 5.2333 | CG65: SCM Operations & Services Management: Sagyndyk Adilbekov / Nurbol Akhtanov
A66: 206003 | B66: Active | C66: 231EAC | D66: COMPACTOR LANDFILL BOMAG BC 473 RB-4 | E66: TMF1 | F66: HDV Heavy Duty Vehicle | G66: Tengiz | H66: 1.0193E+11 | I66: 1.0193E+11 | J66: 20550 | K66: =IFERROR(VLOOKUP(J66,'CC directory'!A:B,2,),"") -> ACTIVE | L66: =IFERROR(VLOOKUP(J66,'CC directory'!A:D,4,),"") -> 150 | M66: =VLOOKUP(J66,'CC directory'!A:I,9,) -> WM Tengiz - Base | N66: =IFERROR(VLOOKUP(J66,'CC directory'!A:C,3,),"") -> OE/HSE | O66: =IFERROR(VLOOKUP(J66,'CC directory'!A:F,6,),"") -> 205 | P66: =IFERROR(VLOOKUP(J66,'CC directory'!A:E,5,),"") -> OE/HSE | Q66: =IFERROR(VLOOKUP(J66,'CC directory'!A:H,8,),"") -> 607 | R66: =IFERROR(VLOOKUP(J66,'CC directory'!A:G,7,),"") -> Tengiz OE/HSE | S66: Tengiz OE/HSE | T66: WM Tengiz - Base | U66: 705 | V66: Tengiz fleet | Z66: Non-Critical | AA66: BOMAG | AB66: BC 473 RB-4 | AC66: USD | AD66: 362000 | AE66: 2018 | AF66: 4 | AH66: 935911C1040 | AI66: 43486 | AJ66: ACY000667 | AK66: 43444 | AL66: 20 | AM66: 43487 | AO66: 5938 | AP66: 5938 | AQ66: 5785.00 mh#1 | AT66: LCP 003 | AU66: 287613 | AV66: 2039 | AW66: 2039 | AZ66: 707 | BD66: =IF((BE66+BG66+BI66)>0, "YES", "NO") -> YES | BE66: 1 | BF66: BOMAG 231 EAC (ТШО 206003) | BG66: 0 | BI66: 0 | BK66: Tengiz Eco Centre | BL66: Self-propelled motorized (HDV/HDE) - Tracked | BM66: =VLOOKUP(BL66,'directory all'!C:D,2,) -> Mileage, engine hours, GPS | BN66: Dispossal equipment | BO66: Assigned | BP66: Unique equipment | BQ66: N/A | BR66: N/A | BS66: N/A | BT66: information missing | BU66: 800–1000 А | BV66: 28 В / 80–100 А | BW66: ~8–10 bar | BX66: ~300–400 m³/h (уплотнение отходов) | BY66: TCO SCM Logistics | BZ66: 2234 | CA66: envsvs@tengizchevroil.com | CB66: YES | CD66: 10 | CE66: Repairing | CF66: Currently used in TEC | CG66: Tengiz Base: Azamat Kurmanov / Rustem Konyrbayev
A67: 206004 | B67: Active | C67: 255EAC | D67: REFUSE COMPACTOR BOMAG BC 473 RB-3 | E67: TMF1 | F67: HDV Heavy Duty Vehicle | G67: Tengiz | H67: 101930131015 | I67: 101930131015 | J67: 20550 | K67: =IFERROR(VLOOKUP(J67,'CC directory'!A:B,2,),"") -> ACTIVE | L67: =IFERROR(VLOOKUP(J67,'CC directory'!A:D,4,),"") -> 150 | M67: =VLOOKUP(J67,'CC directory'!A:I,9,) -> WM Tengiz - Base | N67: =IFERROR(VLOOKUP(J67,'CC directory'!A:C,3,),"") -> OE/HSE | O67: =IFERROR(VLOOKUP(J67,'CC directory'!A:F,6,),"") -> 205 | P67: =IFERROR(VLOOKUP(J67,'CC directory'!A:E,5,),"") -> OE/HSE | Q67: =IFERROR(VLOOKUP(J67,'CC directory'!A:H,8,),"") -> 607 | R67: =IFERROR(VLOOKUP(J67,'CC directory'!A:G,7,),"") -> Tengiz OE/HSE | S67: Tengiz OE/HSE | T67: WM Tengiz - Base | U67: 2235 | V67: Tengiz Fleet | Y67: 45723 | Z67: Critical | AA67: BOMAG GMBH | AB67: BC 473 RB-3 | AC67: KZT | AD67: 266062500 | AE67: 2025 | AG67: Closed cabin | AH67: TCD 2013L06 4V/TIER3 | AI67: 45736 | AJ67: 000029 | AK67: 45717 | AL67: 20 | AM67: 45722 | AT67: LCP 003 | AU67: 61066870-001 | AV67: 2045 | AY67: YES | AZ67: 2445 | BA67: Deutz | BC67: 02.04.25-sutz: The new technical passport with License plate number was received, according to the e-mail from Registration department as of 26.03.25 (Inbox-Registration Department) | BD67: =IF((BE67+BG67+BI67)>0, "YES", "NO") -> NO | BE67: 0 | BG67: 0 | BI67: 0 | BK67: Tengiz Eco Centre | BL67: Self-propelled motorized (HDV/HDE) - Tracked | BM67: =VLOOKUP(BL67,'directory all'!C:D,2,) -> Mileage, engine hours, GPS | BN67: Dispossal equipment | BO67: Assigned | BP67: Unique equipment | BQ67: N/A | BR67: N/A | BS67: N/A | BT67: information missing | BU67: 800–1000 А | BV67: 28 В / 80–100 А | BW67: ~8–10 bar | BX67: ~300–400 m³/h | BY67: TCO SCM Logistics | BZ67: 2234 | CA67: envsvs@tengizchevroil.com | CF67: Currently used in TEC | CG67: Tengiz Base: Azamat Kurmanov / Rustem Konyrbayev
A68: 213003 | B68: Reserved | D68: ROLLER VIBRATING BOMAG BW60SC4 | E68: N-COCR | F68: HDV Heavy Duty Vehicle | G68: Tengiz | J68: 13562 | K68: =IFERROR(VLOOKUP(J68,'CC directory'!A:B,2,),"") -> ACTIVE | L68: =IFERROR(VLOOKUP(J68,'CC directory'!A:D,4,),"") -> 200 | M68: =VLOOKUP(J68,'CC directory'!A:I,9,) -> TCOV Maintenance | N68: =IFERROR(VLOOKUP(J68,'CC directory'!A:C,3,),"") -> Operations | O68: =IFERROR(VLOOKUP(J68,'CC directory'!A:F,6,),"") -> 209 | P68: =IFERROR(VLOOKUP(J68,'CC directory'!A:E,5,),"") -> Supply Chain Management | Q68: =IFERROR(VLOOKUP(J68,'CC directory'!A:H,8,),"") -> 310 | R68: =IFERROR(VLOOKUP(J68,'CC directory'!A:G,7,),"") -> Tengiz Facilities Management | S68: Tengiz Facilities Management | T68: ESS Facilities Maintenance | U68: 706 | V68: Tengiz fleet | Z68: Non-Critical | AA68: BOMAG | AB68: BW60SC4 | AC68: USD | AD68: 14000 | AE68: 1993 | AF68: 19 | AL68: 20 | AM68: 38194 | AO68: 1531 | AP68: 1531 | AT68: RR 003 | AV68: 2024 | AW68: 2024 | AY68: YES | AZ68: 708 | BC68: 17.11.24-xeza: The service zone was changed from "TMF-1" to "N-COCR", according to the e-mail from Contracts Manager with confirmed by Fleet maintenance and Inspection Team Lead as of 17.11.24.(Inbox-Fleet maintenance and Inspection Team Lead). 20.06.24-sutz: The status was changed to “Reserved” according to the e-mail from TCO Fleet maintenance and inspection Team Lead’ Andrey Pavelko as of 20.06.24. (Inbox - TCO Fleet maint and inspec Team Lead) Data was deleted in 06-2024 Assigned Equipments Report. | BD68: =IF((BE68+BG68+BI68)>0, "YES", "NO") -> NO | BE68: 0 | BG68: 0 | BI68: 0 | BL68: Self-propelled motorized (HDV/HDE) - Wheeled | BM68: =VLOOKUP(BL68,'directory all'!C:D,2,) -> Mileage, engine hours, GPS | BN68: Road construction and cleaning equipment | BQ68: N/A | BR68: N/A | BS68: N/A | BT68: N/A | BU68: N/A | BV68: N/A | BW68: N/A | BX68: N/A | CG68: TFM: Konstantin Chernov / Maxat Yeshmaganbetov
A69: 216012 | B69: Reserved | C69: H031906 | D69: TRUCK HD SNOW PLOUGH KENWORTH C-500 | E69: TMF1 | F69: HDV Heavy Duty Vehicle | G69: Tengiz | H69: 1NKCJ48X1DR358145 | I69: 1NKCJ48X1DR358145 | J69: 13502 | K69: =IFERROR(VLOOKUP(J69,'CC directory'!A:B,2,),"") -> ACTIVE | L69: =IFERROR(VLOOKUP(J69,'CC directory'!A:D,4,),"") -> 200 | M69: =VLOOKUP(J69,'CC directory'!A:I,9,) -> Roads Group SCM | N69: =IFERROR(VLOOKUP(J69,'CC directory'!A:C,3,),"") -> Operations | O69: =IFERROR(VLOOKUP(J69,'CC directory'!A:F,6,),"") -> 209 | P69: =IFERROR(VLOOKUP(J69,'CC directory'!A:E,5,),"") -> Supply Chain Management | Q69: =IFERROR(VLOOKUP(J69,'CC directory'!A:H,8,),"") -> 300 | R69: =IFERROR(VLOOKUP(J69,'CC directory'!A:G,7,),"") -> Services Management | S69: SCM Tengiz Services | T69: FMPG/Roads | U69: 709 | V69: Tengiz fleet | Z69: Critical | AA69: KENWORTH | AB69: C-500 | AC69: USD | AD69: 244800 | AE69: 2012 | AF69: 10 | AH69: 79609378 | AJ69: ED00013279 | AK69: 41319 | AL69: 15 | AM69: 41329 | AO69: 103686 | AP69: 103686 | AR69: 445/65R | AS69: 445/65R | AT69: TRKKEN 005 | AU69: 170561 | AV69: 2025 | AW69: 2028 | AZ69: 711 | BA69: IN-LINE 6 | BB69: FRO16210C | BC69: 25.04.2025-oqmh: The status was changed from N-COCR to TMF1 according to the e-mail from Fleet maintenance and inspection Team Lead as of 25.04.2025. (Inbox-TCO Fleet maint and inspec Team Lead) 04.04.25-sutz: Due to the end of the season for using truck, statuses were changed from Active to "Reserved" & TMF1 to "N-COCR", according to the e-mail from TCO Fleet maintenance and inspection Team Lead as of 31.03.2025. (Inbox-TCO Fleet maintenance and inspection Team Lead) 16.11.24-xeza: The status was changed from "Reserved" to "Active", according to the e-mail from TMF Manager with confirmed by Fleet maintenance and Inspection Team Lead as of 15.10.24.(Inbox-Fleet maintenance and Inspection Team Lead). 29.04.24-sutz: The status was changed to Reserved according to the e-mail from TCO Logistics Technical Coordinator on 29.04.2024. (Inbox - TCO Logistics Technical Coordinator) | BD69: =IF((BE69+BG69+BI69)>0, "YES", "NO") -> YES | BE69: 1 | BF69: KENWORTH H 031906 (ТШО 216012) | BG69: 1 | BH69: H 031906 | BI69: 0 | BK69: СС Yard#24 | BL69: Self-propelled motorized (HDV/HDE) - Wheeled | BM69: =VLOOKUP(BL69,'directory all'!C:D,2,) -> Mileage, engine hours, GPS | BN69: Snow plough truck | BO69: Assigned | BP69: Road cleaning and snow removal | BQ69: 18071 | BR69: 26071 | BS69: N/A | BT69: N/A | BU69: N/A | BV69: N/A | BW69: N/A | BX69: N/A | BY69: TCO SCM Logistics | BZ69: 7430 | CA69: tmf1s@tengizchevroil.com | CB69: YES | CC69: 40 | CD69: 1.5 | CE69: Seasonal (Winter) | CF69: Not related to SCM Ops & Services Management | CG69: SCM Operations & Services Management: Sagyndyk Adilbekov / Nurbol Akhtanov
A70: 216013 | B70: Reserved | C70: H032006 | D70: TRUCK HD SNOW PLOUGH KENWORTH C-500 | E70: TMF1 | F70: HDV Heavy Duty Vehicle | G70: Tengiz | H70: 1NKCJ48X3DR358146 | I70: 358146 | J70: 13502 | K70: =IFERROR(VLOOKUP(J70,'CC directory'!A:B,2,),"") -> ACTIVE | L70: =IFERROR(VLOOKUP(J70,'CC directory'!A:D,4,),"") -> 200 | M70: =VLOOKUP(J70,'CC directory'!A:I,9,) -> Roads Group SCM | N70: =IFERROR(VLOOKUP(J70,'CC directory'!A:C,3,),"") -> Operations | O70: =IFERROR(VLOOKUP(J70,'CC directory'!A:F,6,),"") -> 209 | P70: =IFERROR(VLOOKUP(J70,'CC directory'!A:E,5,),"") -> Supply Chain Management | Q70: =IFERROR(VLOOKUP(J70,'CC directory'!A:H,8,),"") -> 300 | R70: =IFERROR(VLOOKUP(J70,'CC directory'!A:G,7,),"") -> Services Management | S70: SCM Tengiz Services | T70: FMPG/Roads | U70: 710 | V70: Tengiz fleet | Z70: Critical | AA70: KENWORTH | AB70: C-500 | AC70: USD | AD70: 244800 | AE70: 2012 | AF70: 10 | AH70: 79609376 | AJ70: ED00013280 | AK70: 41319 | AL70: 15 | AM70: 41329 | AO70: 87757 | AP70: 94961 | AR70: 445/65R | AS70: 445/65R | AT70: TRKKEN 005 | AU70: 170561 | AV70: 2025 | AW70: 2028 | AZ70: 712 | BA70: IN-LINE 6 | BB70: FRO16210C | BC70: 25.04.2025-oqmh: The status was changed from N-COCR to TMF1 according to the e-mail from Fleet maintenance and inspection Team Lead as of 25.04.2025. (Inbox-TCO Fleet maint and inspec Team Lead) 04.04.25-sutz: Due to the end of the season for using truck, statuses were changed from Active to "Reserved" & TMF1 to "N-COCR", according to the e-mail from TCO Fleet maintenance and inspection Team Lead as of 31.03.2025. (Inbox-TCO Fleet maintenance and inspection Team Lead) 16.11.24-xeza: The status was changed from "Reserved" to "Active", according to the e-mail from TMF Manager with confirmed by Fleet maintenance and Inspection Team Lead as of 15.10.24.(Inbox-Fleet maintenance and Inspection Team Lead). 29.04.24-sutz: The status was changed to Reserved according to the e-mail from TCO Logistics Technical Coordinator on 29.04.2024. (Inbox - TCO Logistics Technical Coordinator) | BD70: =IF((BE70+BG70+BI70)>0, "YES", "NO") -> YES | BE70: 1 | BF70: KENWORTH H032006 (ТШО 216013) | BG70: 1 | BH70: H 032006 | BI70: 0 | BK70: СС Yard#24 | BL70: Self-propelled motorized (HDV/HDE) - Wheeled | BM70: =VLOOKUP(BL70,'directory all'!C:D,2,) -> Mileage, engine hours, GPS | BN70: Snow plough truck | BO70: Assigned | BP70: Road cleaning and snow removal | BQ70: 18071 | BR70: 26071 | BS70: N/A | BT70: N/A | BU70: N/A | BV70: N/A | BW70: N/A | BX70: N/A | BY70: TCO SCM Logistics | BZ70: 7430 | CA70: tmf1s@tengizchevroil.com | CB70: YES | CC70: 40 | CD70: 1.5 | CE70: Seasonal (Winter) | CF70: Not related to SCM Ops & Services Management | CG70: SCM Operations & Services Management: Sagyndyk Adilbekov / Nurbol Akhtanov
A71: 216015 | B71: Reserved | C71: H031406 | D71: TRUCK HD SNOW PLOUGH KENWORTH C-500 | E71: TMF1 | F71: HDV Heavy Duty Vehicle | G71: Tengiz | H71: 1NKCJ48X7DR358148 | I71: 358148 | J71: 13502 | K71: =IFERROR(VLOOKUP(J71,'CC directory'!A:B,2,),"") -> ACTIVE | L71: =IFERROR(VLOOKUP(J71,'CC directory'!A:D,4,),"") -> 200 | M71: =VLOOKUP(J71,'CC directory'!A:I,9,) -> Roads Group SCM | N71: =IFERROR(VLOOKUP(J71,'CC directory'!A:C,3,),"") -> Operations | O71: =IFERROR(VLOOKUP(J71,'CC directory'!A:F,6,),"") -> 209 | P71: =IFERROR(VLOOKUP(J71,'CC directory'!A:E,5,),"") -> Supply Chain Management | Q71: =IFERROR(VLOOKUP(J71,'CC directory'!A:H,8,),"") -> 300 | R71: =IFERROR(VLOOKUP(J71,'CC directory'!A:G,7,),"") -> Services Management | S71: SCM Tengiz Services | T71: FMPG/Roads | U71: 712 | V71: Tengiz fleet | Z71: Critical | AA71: KENWORTH | AB71: C-500 | AC71: USD | AD71: 244800 | AE71: 2012 | AF71: 10 | AH71: 79609687 | AJ71: ED00013274 | AK71: 41319 | AL71: 15 | AM71: 41329 | AO71: 108755 | AP71: 108755 | AR71: 445/65R | AS71: 445/65R | AT71: TRKKEN 005 | AU71: 170561 | AV71: 2025 | AW71: 2028 | AZ71: 714 | BA71: IN-LINE 6 | BB71: FRO16210C | BC71: 25.04.2025-oqmh: The status was changed from N-COCR to TMF1 according to the e-mail from Fleet maintenance and inspection Team Lead as of 25.04.2025. (Inbox-TCO Fleet maint and inspec Team Lead) 04.04.25-sutz: Due to the end of the season for using truck, statuses were changed from Active to "Reserved" & TMF1 to "N-COCR", according to the e-mail from TCO Fleet maintenance and inspection Team Lead as of 31.03.2025. (Inbox-TCO Fleet maintenance and inspection Team Lead) 16.11.24-xeza: The status was changed from "Reserved" to "Active", according to the e-mail from TMF Manager with confirmed by Fleet maintenance and Inspection Team Lead as of 15.10.24.(Inbox-Fleet maintenance and Inspection Team Lead). 29.04.24-sutz: The status was changed to Reserved according to the e-mail from TCO Logistics Technical Coordinator on 29.04.2024. (Inbox - TCO Logistics Technical Coordinator) | BD71: =IF((BE71+BG71+BI71)>0, "YES", "NO") -> YES | BE71: 1 | BF71: KENWORTH H 031406 (ТШО 216015) | BG71: 1 | BH71: H 031406 | BI71: 0 | BK71: СС Yard#24 | BL71: Self-propelled motorized (HDV/HDE) - Wheeled | BM71: =VLOOKUP(BL71,'directory all'!C:D,2,) -> Mileage, engine hours, GPS | BN71: Snow plough truck | BO71: Assigned | BP71: Road cleaning and snow removal | BQ71: 18071 | BR71: 26071 | BS71: N/A | BT71: N/A | BU71: N/A | BV71: N/A | BW71: N/A | BX71: N/A | BY71: TCO SCM Logistics | BZ71: 7430 | CA71: tmf1s@tengizchevroil.com | CB71: YES | CC71: 40 | CD71: 1.5 | CE71: Seasonal (Winter) | CF71: Not related to SCM Ops & Services Management | CG71: SCM Operations & Services Management: Sagyndyk Adilbekov / Nurbol Akhtanov
A72: 216016 | B72: Reserved | C72: H031506 | D72: TRUCK HD SNOW PLOUGH KENWORTH C-500 | E72: TMF1 | F72: HDV Heavy Duty Vehicle | G72: Tengiz | H72: 1NKCJ48X9DR358149 | I72: 1NKCJ48X9DR358149 | J72: 13502 | K72: =IFERROR(VLOOKUP(J72,'CC directory'!A:B,2,),"") -> ACTIVE | L72: =IFERROR(VLOOKUP(J72,'CC directory'!A:D,4,),"") -> 200 | M72: =VLOOKUP(J72,'CC directory'!A:I,9,) -> Roads Group SCM | N72: =IFERROR(VLOOKUP(J72,'CC directory'!A:C,3,),"") -> Operations | O72: =IFERROR(VLOOKUP(J72,'CC directory'!A:F,6,),"") -> 209 | P72: =IFERROR(VLOOKUP(J72,'CC directory'!A:E,5,),"") -> Supply Chain Management | Q72: =IFERROR(VLOOKUP(J72,'CC directory'!A:H,8,),"") -> 300 | R72: =IFERROR(VLOOKUP(J72,'CC directory'!A:G,7,),"") -> Services Management | S72: SCM Tengiz Services | T72: FMPG/Roads | U72: 713 | V72: Tengiz fleet | Z72: Critical | AA72: KENWORTH | AB72: C-500 | AC72: USD | AD72: 244800 | AE72: 2012 | AF72: 10 | AH72: 79609688 | AJ72: ED00013275 | AK72: 41319 | AL72: 15 | AM72: 41330 | AO72: 109994 | AP72: 109994 | AR72: 445/65R | AS72: 445/65R | AT72: TRKKEN 005 | AU72: 170561 | AV72: 2025 | AW72: 2028 | AZ72: 715 | BA72: IN-LINE 6 | BB72: FRO16210C | BC72: 25.04.2025-oqmh: The status was changed from N-COCR to TMF1 according to the e-mail from Fleet maintenance and inspection Team Lead as of 25.04.2025. (Inbox-TCO Fleet maint and inspec Team Lead) 04.04.25-sutz: Due to the end of the season for using truck, statuses were changed from Active to "Reserved" & TMF1 to "N-COCR", according to the e-mail from TCO Fleet maintenance and inspection Team Lead as of 31.03.2025. (Inbox-TCO Fleet maintenance and inspection Team Lead) 16.11.24-xeza: The status was changed from "Reserved" to "Active", according to the e-mail from TMF Manager with confirmed by Fleet maintenance and Inspection Team Lead as of 15.10.24.(Inbox-Fleet maintenance and Inspection Team Lead). 29.04.24-sutz: The status was changed to Reserved according to the e-mail from TCO Logistics Technical Coordinator on 29.04.2024. (Inbox - TCO Logistics Technical Coordinator) | BD72: =IF((BE72+BG72+BI72)>0, "YES", "NO") -> YES | BE72: 1 | BF72: KENWORTH H 031506 (ТШО 216016) | BG72: 1 | BH72: H 031506 | BI72: 0 | BK72: СС Yard#24 | BL72: Self-propelled motorized (HDV/HDE) - Wheeled | BM72: =VLOOKUP(BL72,'directory all'!C:D,2,) -> Mileage, engine hours, GPS | BN72: Snow plough truck | BO72: Assigned | BP72: Road cleaning and snow removal | BQ72: 18071 | BR72: 26071 | BS72: N/A | BT72: N/A | BU72: N/A | BV72: N/A | BW72: N/A | BX72: N/A | BY72: TCO SCM Logistics | BZ72: 7430 | CA72: tmf1s@tengizchevroil.com | CB72: YES | CC72: 40 | CD72: 1.5 | CE72: Seasonal (Winter) | CF72: Not related to SCM Ops & Services Management | CG72: SCM Operations & Services Management: Sagyndyk Adilbekov / Nurbol Akhtanov
A73: 216018 | B73: Active | C73: H168406 | D73: TRUCK HD SNOW PLOUGH MAZ KO-806-20(4in1) | E73: TMF1 | F73: HDV Heavy Duty Vehicle | G73: Tengiz | H73: X5H806204G0000094 | I73: Y3M5340B2G0001498 | J73: 13725 | K73: =IFERROR(VLOOKUP(J73,'CC directory'!A:B,2,),"") -> ACTIVE | L73: =IFERROR(VLOOKUP(J73,'CC directory'!A:D,4,),"") -> 200 | M73: =VLOOKUP(J73,'CC directory'!A:I,9,) -> Aviation Operations | N73: =IFERROR(VLOOKUP(J73,'CC directory'!A:C,3,),"") -> Operations | O73: =IFERROR(VLOOKUP(J73,'CC directory'!A:F,6,),"") -> 209 | P73: =IFERROR(VLOOKUP(J73,'CC directory'!A:E,5,),"") -> Supply Chain Management | Q73: =IFERROR(VLOOKUP(J73,'CC directory'!A:H,8,),"") -> 321 | R73: =IFERROR(VLOOKUP(J73,'CC directory'!A:G,7,),"") -> Aviation & Logistics | S73: SCM Logistics | T73: Aviation Operations | U73: 715 | V73: Tengiz fleet | Z73: Critical | AA73: MAZ | AB73: KO-806-20 | AC73: KZT | AD73: 18250000 | AE73: 2016 | AF73: 7 | AH73: F0022230 | AI73: 42559 | AJ73: ED00015464 | AK73: 42559 | AL73: 15 | AM73: 42582 | AO73: 100325 | AP73: 100325 | AR73: 11.00R20И 111AM | AS73: 11.00R20И 111AM | AT73: TRKMAZ 007 | AU73: 246160 | AV73: 2028 | AW73: 2031 | AY73: YES | AZ73: 717 | BA73: 6 (V) | BD73: =IF((BE73+BG73+BI73)>0, "YES", "NO") -> YES | BE73: 1 | BF73: МАЗ Н168406 (ТШО 216018) | BG73: 1 | BH73: H 168406 | BI73: 0 | BK73: Aerodrome | BL73: Self-propelled motorized (HDV/HDE) - Wheeled | BM73: =VLOOKUP(BL73,'directory all'!C:D,2,) -> Mileage, engine hours, GPS | BN73: Snow plough truck | BO73: Assigned | BP73: Aerdrodrome purpose | BQ73: 18000 | BR73: 9000 | BS73: 24 | BT73: 190-220 Ah | BU73: 100 A | BW73: 7-8 Bar | BY73: TCO SCM Logistics | BZ73: 3370 | CA73: opstng@tengizchevroil.com | CB73: YES | CC73: 40 | CD73: 1.5 | CG73: SCM Aviation: Nurzat Khairolla / Zhandos Ospankulov
A74: 216019 | B74: Reserved | C74: N/A | D74: TRUCK HD SNOW PLOUGH KENWORTH C-500 | E74: TMF1 | F74: HDV Heavy Duty Vehicle | G74: Tengiz | H74: 1NKCJ48X9G105160 | I74: 1NKCJ48X9G105160 | J74: 13566 | K74: =IFERROR(VLOOKUP(J74,'CC directory'!A:B,2,),"") -> ACTIVE | L74: =IFERROR(VLOOKUP(J74,'CC directory'!A:D,4,),"") -> 200 | M74: =VLOOKUP(J74,'CC directory'!A:I,9,) -> Shanyrak Village Maitenance | N74: =IFERROR(VLOOKUP(J74,'CC directory'!A:C,3,),"") -> Operations | O74: =IFERROR(VLOOKUP(J74,'CC directory'!A:F,6,),"") -> 209 | P74: =IFERROR(VLOOKUP(J74,'CC directory'!A:E,5,),"") -> Supply Chain Management | Q74: =IFERROR(VLOOKUP(J74,'CC directory'!A:H,8,),"") -> 310 | R74: =IFERROR(VLOOKUP(J74,'CC directory'!A:G,7,),"") -> Tengiz Facilities Management | S74: Tengiz Facilities Management | T74: Shanyrak Village Maintenance | U74: 716 | V74: Tengiz fleet | Z74: Critical | AA74: KENWORTH | AB74: C-500 | AC74: USD | AD74: 277180 | AE74: 2015 | AF74: 7 | AH74: 79858200 | AK74: 42468 | AL74: 15 | AM74: 42666 | AO74: 3360 | AP74: 3360 | AR74: 445/65R | AS74: 445/65R | AT74: TRKKEN 005 | AU74: 226656 | AV74: 2028 | AW74: 2031 | AX74: ADDITIONAL TO THE FL | AZ74: 718 | BA74: INLINE 4 | BD74: =IF((BE74+BG74+BI74)>0, "YES", "NO") -> NO | BE74: 0 | BG74: 0 | BI74: 0 | BL74: Self-propelled motorized (HDV/HDE) - Wheeled | BM74: =VLOOKUP(BL74,'directory all'!C:D,2,) -> Mileage, engine hours, GPS | BN74: Snow plough truck | BQ74: N/A | BR74: N/A | BS74: N/A | BT74: N/A | BU74: N/A | BV74: N/A | BW74: N/A | BX74: N/A | BY74: TCO SCM Logistics | BZ74: 4559 | CG74: TFM: Konstantin Chernov / Maxat Yeshmaganbetov
A75: 216020 | B75: Active | C75: H190706 | D75: TRUCK HD SNOW PLOUGH KAMAZ КО-829 (4in1) | E75: TMF1 | F75: HDV Heavy Duty Vehicle | G75: Tengiz | H75: XVL483320F0001269 | I75: XTC651154F1325529 | J75: 13567 | K75: =IFERROR(VLOOKUP(J75,'CC directory'!A:B,2,),"") -> ACTIVE | L75: =IFERROR(VLOOKUP(J75,'CC directory'!A:D,4,),"") -> 200 | M75: =VLOOKUP(J75,'CC directory'!A:I,9,) -> Tengiz Services | N75: =IFERROR(VLOOKUP(J75,'CC directory'!A:C,3,),"") -> Operations | O75: =IFERROR(VLOOKUP(J75,'CC directory'!A:F,6,),"") -> 209 | P75: =IFERROR(VLOOKUP(J75,'CC directory'!A:E,5,),"") -> Supply Chain Management | Q75: =IFERROR(VLOOKUP(J75,'CC directory'!A:H,8,),"") -> 301 | R75: =IFERROR(VLOOKUP(J75,'CC directory'!A:G,7,),"") -> SCM Operations | S75: SCM Tengiz Services | T75: Tengiz Services / Light FM Compass Kazakhstan | U75: 717 | V75: Tengiz fleet | Z75: Critical | AA75: KAMAZ | AB75: КО-829Б | AC75: KZT | AD75: 28761600 | AE75: 2015 | AF75: 7 | AH75: 86044464 | AI75: 42798 | AJ75: ED00015857 | AL75: 15 | AM75: 42695 | AO75: 20503 | AP75: 20503 | AR75: 11R22,5 | AS75: 11R22,5 | AT75: TRKKAM 011 | AU75: 258080 | AV75: 2028 | AW75: 2031 | AY75: YES | AZ75: 719 | BD75: =IF((BE75+BG75+BI75)>0, "YES", "NO") -> YES | BE75: 1 | BF75: КАМАЗ Н190706 (ТШО 216020) | BG75: 1 | BH75: H 190706 | BI75: 0 | BK75: TCOV | BL75: Self-propelled motorized (HDV/HDE) - Wheeled | BM75: =VLOOKUP(BL75,'directory all'!C:D,2,) -> Mileage, engine hours, GPS | BN75: Snow plough truck | BO75: Assigned | BP75: Plant watering, snow removal | BQ75: 11760 | BR75: 24950 | BS75: N/A | BT75: N/A | BU75: N/A | BV75: N/A | BW75: N/A | BX75: N/A | BY75: TCO SCM Logistics | BZ75: 200-4999 | CA75: esstfm@esskaz.com | CB75: YES | CC75: 22.7 | CD75: 5.4 | CG75: SCM Operations & Services Management: Sagyndyk Adilbekov / Nurbol Akhtanov
A76: 216022 | B76: Active | C76: H240306 | D76: TRUCK HD SNOW PLOUGH KAMAZ КО-829 (4in1) | E76: TMF1 | F76: HDV Heavy Duty Vehicle | G76: Tengiz | H76: XWC651154H0011818 | I76: XWC651154H0011818 | J76: 13585 | K76: =IFERROR(VLOOKUP(J76,'CC directory'!A:B,2,),"") -> ACTIVE | L76: =IFERROR(VLOOKUP(J76,'CC directory'!A:D,4,),"") -> 200 | M76: =VLOOKUP(J76,'CC directory'!A:I,9,) -> TCOV Services | N76: =IFERROR(VLOOKUP(J76,'CC directory'!A:C,3,),"") -> Operations | O76: =IFERROR(VLOOKUP(J76,'CC directory'!A:F,6,),"") -> 209 | P76: =IFERROR(VLOOKUP(J76,'CC directory'!A:E,5,),"") -> Supply Chain Management | Q76: =IFERROR(VLOOKUP(J76,'CC directory'!A:H,8,),"") -> 301 | R76: =IFERROR(VLOOKUP(J76,'CC directory'!A:G,7,),"") -> SCM Operations | S76: SCM Tengiz Services | T76: TCOV Services / Light FM Compass Kazakhstan | U76: 719 | V76: Tengiz fleet | Z76: Critical | AA76: Kamaz | AB76: КО-829Б | AC76: KZT | AD76: 29300000 | AE76: 2017 | AF76: 5 | AH76: Н2489359 | AI76: 43089 | AJ76: EB00052311 | AL76: 15 | AM76: 43092 | AO76: 14424 | AP76: 14424 | AR76: 11R22,5 | AS76: 11R22,5 | AT76: TRKKAM 012 | AU76: 272928 | AV76: 2029 | AW76: 2032 | AY76: YES | AZ76: 721 | BD76: =IF((BE76+BG76+BI76)>0, "YES", "NO") -> YES | BE76: 1 | BF76: KAMAZ H240306 (ТШО 216022) | BG76: 1 | BH76: H 240306 | BI76: 0 | BK76: TCOV | BL76: Self-propelled motorized (HDV/HDE) - Wheeled | BM76: =VLOOKUP(BL76,'directory all'!C:D,2,) -> Mileage, engine hours, GPS | BN76: Snow plough truck | BO76: Assigned | BP76: Plant watering, snow removal | BQ76: 11760 | BR76: 24950 | BS76: N/A | BT76: N/A | BU76: N/A | BV76: N/A | BW76: N/A | BX76: N/A | BY76: TCO SCM Logistics | BZ76: 200-4999 | CA76: esstfm@esskaz.com | CB76: YES | CC76: 43.4 | CD76: 1.6833 | CG76: SCM Operations & Services Management: Sagyndyk Adilbekov / Nurbol Akhtanov
A77: 218011 | B77: Sent to BP | D77: SWEEPING MACHINE GS 1200 | E77: N-COCR | F77: HDE Heavy Duty Equipment | G77: Tengiz | H77: 300252 | J77: 13562 | K77: =IFERROR(VLOOKUP(J77,'CC directory'!A:B,2,),"") -> ACTIVE | L77: =IFERROR(VLOOKUP(J77,'CC directory'!A:D,4,),"") -> 200 | M77: =VLOOKUP(J77,'CC directory'!A:I,9,) -> TCOV Maintenance | N77: =IFERROR(VLOOKUP(J77,'CC directory'!A:C,3,),"") -> Operations | O77: =IFERROR(VLOOKUP(J77,'CC directory'!A:F,6,),"") -> 209 | P77: =IFERROR(VLOOKUP(J77,'CC directory'!A:E,5,),"") -> Supply Chain Management | Q77: =IFERROR(VLOOKUP(J77,'CC directory'!A:H,8,),"") -> 310 | R77: =IFERROR(VLOOKUP(J77,'CC directory'!A:G,7,),"") -> Tengiz Facilities Management | S77: Tengiz Facilities Management | T77: FM TCOV MAINT | U77: 1476 | V77: Tengiz Fleet | Z77: Non-Critical | AA77: GS ENGINEERING | AB77: GS 1200 | AC77: KZT | AD77: 2858210.3 | AE77: 2008 | AF77: 15 | AI77: 1 | AK77: 39856 | AL77: 20 | AM77: 40280 | AO77: 0 | AP77: 0 | AT77: GRM 040 | AU77: FM27613 | AV77: 2013 | AW77: 2028 | AY77: YES | AZ77: 1682 | BD77: =IF((BE77+BG77+BI77)>0, "YES", "NO") -> NO | BE77: 0 | BG77: 0 | BI77: 0 | BL77: Not self-propelled motorized HDE | BM77: =VLOOKUP(BL77,'directory all'!C:D,2,) -> Engine hours, GPS | BN77: Cleaning, washing tools etc. | BQ77: N/A | BR77: N/A | BS77: N/A | BT77: N/A | BU77: N/A | BV77: N/A | BW77: N/A | BX77: N/A | CG77: TFM: Konstantin Chernov / Maxat Yeshmaganbetov
A78: 219001 | B78: Sent to BP | D78: ATTACHMENT - RAKE GROUND BOBCAT LR 5B | E78: N-COCR | F78: HDV Heavy Duty Vehicle | G78: Tengiz | J78: 13566 | K78: =IFERROR(VLOOKUP(J78,'CC directory'!A:B,2,),"") -> ACTIVE | L78: =IFERROR(VLOOKUP(J78,'CC directory'!A:D,4,),"") -> 200 | M78: =VLOOKUP(J78,'CC directory'!A:I,9,) -> Shanyrak Village Maitenance | N78: =IFERROR(VLOOKUP(J78,'CC directory'!A:C,3,),"") -> Operations | O78: =IFERROR(VLOOKUP(J78,'CC directory'!A:F,6,),"") -> 209 | P78: =IFERROR(VLOOKUP(J78,'CC directory'!A:E,5,),"") -> Supply Chain Management | Q78: =IFERROR(VLOOKUP(J78,'CC directory'!A:H,8,),"") -> 310 | R78: =IFERROR(VLOOKUP(J78,'CC directory'!A:G,7,),"") -> Tengiz Facilities Management | S78: Tengiz Facilities Management | T78: FM SV MAINT | U78: 1477 | V78: Tengiz Fleet | Z78: Non-Critical | AA78: BOBCAT | AB78: LR 5B | AC78: USD | AD78: 6003.6 | AE78: 2004 | AF78: 19 | AI78: 1 | AK78: 1 | AL78: 20 | AM78: 38050 | AO78: 0 | AP78: 0 | AT78: GRMATC 003 | AU78: 83657 | AV78: 2014 | AW78: 2024 | AY78: NO | AZ78: 1683 | BD78: =IF((BE78+BG78+BI78)>0, "YES", "NO") -> NO | BE78: 0 | BG78: 0 | BI78: 0 | BL78: Self-propelled motorized (HDV/HDE) - Wheeled | BM78: =VLOOKUP(BL78,'directory all'!C:D,2,) -> Mileage, engine hours, GPS | BN78: Attachment | BQ78: N/A | BR78: N/A | BS78: N/A | BT78: N/A | BU78: N/A | BV78: N/A | BW78: N/A | BX78: N/A | BZ78: 4559 | CG78: TFM: Konstantin Chernov / Maxat Yeshmaganbetov
A79: 270017 | B79: Sent to BP | D79: SNOW BLOWER SAARBRUKEN MTD E660G | E79: N-COCR | F79: HDE Heavy Duty Equipment | G79: Tengiz | H79: 1/196B10455 | J79: 13562 | K79: =IFERROR(VLOOKUP(J79,'CC directory'!A:B,2,),"") -> ACTIVE | L79: =IFERROR(VLOOKUP(J79,'CC directory'!A:D,4,),"") -> 200 | M79: =VLOOKUP(J79,'CC directory'!A:I,9,) -> TCOV Maintenance | N79: =IFERROR(VLOOKUP(J79,'CC directory'!A:C,3,),"") -> Operations | O79: =IFERROR(VLOOKUP(J79,'CC directory'!A:F,6,),"") -> 209 | P79: =IFERROR(VLOOKUP(J79,'CC directory'!A:E,5,),"") -> Supply Chain Management | Q79: =IFERROR(VLOOKUP(J79,'CC directory'!A:H,8,),"") -> 310 | R79: =IFERROR(VLOOKUP(J79,'CC directory'!A:G,7,),"") -> Tengiz Facilities Management | S79: Tengiz Facilities Management | T79: ESS Facilities Maintenance | U79: 1480 | V79: Tengiz Fleet | Z79: Non-Critical | AA79: SAARBRUKEN | AB79: MTD E660G | AC79: EUR | AD79: 2387 | AE79: 2006 | AF79: 17 | AI79: 1 | AK79: 1 | AL79: 20 | AM79: 39356 | AO79: 0 | AP79: 0 | AT79: BLWSN 002 | AU79: 105357 | AV79: 2012 | AW79: 2027 | AZ79: 1686 | BD79: =IF((BE79+BG79+BI79)>0, "YES", "NO") -> NO | BE79: 0 | BG79: 0 | BI79: 0 | BL79: Non-motorized HDE | BM79: =VLOOKUP(BL79,'directory all'!C:D,2,) -> GPS | BN79: Snow blower (do not use) | BQ79: N/A | BR79: N/A | BS79: N/A | BT79: N/A | BU79: N/A | BV79: N/A | BW79: N/A | BX79: N/A | CG79: TFM: Konstantin Chernov / Maxat Yeshmaganbetov
A80: 270020 | B80: Sent to BP | D80: SNOW BLOWER SAARBRUKEN MTD E660G | E80: N-COCR | F80: HDE Heavy Duty Equipment | G80: Tengiz | H80: 1196B10459 | J80: 13562 | K80: =IFERROR(VLOOKUP(J80,'CC directory'!A:B,2,),"") -> ACTIVE | L80: =IFERROR(VLOOKUP(J80,'CC directory'!A:D,4,),"") -> 200 | M80: =VLOOKUP(J80,'CC directory'!A:I,9,) -> TCOV Maintenance | N80: =IFERROR(VLOOKUP(J80,'CC directory'!A:C,3,),"") -> Operations | O80: =IFERROR(VLOOKUP(J80,'CC directory'!A:F,6,),"") -> 209 | P80: =IFERROR(VLOOKUP(J80,'CC directory'!A:E,5,),"") -> Supply Chain Management | Q80: =IFERROR(VLOOKUP(J80,'CC directory'!A:H,8,),"") -> 310 | R80: =IFERROR(VLOOKUP(J80,'CC directory'!A:G,7,),"") -> Tengiz Facilities Management | S80: Tengiz Facilities Management | T80: ESS Facilities Maintenance | U80: 1483 | V80: Tengiz Fleet | Z80: Non-Critical | AA80: SAARBRUKEN | AB80: MTD E660G | AC80: EUR | AD80: 2387 | AE80: 2006 | AF80: 17 | AI80: 1 | AK80: 39356 | AL80: 20 | AM80: 39356 | AO80: 0 | AP80: 0 | AT80: BLWSN 004 | AU80: 105363 | AV80: 2012 | AW80: 2027 | AZ80: 1689 | BD80: =IF((BE80+BG80+BI80)>0, "YES", "NO") -> NO | BE80: 0 | BG80: 0 | BI80: 0 | BL80: Non-motorized HDE | BM80: =VLOOKUP(BL80,'directory all'!C:D,2,) -> GPS | BN80: Snow blower (do not use) | BQ80: N/A | BR80: N/A | BS80: N/A | BT80: N/A | BU80: N/A | BV80: N/A | BW80: N/A | BX80: N/A | CG80: TFM: Konstantin Chernov / Maxat Yeshmaganbetov
A81: 270025 | B81: Active | C81: 233EAD | D81: TRUCK HD MULTI-PURPOSE WAUSAU-EVEREST SD | E81: TMF1 | F81: HDV Heavy Duty Vehicle | G81: Tengiz | H81: C26049 SN1040 | I81: C26049 SN1040 | J81: 13727 | K81: =IFERROR(VLOOKUP(J81,'CC directory'!A:B,2,),"") -> ACTIVE | L81: =IFERROR(VLOOKUP(J81,'CC directory'!A:D,4,),"") -> 200 | M81: =VLOOKUP(J81,'CC directory'!A:I,9,) -> Flight Ops & Charters | N81: =IFERROR(VLOOKUP(J81,'CC directory'!A:C,3,),"") -> Operations | O81: =IFERROR(VLOOKUP(J81,'CC directory'!A:F,6,),"") -> 209 | P81: =IFERROR(VLOOKUP(J81,'CC directory'!A:E,5,),"") -> Supply Chain Management | Q81: =IFERROR(VLOOKUP(J81,'CC directory'!A:H,8,),"") -> 321 | R81: =IFERROR(VLOOKUP(J81,'CC directory'!A:G,7,),"") -> Aviation & Logistics | S81: SCM Logistics | T81: Flight Ops & Charters | U81: 720 | V81: Tengiz fleet | Z81: Critical | AA81: WAUSAU-EVEREST | AB81: SD3131 | AC81: USD | AD81: 778825 | AE81: 2012 | AF81: 10 | AH81: 79607389 | AJ81: KGI 189698 | AK81: 41345 | AL81: 15 | AM81: 41349 | AO81: 4298 | AP81: 4298 | AR81: 16.00R20 | AS81: 16.00R20 | AT81: TRKWAU 001 | AU81: 170560 | AV81: 2028 | AW81: 2028 | AZ81: 722 | BA81: IN-LINE 6 | BB81: TC-561 | BC81: CC was changed from 13780 - Heavy Equipment Operations to 13727 - Flight Ops & Charters, according to the e-mail from TCO COCR Fleet Manager’s Amangeldy with confirmed by TCO Transportation Team Lead’s Erbol as of 04.10.2023 (Inbox - CC Change) | BD81: =IF((BE81+BG81+BI81)>0, "YES", "NO") -> YES | BE81: 1 | BF81: Wausau Everes 233EAD (ТШО 270025) | BG81: 1 | BH81: 233 EAD | BI81: 0 | BK81: Aerodrome | BL81: Self-propelled motorized (HDV/HDE) - Wheeled | BM81: =VLOOKUP(BL81,'directory all'!C:D,2,) -> Mileage, engine hours, GPS | BN81: Snow plough truck | BO81: Assigned | BP81: Aerdrodrome purpose | BQ81: 18806 (Truck only) | BR81: 62,000 LBS GVW | BS81: 12 | BT81: 100 (4ea) | BU81: 120 A | BW81: 10 bar | BY81: TCO SCM Logistics | BZ81: 3370 | CA81: opstng@tengizchevroil.com | CB81: YES | CC81: 40 | CD81: 1.5 | CE81: Backup | CG81: SCM Aviation: Nurzat Khairolla / Zhandos Ospankulov
A82: 270026 | B82: Active | C82: 234EAD | D82: TRUCK HD MULTI-PURPOSE WAUSAU-EVEREST SD | E82: TMF1 | F82: HDV Heavy Duty Vehicle | G82: Tengiz | H82: C26049 SN1041 | I82: C26049 SN1041 | J82: 13727 | K82: =IFERROR(VLOOKUP(J82,'CC directory'!A:B,2,),"") -> ACTIVE | L82: =IFERROR(VLOOKUP(J82,'CC directory'!A:D,4,),"") -> 200 | M82: =VLOOKUP(J82,'CC directory'!A:I,9,) -> Flight Ops & Charters | N82: =IFERROR(VLOOKUP(J82,'CC directory'!A:C,3,),"") -> Operations | O82: =IFERROR(VLOOKUP(J82,'CC directory'!A:F,6,),"") -> 209 | P82: =IFERROR(VLOOKUP(J82,'CC directory'!A:E,5,),"") -> Supply Chain Management | Q82: =IFERROR(VLOOKUP(J82,'CC directory'!A:H,8,),"") -> 321 | R82: =IFERROR(VLOOKUP(J82,'CC directory'!A:G,7,),"") -> Aviation & Logistics | S82: SCM Logistics | T82: Flight Ops & Charters | U82: 721 | V82: Tengiz fleet | Z82: Critical | AA82: WAUSAU-EVEREST | AB82: SD3131 | AC82: USD | AD82: 778825 | AE82: 2012 | AF82: 10 | AH82: 79605762 | AJ82: KGI 189699 | AK82: 41345 | AL82: 15 | AM82: 41350 | AO82: 4420 | AP82: 4420 | AQ82: 3995.00 mh#1 | AR82: 16.00R20 | AS82: 16.00R20 | AT82: TRKWAU 001 | AU82: 170560 | AV82: 2028 | AW82: 2028 | AZ82: 723 | BA82: IN-LINE 6 | BB82: TC-561 | BC82: CC was changed from 13780 - Heavy Equipment Operations to 13727 - Flight Ops & Charters, according to the e-mail from TCO COCR Fleet Manager’s Amangeldy with confirmed by TCO Transportation Team Lead’s Erbol as of 04.10.2023 (Inbox - CC Change) | BD82: =IF((BE82+BG82+BI82)>0, "YES", "NO") -> YES | BE82: 1 | BF82: Wausau Everes 234EAD (ТШО 270026) | BG82: 1 | BH82: 234 EAD | BI82: 0 | BK82: Aerodrome | BL82: Self-propelled motorized (HDV/HDE) - Wheeled | BM82: =VLOOKUP(BL82,'directory all'!C:D,2,) -> Mileage, engine hours, GPS | BN82: Snow plough truck | BO82: Assigned | BP82: Aerdrodrome purpose | BQ82: 18806 (Truck only) | BR82: 62,000 LBS GVW | BS82: 12 | BT82: 100 (4ea) | BU82: 120 A | BW82: 10 bar | BY82: TCO SCM Logistics | BZ82: 3370 | CA82: opstng@tengizchevroil.com | CB82: YES | CC82: 40 | CD82: 1.5 | CG82: SCM Aviation: Nurzat Khairolla / Zhandos Ospankulov
A83: 270031 | B83: Sent to BP | D83: BLOWER - SNOW 7.4 KW/3600 RPM MTD ME76 | E83: N-COCR | F83: HDE Heavy Duty Equipment | G83: Tengiz | H83: 1H213B30282 | I83: 1H213B30282 | J83: 13566 | K83: =IFERROR(VLOOKUP(J83,'CC directory'!A:B,2,),"") -> ACTIVE | L83: =IFERROR(VLOOKUP(J83,'CC directory'!A:D,4,),"") -> 200 | M83: =VLOOKUP(J83,'CC directory'!A:I,9,) -> Shanyrak Village Maitenance | N83: =IFERROR(VLOOKUP(J83,'CC directory'!A:C,3,),"") -> Operations | O83: =IFERROR(VLOOKUP(J83,'CC directory'!A:F,6,),"") -> 209 | P83: =IFERROR(VLOOKUP(J83,'CC directory'!A:E,5,),"") -> Supply Chain Management | Q83: =IFERROR(VLOOKUP(J83,'CC directory'!A:H,8,),"") -> 310 | R83: =IFERROR(VLOOKUP(J83,'CC directory'!A:G,7,),"") -> Tengiz Facilities Management | S83: Tengiz Facilities Management | T83: FM SV MAINT | U83: 1484 | V83: Tengiz Fleet | Z83: Non-Critical | AA83: MTD | AB83: ME76 | AC83: KZT | AD83: 320000 | AE83: 2013 | AF83: 9 | AH83: 483-SHB1306221A0862 | AI83: 1 | AK83: 41771 | AL83: 20 | AM83: 41641 | AO83: 0 | AP83: 0 | AR83: 16X6.50 | AS83: 16X6.50 | AT83: GRM 037 | AU83: SHFM55676 | AV83: 2019 | AW83: 2034 | AZ83: 1690 | BD83: =IF((BE83+BG83+BI83)>0, "YES", "NO") -> NO | BE83: 0 | BG83: 0 | BI83: 0 | BL83: Non-motorized HDE | BM83: =VLOOKUP(BL83,'directory all'!C:D,2,) -> GPS | BN83: Snow blower (do not use) | BQ83: N/A | BR83: N/A | BS83: N/A | BT83: N/A | BU83: N/A | BV83: N/A | BW83: N/A | BX83: N/A | BZ83: 4559 | CG83: TFM: Konstantin Chernov / Maxat Yeshmaganbetov
A84: 270032 | B84: Sent to BP | D84: BLOWER - SNOW 7.4 KW/3600 RPM MTD ME76 | E84: N-COCR | F84: HDE Heavy Duty Equipment | G84: Tengiz | H84: 1H213B30329 | I84: 1H213B30329 | J84: 13566 | K84: =IFERROR(VLOOKUP(J84,'CC directory'!A:B,2,),"") -> ACTIVE | L84: =IFERROR(VLOOKUP(J84,'CC directory'!A:D,4,),"") -> 200 | M84: =VLOOKUP(J84,'CC directory'!A:I,9,) -> Shanyrak Village Maitenance | N84: =IFERROR(VLOOKUP(J84,'CC directory'!A:C,3,),"") -> Operations | O84: =IFERROR(VLOOKUP(J84,'CC directory'!A:F,6,),"") -> 209 | P84: =IFERROR(VLOOKUP(J84,'CC directory'!A:E,5,),"") -> Supply Chain Management | Q84: =IFERROR(VLOOKUP(J84,'CC directory'!A:H,8,),"") -> 310 | R84: =IFERROR(VLOOKUP(J84,'CC directory'!A:G,7,),"") -> Tengiz Facilities Management | S84: Tengiz Facilities Management | T84: FM SV MAINT | U84: 1485 | V84: Tengiz Fleet | Z84: Non-Critical | AA84: MTD | AB84: ME76 | AC84: KZT | AD84: 320000 | AE84: 2013 | AF84: 9 | AH84: 483-SHB1306221A0901 | AI84: 1 | AK84: 41771 | AL84: 20 | AM84: 41641 | AO84: 0 | AP84: 0 | AR84: 16X6.50 | AS84: 16X6.50 | AT84: GRM 037 | AU84: SHFM55676 | AV84: 2019 | AW84: 2034 | AZ84: 1691 | BD84: =IF((BE84+BG84+BI84)>0, "YES", "NO") -> NO | BE84: 0 | BG84: 0 | BI84: 0 | BL84: Non-motorized HDE | BM84: =VLOOKUP(BL84,'directory all'!C:D,2,) -> GPS | BN84: Snow blower (do not use) | BQ84: N/A | BR84: N/A | BS84: N/A | BT84: N/A | BU84: N/A | BV84: N/A | BW84: N/A | BX84: N/A | BZ84: 4559 | CG84: TFM: Konstantin Chernov / Maxat Yeshmaganbetov
A85: 270033 | B85: Sent to BP | D85: BLOWER - SNOW 7.4 KW/3600 RPM MTD ME76 | E85: N-COCR | F85: HDE Heavy Duty Equipment | G85: Tengiz | H85: 1H213B30340 | I85: 1H213B30340 | J85: 13566 | K85: =IFERROR(VLOOKUP(J85,'CC directory'!A:B,2,),"") -> ACTIVE | L85: =IFERROR(VLOOKUP(J85,'CC directory'!A:D,4,),"") -> 200 | M85: =VLOOKUP(J85,'CC directory'!A:I,9,) -> Shanyrak Village Maitenance | N85: =IFERROR(VLOOKUP(J85,'CC directory'!A:C,3,),"") -> Operations | O85: =IFERROR(VLOOKUP(J85,'CC directory'!A:F,6,),"") -> 209 | P85: =IFERROR(VLOOKUP(J85,'CC directory'!A:E,5,),"") -> Supply Chain Management | Q85: =IFERROR(VLOOKUP(J85,'CC directory'!A:H,8,),"") -> 310 | R85: =IFERROR(VLOOKUP(J85,'CC directory'!A:G,7,),"") -> Tengiz Facilities Management | S85: Tengiz Facilities Management | T85: FM SV MAINT | U85: 1486 | V85: Tengiz Fleet | Z85: Non-Critical | AA85: MTD | AB85: ME76 | AC85: KZT | AD85: 320000 | AE85: 2013 | AF85: 9 | AH85: 483-SHB1207101A0558 | AI85: 1 | AK85: 41771 | AL85: 20 | AM85: 41641 | AO85: 0 | AP85: 0 | AR85: 16X6.50 | AS85: 16X6.50 | AT85: GRM 037 | AU85: SHFM55676 | AV85: 2019 | AW85: 2034 | AZ85: 1692 | BD85: =IF((BE85+BG85+BI85)>0, "YES", "NO") -> NO | BE85: 0 | BG85: 0 | BI85: 0 | BL85: Non-motorized HDE | BM85: =VLOOKUP(BL85,'directory all'!C:D,2,) -> GPS | BN85: Snow blower (do not use) | BQ85: N/A | BR85: N/A | BS85: N/A | BT85: N/A | BU85: N/A | BV85: N/A | BW85: N/A | BX85: N/A | BZ85: 4559 | CG85: TFM: Konstantin Chernov / Maxat Yeshmaganbetov
A86: 270034 | B86: Sent to BP | D86: BLOWER - SNOW 7.4 KW/3600 RPM MTD ME76 | E86: N-COCR | F86: HDE Heavy Duty Equipment | G86: Tengiz | H86: 1H213B30344 | I86: 1H213B30344 | J86: 13566 | K86: =IFERROR(VLOOKUP(J86,'CC directory'!A:B,2,),"") -> ACTIVE | L86: =IFERROR(VLOOKUP(J86,'CC directory'!A:D,4,),"") -> 200 | M86: =VLOOKUP(J86,'CC directory'!A:I,9,) -> Shanyrak Village Maitenance | N86: =IFERROR(VLOOKUP(J86,'CC directory'!A:C,3,),"") -> Operations | O86: =IFERROR(VLOOKUP(J86,'CC directory'!A:F,6,),"") -> 209 | P86: =IFERROR(VLOOKUP(J86,'CC directory'!A:E,5,),"") -> Supply Chain Management | Q86: =IFERROR(VLOOKUP(J86,'CC directory'!A:H,8,),"") -> 310 | R86: =IFERROR(VLOOKUP(J86,'CC directory'!A:G,7,),"") -> Tengiz Facilities Management | S86: Tengiz Facilities Management | T86: FM SV MAINT | U86: 1487 | V86: Tengiz Fleet | Z86: Non-Critical | AA86: MTD | AB86: ME76 | AC86: KZT | AD86: 320000 | AE86: 2013 | AF86: 9 | AH86: 483-SHB1207101A0554 | AI86: 1 | AK86: 41771 | AL86: 20 | AM86: 41641 | AO86: 0 | AP86: 0 | AR86: 16X6.50 | AS86: 16X6.50 | AT86: GRM 037 | AU86: SHFM55676 | AV86: 2019 | AW86: 2034 | AZ86: 1693 | BD86: =IF((BE86+BG86+BI86)>0, "YES", "NO") -> NO | BE86: 0 | BG86: 0 | BI86: 0 | BL86: Non-motorized HDE | BM86: =VLOOKUP(BL86,'directory all'!C:D,2,) -> GPS | BN86: Snow blower (do not use) | BQ86: N/A | BR86: N/A | BS86: N/A | BT86: N/A | BU86: N/A | BV86: N/A | BW86: N/A | BX86: N/A | BZ86: 3336 / 7068 | CG86: TFM: Konstantin Chernov / Maxat Yeshmaganbetov
A87: 270035 | B87: Sent to BP | D87: BLOWER - SNOW 7.4 KW/3600 RPM MTD ME76 | E87: N-COCR | F87: HDE Heavy Duty Equipment | G87: Tengiz | H87: 1H213B30346 | I87: 1H213B30346 | J87: 13566 | K87: =IFERROR(VLOOKUP(J87,'CC directory'!A:B,2,),"") -> ACTIVE | L87: =IFERROR(VLOOKUP(J87,'CC directory'!A:D,4,),"") -> 200 | M87: =VLOOKUP(J87,'CC directory'!A:I,9,) -> Shanyrak Village Maitenance | N87: =IFERROR(VLOOKUP(J87,'CC directory'!A:C,3,),"") -> Operations | O87: =IFERROR(VLOOKUP(J87,'CC directory'!A:F,6,),"") -> 209 | P87: =IFERROR(VLOOKUP(J87,'CC directory'!A:E,5,),"") -> Supply Chain Management | Q87: =IFERROR(VLOOKUP(J87,'CC directory'!A:H,8,),"") -> 310 | R87: =IFERROR(VLOOKUP(J87,'CC directory'!A:G,7,),"") -> Tengiz Facilities Management | S87: Tengiz Facilities Management | T87: FM SV MAINT | U87: 1488 | V87: Tengiz Fleet | Z87: Non-Critical | AA87: MTD | AB87: ME76 | AC87: KZT | AD87: 320000 | AE87: 2013 | AF87: 9 | AH87: 483-SHB1207101A0552 | AI87: 1 | AK87: 41771 | AL87: 20 | AM87: 41641 | AO87: 0 | AP87: 0 | AR87: 16X6.50 | AS87: 16X6.50 | AT87: GRM 037 | AU87: SHFM55676 | AV87: 2019 | AW87: 2034 | AZ87: 1694 | BD87: =IF((BE87+BG87+BI87)>0, "YES", "NO") -> NO | BE87: 0 | BG87: 0 | BI87: 0 | BL87: Non-motorized HDE | BM87: =VLOOKUP(BL87,'directory all'!C:D,2,) -> GPS | BN87: Snow blower (do not use) | BQ87: N/A | BR87: N/A | BS87: N/A | BT87: N/A | BU87: N/A | BV87: N/A | BW87: N/A | BX87: N/A | BZ87: 5158 | CG87: TFM: Konstantin Chernov / Maxat Yeshmaganbetov
A88: 270036 | B88: Sent to BP | D88: BLOWER - SNOW 7.4 KW/3600 RPM MTD ME76 | E88: N-COCR | F88: HDE Heavy Duty Equipment | G88: Tengiz | H88: 1H213B30341 | I88: 1H213B30341 | J88: 13566 | K88: =IFERROR(VLOOKUP(J88,'CC directory'!A:B,2,),"") -> ACTIVE | L88: =IFERROR(VLOOKUP(J88,'CC directory'!A:D,4,),"") -> 200 | M88: =VLOOKUP(J88,'CC directory'!A:I,9,) -> Shanyrak Village Maitenance | N88: =IFERROR(VLOOKUP(J88,'CC directory'!A:C,3,),"") -> Operations | O88: =IFERROR(VLOOKUP(J88,'CC directory'!A:F,6,),"") -> 209 | P88: =IFERROR(VLOOKUP(J88,'CC directory'!A:E,5,),"") -> Supply Chain Management | Q88: =IFERROR(VLOOKUP(J88,'CC directory'!A:H,8,),"") -> 310 | R88: =IFERROR(VLOOKUP(J88,'CC directory'!A:G,7,),"") -> Tengiz Facilities Management | S88: Tengiz Facilities Management | T88: FM SV MAINT | U88: 1489 | V88: Tengiz Fleet | Z88: Non-Critical | AA88: MTD | AB88: ME76 | AC88: KZT | AD88: 320000 | AE88: 2013 | AF88: 9 | AH88: 483-SHB1207101A0555 | AI88: 1 | AK88: 41771 | AL88: 20 | AM88: 41641 | AO88: 0 | AP88: 0 | AR88: 16X6.50 | AS88: 16X6.50 | AT88: GRM 037 | AU88: SHFM55676 | AV88: 2019 | AW88: 2034 | AZ88: 1695 | BD88: =IF((BE88+BG88+BI88)>0, "YES", "NO") -> NO | BE88: 0 | BG88: 0 | BI88: 0 | BL88: Non-motorized HDE | BM88: =VLOOKUP(BL88,'directory all'!C:D,2,) -> GPS | BN88: Snow blower (do not use) | BQ88: N/A | BR88: N/A | BS88: N/A | BT88: N/A | BU88: N/A | BV88: N/A | BW88: N/A | BX88: N/A | BZ88: 3336 / 7068 | CG88: TFM: Konstantin Chernov / Maxat Yeshmaganbetov
A89: 270037 | B89: Sent to BP | D89: SNOW BLOWER MTD OPTIMA ME66 | E89: N-COCR | F89: HDE Heavy Duty Equipment | G89: Tengiz | H89: 1H213B30338 | I89: 1H213B30338 | J89: 13566 | K89: =IFERROR(VLOOKUP(J89,'CC directory'!A:B,2,),"") -> ACTIVE | L89: =IFERROR(VLOOKUP(J89,'CC directory'!A:D,4,),"") -> 200 | M89: =VLOOKUP(J89,'CC directory'!A:I,9,) -> Shanyrak Village Maitenance | N89: =IFERROR(VLOOKUP(J89,'CC directory'!A:C,3,),"") -> Operations | O89: =IFERROR(VLOOKUP(J89,'CC directory'!A:F,6,),"") -> 209 | P89: =IFERROR(VLOOKUP(J89,'CC directory'!A:E,5,),"") -> Supply Chain Management | Q89: =IFERROR(VLOOKUP(J89,'CC directory'!A:H,8,),"") -> 310 | R89: =IFERROR(VLOOKUP(J89,'CC directory'!A:G,7,),"") -> Tengiz Facilities Management | S89: Tengiz Facilities Management | T89: FM SV MAINT | U89: 1490 | V89: Tengiz Fleet | Z89: Non-Critical | AA89: MTD | AB89: 31AY55T5678 | AC89: KZT | AD89: 0 | AE89: 2013 | AF89: 9 | AH89: 483-SHB1207101A0555 | AI89: 1 | AK89: 42167 | AL89: 20 | AM89: 42381 | AO89: 0 | AP89: 0 | AR89: 16X6.50 | AS89: 16X6.50 | AT89: BLWSN 003 | AV89: 2019 | AW89: 2034 | AZ89: 1696 | BD89: =IF((BE89+BG89+BI89)>0, "YES", "NO") -> NO | BE89: 0 | BG89: 0 | BI89: 0 | BL89: Not self-propelled motorized HDE | BM89: =VLOOKUP(BL89,'directory all'!C:D,2,) -> Engine hours, GPS | BN89: Snow blower (do not use) | BQ89: N/A | BR89: N/A | BS89: N/A | BT89: N/A | BU89: N/A | BV89: N/A | BW89: N/A | BX89: N/A | CG89: TFM: Konstantin Chernov / Maxat Yeshmaganbetov
A90: 270038 | B90: Sent to BP | D90: SNOW BLOWER MTD OPTIMA ME66 | E90: N-COCR | F90: HDE Heavy Duty Equipment | G90: Tengiz | H90: 1H213B30437 | I90: 1H213B30437 | J90: 13566 | K90: =IFERROR(VLOOKUP(J90,'CC directory'!A:B,2,),"") -> ACTIVE | L90: =IFERROR(VLOOKUP(J90,'CC directory'!A:D,4,),"") -> 200 | M90: =VLOOKUP(J90,'CC directory'!A:I,9,) -> Shanyrak Village Maitenance | N90: =IFERROR(VLOOKUP(J90,'CC directory'!A:C,3,),"") -> Operations | O90: =IFERROR(VLOOKUP(J90,'CC directory'!A:F,6,),"") -> 209 | P90: =IFERROR(VLOOKUP(J90,'CC directory'!A:E,5,),"") -> Supply Chain Management | Q90: =IFERROR(VLOOKUP(J90,'CC directory'!A:H,8,),"") -> 310 | R90: =IFERROR(VLOOKUP(J90,'CC directory'!A:G,7,),"") -> Tengiz Facilities Management | S90: Tengiz Facilities Management | T90: FM SV MAINT | U90: 1491 | V90: Tengiz Fleet | Z90: Non-Critical | AA90: MTD | AB90: 31AY55T5678 | AC90: KZT | AD90: 0 | AE90: 2013 | AF90: 9 | AH90: 483-SHB1207101A0555 | AI90: 1 | AK90: 42167 | AL90: 20 | AM90: 42381 | AO90: 0 | AP90: 0 | AR90: 16X6.50 | AS90: 16X6.50 | AT90: BLWSN 003 | AV90: 2019 | AW90: 2034 | AZ90: 1697 | BD90: =IF((BE90+BG90+BI90)>0, "YES", "NO") -> NO | BE90: 0 | BG90: 0 | BI90: 0 | BL90: Not self-propelled motorized HDE | BM90: =VLOOKUP(BL90,'directory all'!C:D,2,) -> Engine hours, GPS | BN90: Snow blower (do not use) | BQ90: N/A | BR90: N/A | BS90: N/A | BT90: N/A | BU90: N/A | BV90: N/A | BW90: N/A | BX90: N/A | CG90: TFM: Konstantin Chernov / Maxat Yeshmaganbetov
A91: 270039 | B91: Sent to BP | D91: SNOW BLOWER MTD OPTIMA ME66 | E91: N-COCR | F91: HDE Heavy Duty Equipment | G91: Tengiz | H91: 1H213B30347 | I91: 1H213B30347 | J91: 13566 | K91: =IFERROR(VLOOKUP(J91,'CC directory'!A:B,2,),"") -> ACTIVE | L91: =IFERROR(VLOOKUP(J91,'CC directory'!A:D,4,),"") -> 200 | M91: =VLOOKUP(J91,'CC directory'!A:I,9,) -> Shanyrak Village Maitenance | N91: =IFERROR(VLOOKUP(J91,'CC directory'!A:C,3,),"") -> Operations | O91: =IFERROR(VLOOKUP(J91,'CC directory'!A:F,6,),"") -> 209 | P91: =IFERROR(VLOOKUP(J91,'CC directory'!A:E,5,),"") -> Supply Chain Management | Q91: =IFERROR(VLOOKUP(J91,'CC directory'!A:H,8,),"") -> 310 | R91: =IFERROR(VLOOKUP(J91,'CC directory'!A:G,7,),"") -> Tengiz Facilities Management | S91: Tengiz Facilities Management | T91: FM SV MAINT | U91: 1492 | V91: Tengiz Fleet | Z91: Non-Critical | AA91: MTD | AB91: 31AY55T5678 | AC91: KZT | AD91: 0 | AE91: 2013 | AF91: 9 | AH91: 483-SHB1207101A0555 | AI91: 1 | AK91: 42167 | AL91: 20 | AM91: 42381 | AO91: 0 | AP91: 0 | AR91: 16X6.50 | AS91: 16X6.50 | AT91: BLWSN 003 | AV91: 2019 | AW91: 2034 | AZ91: 1698 | BD91: =IF((BE91+BG91+BI91)>0, "YES", "NO") -> NO | BE91: 0 | BG91: 0 | BI91: 0 | BL91: Not self-propelled motorized HDE | BM91: =VLOOKUP(BL91,'directory all'!C:D,2,) -> Engine hours, GPS | BN91: Snow blower (do not use) | BQ91: N/A | BR91: N/A | BS91: N/A | BT91: N/A | BU91: N/A | BV91: N/A | BW91: N/A | BX91: N/A | CG91: TFM: Konstantin Chernov / Maxat Yeshmaganbetov
A92: 301011 | B92: Sent to BP | D92: COMPRESSOR AIR DIESEL 22KW 530L/MIN BAUE | E92: N-COCR | F92: HDE Heavy Duty Equipment | G92: Tengiz | H92: 21201211 | I92: 21201211 | J92: 9601120356 | K92: =IFERROR(VLOOKUP(J92,'CC directory'!A:B,2,),"") -> ACTIVE | L92: =IFERROR(VLOOKUP(J92,'CC directory'!A:D,4,),"") -> 200 | M92: =VLOOKUP(J92,'CC directory'!A:I,9,) -> Sp Accum Drill Rig Support&TCC | N92: =IFERROR(VLOOKUP(J92,'CC directory'!A:C,3,),"") -> Operations | O92: =IFERROR(VLOOKUP(J92,'CC directory'!A:F,6,),"") -> 203 | P92: =IFERROR(VLOOKUP(J92,'CC directory'!A:E,5,),"") -> Drilling | Q92: =IFERROR(VLOOKUP(J92,'CC directory'!A:H,8,),"") -> 500 | R92: =IFERROR(VLOOKUP(J92,'CC directory'!A:G,7,),"") -> Drilling | S92: Drilling | T92: SpecAccum-Drilling Rig Support | U92: 1493 | V92: Tengiz Fleet | Z92: Non-Critical | AA92: BAUER | AB92: KAR150-20DA-H | AC92: GBP | AD92: 28571 | AE92: 2011 | AF92: 11 | AH92: 5946312 | AI92: 1 | AK92: 41095 | AL92: 20 | AM92: 41615 | AO92: 0 | AP92: 0 | AT92: CMP 024 | AU92: 150355 | AV92: 2017 | AW92: 2032 | AZ92: 1699 | BD92: =IF((BE92+BG92+BI92)>0, "YES", "NO") -> NO | BE92: 0 | BG92: 0 | BI92: 0 | BK92: Wells, Field | BL92: Not self-propelled motorized HDE | BM92: =VLOOKUP(BL92,'directory all'!C:D,2,) -> Engine hours, GPS | BN92: Air compressor motorized | BO92: Assigned | BP92: Wells SIP / Breathing Air | BQ92: N/A | BR92: N/A | BS92: N/A | BT92: N/A | BU92: N/A | BV92: N/A | BW92: 4500 psi | BX92: 31.8 m³/h | BY92: Akbarys | BZ92: 7654 | CA92: TCOAKOPS@tengizchevroil.com | CF92: Not for outside use. Dedicated SIP compressor. | CG92: Drilling: Kyle Harrelson / Joseph Bothner
A93: 301012 | B93: Sent to BP | D93: COMPRESSOR AIR DIESEL 22KW 530L/MIN BAUE | E93: N-COCR | F93: HDE Heavy Duty Equipment | G93: Tengiz | H93: 19060311 | I93: 19060311 | J93: 9601120356 | K93: =IFERROR(VLOOKUP(J93,'CC directory'!A:B,2,),"") -> ACTIVE | L93: =IFERROR(VLOOKUP(J93,'CC directory'!A:D,4,),"") -> 200 | M93: =VLOOKUP(J93,'CC directory'!A:I,9,) -> Sp Accum Drill Rig Support&TCC | N93: =IFERROR(VLOOKUP(J93,'CC directory'!A:C,3,),"") -> Operations | O93: =IFERROR(VLOOKUP(J93,'CC directory'!A:F,6,),"") -> 203 | P93: =IFERROR(VLOOKUP(J93,'CC directory'!A:E,5,),"") -> Drilling | Q93: =IFERROR(VLOOKUP(J93,'CC directory'!A:H,8,),"") -> 500 | R93: =IFERROR(VLOOKUP(J93,'CC directory'!A:G,7,),"") -> Drilling | S93: Drilling | T93: SpecAccum-Drilling Rig Support | U93: 1494 | V93: Tengiz Fleet | Z93: Non-Critical | AA93: BAUER | AB93: KAR150-20DA-H | AC93: GBP | AD93: 28571 | AE93: 2011 | AF93: 11 | AH93: 5946312 | AI93: 1 | AK93: 41095 | AL93: 20 | AM93: 41615 | AO93: 0 | AP93: 0 | AT93: CMP 024 | AU93: 160471 | AV93: 2017 | AW93: 2032 | AZ93: 1700 | BD93: =IF((BE93+BG93+BI93)>0, "YES", "NO") -> NO | BE93: 0 | BG93: 0 | BI93: 0 | BK93: Wells, Field | BL93: Not self-propelled motorized HDE | BM93: =VLOOKUP(BL93,'directory all'!C:D,2,) -> Engine hours, GPS | BN93: Air compressor motorized | BO93: Assigned | BP93: Wells SIP / Breathing Air | BQ93: N/A | BR93: N/A | BS93: N/A | BT93: N/A | BU93: N/A | BV93: N/A | BW93: 4500 psi | BX93: 31.8 m³/h | BY93: Akbarys | BZ93: 7654 | CA93: TCOAKOPS@tengizchevroil.com | CF93: Not for outside use. Dedicated SIP compressor. | CG93: Drilling: Kyle Harrelson / Joseph Bothner
A94: 301013 | B94: Sent to BP | D94: COMPRESSOR AIR DIESEL 22KW 530L/MIN BAUE | E94: N-COCR | F94: HDE Heavy Duty Equipment | G94: Tengiz | H94: 250521013 | I94: 250521013 | J94: 20302 | K94: =IFERROR(VLOOKUP(J94,'CC directory'!A:B,2,),"") -> ACTIVE | L94: =IFERROR(VLOOKUP(J94,'CC directory'!A:D,4,),"") -> 200 | M94: =VLOOKUP(J94,'CC directory'!A:I,9,) -> Drilling ERT | N94: =IFERROR(VLOOKUP(J94,'CC directory'!A:C,3,),"") -> Operations | O94: =IFERROR(VLOOKUP(J94,'CC directory'!A:F,6,),"") -> 203 | P94: =IFERROR(VLOOKUP(J94,'CC directory'!A:E,5,),"") -> Drilling | Q94: =IFERROR(VLOOKUP(J94,'CC directory'!A:H,8,),"") -> 500 | R94: =IFERROR(VLOOKUP(J94,'CC directory'!A:G,7,),"") -> Drilling | S94: Drilling | T94: Drilling ERT | U94: 1495 | V94: Tengiz Fleet | Z94: Non-Critical | AA94: BAUER | AB94: KAR150-20DA-HU | AC94: GBP | AD94: 33975 | AE94: 2013 | AF94: 9 | AH94: 4325202100 | AI94: 1 | AK94: 41732 | AL94: 20 | AM94: 41885 | AO94: 0 | AP94: 0 | AT94: CMP 024 | AU94: 192443 | AV94: 2024 | AW94: 2034 | AZ94: 1701 | BD94: =IF((BE94+BG94+BI94)>0, "YES", "NO") -> NO | BE94: 0 | BG94: 0 | BI94: 0 | BK94: Wells, Field | BL94: Not self-propelled motorized HDE | BM94: =VLOOKUP(BL94,'directory all'!C:D,2,) -> Engine hours, GPS | BN94: Air compressor motorized | BO94: Assigned | BP94: Wells SIP / Breathing Air | BQ94: N/A | BR94: N/A | BS94: N/A | BT94: N/A | BU94: N/A | BV94: N/A | BW94: 4500 psi | BX94: 31.8 m³/h | BY94: Akbarys | BZ94: 7654 | CA94: TCOAKOPS@tengizchevroil.com | CF94: Not for outside use. Dedicated SIP compressor. | CG94: Drilling: Kyle Harrelson / Joseph Bothner
A95: 301014 | B95: Sent to BP | D95: COMPRESSOR AIR DIESEL 22KW 530L/MIN BAUE | E95: N-COCR | F95: HDE Heavy Duty Equipment | G95: Tengiz | H95: 250511013 | I95: 250511013 | J95: 20302 | K95: =IFERROR(VLOOKUP(J95,'CC directory'!A:B,2,),"") -> ACTIVE | L95: =IFERROR(VLOOKUP(J95,'CC directory'!A:D,4,),"") -> 200 | M95: =VLOOKUP(J95,'CC directory'!A:I,9,) -> Drilling ERT | N95: =IFERROR(VLOOKUP(J95,'CC directory'!A:C,3,),"") -> Operations | O95: =IFERROR(VLOOKUP(J95,'CC directory'!A:F,6,),"") -> 203 | P95: =IFERROR(VLOOKUP(J95,'CC directory'!A:E,5,),"") -> Drilling | Q95: =IFERROR(VLOOKUP(J95,'CC directory'!A:H,8,),"") -> 500 | R95: =IFERROR(VLOOKUP(J95,'CC directory'!A:G,7,),"") -> Drilling | S95: Drilling | T95: Drilling ERT | U95: 1496 | V95: Tengiz Fleet | Z95: Non-Critical | AA95: BAUER | AB95: KAR150-20DA-HU | AC95: GBP | AD95: 33975 | AE95: 2013 | AF95: 9 | AH95: 4325202100 | AI95: 1 | AK95: 41732 | AL95: 20 | AM95: 41885 | AO95: 0 | AP95: 0 | AT95: CMP 024 | AU95: 192443 | AV95: 2024 | AW95: 2034 | AZ95: 1702 | BD95: =IF((BE95+BG95+BI95)>0, "YES", "NO") -> NO | BE95: 0 | BG95: 0 | BI95: 0 | BK95: Wells, Field | BL95: Not self-propelled motorized HDE | BM95: =VLOOKUP(BL95,'directory all'!C:D,2,) -> Engine hours, GPS | BN95: Air compressor motorized | BO95: Assigned | BP95: Wells SIP / Breathing Air | BQ95: N/A | BR95: N/A | BS95: N/A | BT95: N/A | BU95: N/A | BV95: N/A | BW95: 4500 psi | BX95: 31.8 m³/h | BY95: Akbarys | BZ95: 7654 | CA95: TCOAKOPS@tengizchevroil.com | CF95: Not for outside use. Dedicated SIP compressor. | CG95: Drilling: Kyle Harrelson / Joseph Bothner
A96: 301015 | B96: Sent to BP | D96: COMPRESSOR AIR DIESEL 22KW 530L/MIN BAUE | E96: N-COCR | F96: HDE Heavy Duty Equipment | G96: Tengiz | H96: 0028401215 - 1 | J96: 20302 | K96: =IFERROR(VLOOKUP(J96,'CC directory'!A:B,2,),"") -> ACTIVE | L96: =IFERROR(VLOOKUP(J96,'CC directory'!A:D,4,),"") -> 200 | M96: =VLOOKUP(J96,'CC directory'!A:I,9,) -> Drilling ERT | N96: =IFERROR(VLOOKUP(J96,'CC directory'!A:C,3,),"") -> Operations | O96: =IFERROR(VLOOKUP(J96,'CC directory'!A:F,6,),"") -> 203 | P96: =IFERROR(VLOOKUP(J96,'CC directory'!A:E,5,),"") -> Drilling | Q96: =IFERROR(VLOOKUP(J96,'CC directory'!A:H,8,),"") -> 500 | R96: =IFERROR(VLOOKUP(J96,'CC directory'!A:G,7,),"") -> Drilling | S96: Drilling | T96: Drilling ERT | U96: 1497 | V96: Tengiz Fleet | Z96: Non-Critical | AA96: BAUER | AB96: IK150 MKIIV001 | AC96: GBP | AD96: 43778 | AE96: 2015 | AF96: 7 | AI96: 1 | AK96: 42979 | AL96: 20 | AM96: 42464 | AO96: 0 | AP96: 0 | AT96: CMP 035 | AU96: 234435 | AV96: 2026 | AW96: 2036 | AZ96: 1703 | BD96: =IF((BE96+BG96+BI96)>0, "YES", "NO") -> NO | BE96: 0 | BG96: 0 | BI96: 0 | BK96: Wells, Field | BL96: Not self-propelled motorized HDE | BM96: =VLOOKUP(BL96,'directory all'!C:D,2,) -> Engine hours, GPS | BN96: Air compressor motorized | BO96: Assigned | BP96: Wells SIP / Breathing Air | BQ96: N/A | BR96: N/A | BS96: N/A | BT96: N/A | BU96: N/A | BV96: N/A | BW96: 4500 psi | BX96: 31.8 m³/h | BY96: Akbarys | BZ96: 7654 | CA96: TCOAKOPS@tengizchevroil.com | CF96: Not for outside use. Dedicated SIP compressor. | CG96: Drilling: Kyle Harrelson / Joseph Bothner
A97: 301016 | B97: Sent to BP | D97: COMPRESSOR AIR DIESEL 22KW 530L/MIN BAUE | E97: N-COCR | F97: HDE Heavy Duty Equipment | G97: Tengiz | H97: 0028401215 - 2 | J97: 20302 | K97: =IFERROR(VLOOKUP(J97,'CC directory'!A:B,2,),"") -> ACTIVE | L97: =IFERROR(VLOOKUP(J97,'CC directory'!A:D,4,),"") -> 200 | M97: =VLOOKUP(J97,'CC directory'!A:I,9,) -> Drilling ERT | N97: =IFERROR(VLOOKUP(J97,'CC directory'!A:C,3,),"") -> Operations | O97: =IFERROR(VLOOKUP(J97,'CC directory'!A:F,6,),"") -> 203 | P97: =IFERROR(VLOOKUP(J97,'CC directory'!A:E,5,),"") -> Drilling | Q97: =IFERROR(VLOOKUP(J97,'CC directory'!A:H,8,),"") -> 500 | R97: =IFERROR(VLOOKUP(J97,'CC directory'!A:G,7,),"") -> Drilling | S97: Drilling | T97: Drilling ERT | U97: 1498 | V97: Tengiz Fleet | Z97: Non-Critical | AA97: BAUER | AB97: IK150 MKIIV002 | AC97: GBP | AD97: 43778 | AE97: 2015 | AF97: 7 | AI97: 1 | AK97: 42979 | AL97: 20 | AM97: 42464 | AO97: 0 | AP97: 0 | AT97: CMP 035 | AU97: 234435 | AV97: 2026 | AW97: 2036 | AZ97: 1704 | BD97: =IF((BE97+BG97+BI97)>0, "YES", "NO") -> NO | BE97: 0 | BG97: 0 | BI97: 0 | BK97: Wells, Field | BL97: Not self-propelled motorized HDE | BM97: =VLOOKUP(BL97,'directory all'!C:D,2,) -> Engine hours, GPS | BN97: Air compressor motorized | BO97: Assigned | BP97: Wells SIP / Breathing Air | BQ97: N/A | BR97: N/A | BS97: N/A | BT97: N/A | BU97: N/A | BV97: N/A | BW97: 4500 psi | BX97: 31.8 m³/h | BY97: Akbarys | BZ97: 7654 | CA97: TCOAKOPS@tengizchevroil.com | CF97: Not for outside use. Dedicated SIP compressor. | CG97: Drilling: Kyle Harrelson / Joseph Bothner
A98: 301019 | B98: Active | D98: COMPRESSOR AIR DIESEL UKS 400 on KAMAZ | E98: TMF1 | F98: HDE Heavy Duty Equipment | G98: Tengiz | H98: 181009 | I98: 181009 | J98: 13780 | K98: =IFERROR(VLOOKUP(J98,'CC directory'!A:B,2,),"") -> ACTIVE | L98: =IFERROR(VLOOKUP(J98,'CC directory'!A:D,4,),"") -> 200 | M98: =VLOOKUP(J98,'CC directory'!A:I,9,) -> Heavy Equipment Operations | N98: =IFERROR(VLOOKUP(J98,'CC directory'!A:C,3,),"") -> Operations | O98: =IFERROR(VLOOKUP(J98,'CC directory'!A:F,6,),"") -> 209 | P98: =IFERROR(VLOOKUP(J98,'CC directory'!A:E,5,),"") -> Supply Chain Management | Q98: =IFERROR(VLOOKUP(J98,'CC directory'!A:H,8,),"") -> 322 | R98: =IFERROR(VLOOKUP(J98,'CC directory'!A:G,7,),"") -> Tengiz Ground Transportation | S98: SCM Logistics | T98: Heavy Equipment Operations | U98: 724 | V98: Tengiz fleet | Z98: Non-Critical | AA98: UKS-400 | AB98: VS-2.3/230 | AC98: KZT | AD98: 65089285 | AE98: 2018 | AF98: 4 | AH98: 125929 | AK98: 43432 | AL98: 20 | AM98: 43454 | AO98: 11202 | AP98: 11202 | AQ98: 1736.00 mh#1 | AT98: CMP 026 | AU98: 289934 | AV98: 2028 | AW98: 2038 | AY98: YES | AZ98: 726 | BD98: =IF((BE98+BG98+BI98)>0, "YES", "NO") -> YES | BE98: 1 | BF98: KAMAZ компрессор (ТШО 301019) | BG98: 0 | BI98: 0 | BK98: Industrial Base | BL98: Not self-propelled motorized HDE | BM98: =VLOOKUP(BL98,'directory all'!C:D,2,) -> Engine hours, GPS | BN98: Air compressor motorized | BO98: Shared without conditions | BQ98: N/A | BR98: N/A | BS98: N/A | BT98: N/A | BU98: N/A | BV98: N/A | BW98: 400 CFM | BX98: 678 m³/h | BY98: TCO SCM Logistics | BZ98: 2889 | CB98: YES | CD98: 1.5 | CG98: SCM Logistics: Yerbol Nauryzbay / Yerlan Yeshmagambetov
A99: 301020 | B99: Active | C99: N/A | D99: COMPRESSOR AIR DIESEL UKS 400 on KAMAZ | E99: TMF1 | F99: HDE Heavy Duty Equipment | G99: Tengiz | H99: 010723 | I99: 010723 | J99: 13780 | K99: =IFERROR(VLOOKUP(J99,'CC directory'!A:B,2,),"") -> ACTIVE | L99: =IFERROR(VLOOKUP(J99,'CC directory'!A:D,4,),"") -> 200 | M99: =VLOOKUP(J99,'CC directory'!A:I,9,) -> Heavy Equipment Operations | N99: =IFERROR(VLOOKUP(J99,'CC directory'!A:C,3,),"") -> Operations | O99: =IFERROR(VLOOKUP(J99,'CC directory'!A:F,6,),"") -> 209 | P99: =IFERROR(VLOOKUP(J99,'CC directory'!A:E,5,),"") -> Supply Chain Management | Q99: =IFERROR(VLOOKUP(J99,'CC directory'!A:H,8,),"") -> 322 | R99: =IFERROR(VLOOKUP(J99,'CC directory'!A:G,7,),"") -> Tengiz Ground Transportation | S99: SCM Logistics | T99: Heavy Equipment Operations | U99: 1443 | V99: Tengiz Fleet | Y99: 45172 | Z99: Critical | AA99: UKS-400В | AB99: VS-2.3/400 | AE99: 2023 | AK99: 45169 | AM99: 45172 | AT99: CMP 034 | AU99: 383361 | AZ99: 1468 | BC99: The new compressor on Kamaz TCO# 126-032 was issued from CC 13780 - Registration Department to СС 13780 - Heavy Equipment Operations, according to the acceptance act as of 03.10.2023 and e-mail from Registration Department as of 07.10.2023. (Inbox-CC change). | BD99: =IF((BE99+BG99+BI99)>0, "YES", "NO") -> YES | BE99: 1 | BF99: Компрессор ТСО301020 | BG99: 0 | BI99: 0 | BK99: Industrial Base | BL99: Not self-propelled motorized HDE | BM99: =VLOOKUP(BL99,'directory all'!C:D,2,) -> Engine hours, GPS | BN99: Air compressor motorized | BO99: Shared without conditions | BQ99: N/A | BR99: N/A | BS99: N/A | BT99: N/A | BU99: N/A | BV99: N/A | BW99: 400 CFM | BX99: 678 m³/h | BY99: TCO SCM Logistics | BZ99: 5666 | CB99: YES | CD99: 1.5 | CG99: SCM Logistics: Yerbol Nauryzbay / Yerlan Yeshmagambetov
A100: 301021 | B100: Active | C100: N/A | D100: AIR SCREW COMPRESSOR EKOMAK | E100: N-COCR | F100: HDE Heavy Duty Equipment | G100: Tengiz | H100: 112143 | J100: 20145 | K100: =IFERROR(VLOOKUP(J100,'CC directory'!A:B,2,),"") -> ACTIVE | L100: =IFERROR(VLOOKUP(J100,'CC directory'!A:D,4,),"") -> 131 | M100: =VLOOKUP(J100,'CC directory'!A:I,9,) -> SCP Concreate Batch Plant | N100: =IFERROR(VLOOKUP(J100,'CC directory'!A:C,3,),"") -> Projects | O100: =IFERROR(VLOOKUP(J100,'CC directory'!A:F,6,),"") -> 320 | P100: =IFERROR(VLOOKUP(J100,'CC directory'!A:E,5,),"") -> Construction Manager | Q100: =IFERROR(VLOOKUP(J100,'CC directory'!A:H,8,),"") -> 109 | R100: =IFERROR(VLOOKUP(J100,'CC directory'!A:G,7,),"") -> SCP Construction | S100: SCP Construction | T100: SCP Concreate Batch Plant | U100: 2173 | V100: Tengiz Fleet | W100: Allocated | Y100: 45235 | Z100: Non-Critical | AA100: EKOMAK | AB100: DMD150C | AE100: 2014 | AL100: 10 | AM100: 45235 | AT100: CMP 028 | AU100: CW1895079 | AZ100: 2380 | BD100: =IF((BE100+BG100+BI100)>0, "YES", "NO") -> NO | BE100: 0 | BG100: 0 | BI100: 0 | BK100: CC-CONCRETE BATCH PLANT | BL100: Stationary HDE | BM100: =VLOOKUP(BL100,'directory all'!C:D,2,) -> Engine hours, GPS | BN100: Air compressor electric | BO100: Assigned | BP100: CBP Production line | BQ100: N/A | BR100: N/A | BS100: N/A | BT100: N/A | BU100: N/A | BV100: N/A | BW100: 53 CFM | BX100: 15 m³/h | BY100: PCG/CBP BP | BZ100: 4775 | CA100: fecgt@tengizchevroil.com | CG100: Construction: Nurlan Issabekov / David Williams
...

Sheet Written off equipement
A1: General info | B1: General info | C1: General info | D1: General info | E1: General info | F1: General info | G1: General info | H1: General info | I1: General info | J1: General info | K1: General info | L1: General info | M1: General info | N1: General info | O1: General info | P1: General info | Q1: General info | R1: General info | S1: General info | T1: General info | U1: From report | V1: From report | W1: From report | X1: From report | Y1: From report | Z1: From report | AA1: From report | AB1: From report | AC1: From report | AD1: From report | AE1: From report | AF1: From report | AG1: From report | AH1: From report | AI1: From report | AJ1: From report | AK1: From report | AL1: From report | AM1: From report | AN1: From report | AO1: From report | AP1: From report | AQ1: From report | AR1: From report | AS1: From report | AT1: From report | AU1: From report | AV1: From report | AW1: From report | AX1: From report | AY1: From report | AZ1: From report | BA1: From report | BB1: From report | BC1: From report | BD1: Tracker info | BE1: Tracker info | BF1: Tracker info | BG1: Tracker info | BH1: Tracker info | BI1: Tracker info | BJ1: Tracker info | BK1: Additional info | BL1: Additional info | BM1: Additional info | BN1: Additional info | BO1: Additional info | BQ1: Additional info | BS1: Additional info | BW1: Additional info | BY1: Additional info | BZ1: Additional info | CA1: Additional info | CB1: Additional info | CF1: Additional info
K2: derived fromCC | L2: derived fromCC | M2: derived fromCC | N2: derived fromCC | O2: derived fromCC | P2: derived fromCC | Q2: derived fromCC | R2: derived fromCC | S2: derived fromCC | BO2: Equipment Usage Status | BQ2: Loading capacity / Грузоподьемность | BS2: Generator specifications | BW2: Compressor specifications | CB2: Target utlization
A3: Equipment | B3: Operation Status | C3: License | D3: Description | E3: Service Zone | F3: Class | G3: Location | H3: Serial Number | I3: VIN/Chassis No | J3: CC code | K3: CC status | L3: Division code | M3: CC name | N3: Division name | O3: Group code | P3: Group name | Q3: Department code | R3: Department name from WP | S3: Department name | T3: User Department (from Report) | U3: Title | V3: Fleet | W3: Allocation | X3: Writeoff Status | Y3: Fleet Active Date | Z3: Criticality | AA3: Manufacturer | AB3: Model | AC3: Currency | AD3: Capital Cost | AE3: Year | AF3: Age of Fleet (Yrs) | AG3: Body No | AH3: Engine No | AI3: Date of Registr. In GAI | AJ3: Technical Passport No | AK3: Date Acquired by user | AL3: Life Cycle 2 (years) | AM3: Commission Date | AN3: Withdrawal date | AO3: Total Counter Reading | AP3: Last Reading | AQ3: Last Reading Motor Hour | AR3: FrontTireSize | AS3: RearTireSize | AT3: FleetCode | AU3: PO | AV3: Replace in Year | AW3: TCO Requested Replace in Year | AX3: Replaced by | AY3: TCO Charge | AZ3: ID | BA3: Eng Model | BB3: Transmission model | BC3: NOTES | BD3: Tracker existence | BE3: WIALON Qty | BF3: WIALON "group" | BG3: IVMS Qty | BH3: IVMS "Registration number" | BI3: Vega Qty | BJ3: Vega "deviceId" | BK3: Assigned location | BL3: HDV/HDE classification | BM3: Expected metrics from trackers | BN3: Category | BO3: Equipment Usage Status | BP3: Justification if "Assigned" | BQ3: Weight-based, kg | BR3: Volume-based, m³ | BS3: System Voltage, V | BT3: Battery Capacity, Ah | BU3: Current, A | BV3: Alternator Output, kvA | BW3: Pneumatic Pressure, ft³ (CFM) | BX3: Work output, m³/h | BY3: Maintenance BP | BZ3: Contact number | CA3: Contact e-mail | CB3: if required | CC3: km/day | CD3: mh/day | CE3: comments | CF3: General comments | CG3: Assignee | CH3: Who gave confirmation for write off? | CI3: Write off date
A4: 123020 | B4: Active | C4: H724250 | D4: TRUCK DUMP FREIGHTLINER 6X4 M2 112 | E4: TMF1 | F4: HDV Heavy Duty Vehicle | G4: Tengiz | H4: 1FVHC5CV4ADAT6676 | I4: 1FVHC5CV4ADAT6676 | J4: 20550 | K4: ACTIVE | L4: 150 | M4: WM Tengiz - Base | N4: OE/HSE | O4: 205 | P4: OE/HSE | Q4: 607 | R4: Tengiz OE/HSE | S4: Tengiz OE/HSE | T4: WM Tengiz - Base | U4: 675 | V4: Tengiz fleet | Z4: Non-Critical | AA4: FREIGHTLINER | AB4: M2 112 | AC4: USD | AD4: 94815.95 | AE4: 2010 | AF4: 13 | AH4: 460914U0924012 | AJ4: ED00010993 | AK4: 40270 | AL4: 15 | AM4: 40278 | AO4: 73176 | AP4: 73176 | AR4: 12R22,5 | AS4: 11R X 22.5 | AT4: TRKFLNR 007 | AU4: 135768 | AV4: 2022 | AW4: 2025 | AY4: YES | AZ4: 677 | BA4: 6 | BB4: RTOF-16908LL | BD4: YES | BE4: 1 | BF4: FREIGHTLINER H724250 (ТШО 123020) | BG4: 1 | BH4: H 724250 | BI4: 0 | BK4: Tengiz Eco Centre | BL4: Self-propelled motorized (HDV/HDE) - Wheeled | BM4: Mileage, engine hours, GPS | BN4: Dump truck | BO4: Shared with conditions | BQ4: 35000 | BR4: N/A | BS4: N/A | BT4: 380 - 450 Ah | BU4: 600–900 А | BV4: 160–200 А (12/24 В) | BW4: ~8–10 bar | BX4: ~20–25 m³/h | BY4: TCO SCM Logistics | BZ4: 2234 | CA4: envsvs@tengizchevroil.com | CB4: YES | CC4: 60 | CF4: Approved for write off | CG4: Tengiz Base: Azamat Kurmanov / Rustem Konyrbayev | CH4: Assylbek Amangaliyev | CI4: sent to Finance Kaiyrbek on 15.12.2025
A5: 128035 | B5: Active | C5: H167006 | D5: TRUCK HD BOX INSULATED FORD 2526 HR | E5: TMF1 | F5: HDV Heavy Duty Vehicle | G5: Tengiz | H5: NM0LKXTP6LEG95222 | I5: NM0LKXTP6LEG95222 | J5: 13583 | K5: ACTIVE | L5: 200 | M5: FMA & Butchery Services | N5: Operations | O5: 209 | P5: Supply Chain Management | Q5: 301 | R5: SCM Operations | S5: SCM Tengiz Services | T5: FMA WHSE IB | U5: 695 | V5: Tengiz fleet | Z5: Non-Critical | AA5: FORD | AB5: FORD CARGO 2526 | AC5: KZT | AD5: 32182850 | AE5: 2014 | AF5: 7 | AH5: EG 95222 | AI5: 42515 | AJ5: ED00015394 | AK5: 42443 | AL5: 15 | AM5: 42464 | AO5: 154807 | AP5: 154807 | AR5: 315 /60R22,5 | AS5: 315 /60R22,5 | AT5: TRKFDBX 001 | AU5: 242985 | AV5: 2028 | AW5: 2031 | AY5: YES | AZ5: 697 | BA5: 6 | BD5: YES | BE5: 1 | BF5: FORD H167006 (ТШО 128035) | BG5: 1 | BH5: H 167006 | BI5: 0 | BK5: IB TCO | BL5: Self-propelled motorized (HDV/HDE) - Wheeled | BM5: Mileage, engine hours, GPS | BN5: Food truck | BO5: Assigned | BP5: Food delivery | BQ5: 9980 | BR5: 34980 | BS5: N/A | BT5: N/A | BU5: N/A | BV5: N/A | BW5: N/A | BX5: N/A | BY5: TCO SCM Logistics | BZ5: 200-4593 | CA5: ersswpm@tengizchevroil.com> | CB5: YES | CC5: 17.59 | CD5: 2.2 | CE5: In preservation | CF5: Approved for write-off | CG5: SCM Operations & Services Management: Sagyndyk Adilbekov / Nurbol Akhtanov | CH5: Assylbek Amangaliyev | CI5: sent to Finance Kaiyrbek on 15.12.2025
A6: 521022 | B6: Sent to BP | D6: MANLIFT ELECTRIC AWP GENIE AWP-30S | E6: N-COCR | F6: HDE Heavy Duty Equipment | G6: Tengiz | J6: 20702 | K6: ACTIVE | L6: 200 | M6: SGI Operations | N6: Operations | O6: 207 | P6: Production Operations | Q6: 795 | R6: SGI/SGP | S6: SGI/SGP | T6: SGI Operations | U6: 1562 | V6: Tengiz Fleet | Z6: Non-Critical | AA6: GENIE | AB6: AWP-30S | AC6: GBP | AD6: 6745 | AE6: 2006 | AF6: 15 | AI6: 39726 | AK6: 39877 | AL6: 20 | AM6: 39908 | AO6: 0 | AP6: 0 | AT6: ML 009 | AU6: 104606 | AV6: 2008 | AW6: 2028 | AZ6: 1768 | BD6: NO | BE6: 0 | BG6: 0 | BI6: 0 | BK6: Plant SGI/Завод ЗСГ | BL6: Self-propelled motorized (HDV/HDE) - Wheeled | BM6: Mileage, engine hours, GPS | BN6: Lifting equipment electric | BO6: Assigned | BP6: Stationary use at SGI only | BQ6: N/A | BR6: N/A | BS6: N/A | BT6: N/A | BU6: N/A | BV6: N/A | BW6: N/A | BX6: N/A | BZ6: 200-4410 | CA6: msslte@tengizchevroil.com | CF6: Not found | CG6: Maintenance: Assylbek Amangaliyev / Yerkin Dauletov | CH6: Assylbek Amangaliyev | CI6: sent to Finance Kaiyrbek on 15.12.2025
A7: 702013 | B7: Sent to BP | D7: LIGHTING SET MOBILE HAVERHILL 40KVA | E7: N-COCR | F7: HDE Heavy Duty Equipment | G7: Tengiz | J7: 29450 | K7: ACTIVE | L7: 200 | M7: Export Ops | N7: Operations | O7: 207 | P7: Production Operations | Q7: 708 | R7: FIELD & EXPORT | S7: FIELD & EXPORT | T7: Product Shipping & Storage | U7: 1613 | V7: Tengiz Fleet | Z7: Non-Critical | AA7: HAVERHILL | AB7: 40KVA | AC7: USD | AD7: 7000 | AE7: 1998 | AF7: 19 | AI7: 1 | AK7: 1 | AL7: 20 | AM7: 38755 | AO7: 0 | AP7: 0 | AT7: LTS 001 | AV7: 2009 | AW7: 2024 | AY7: YES | AZ7: 1819 | BD7: NO | BE7: 0 | BG7: 0 | BI7: 0 | BL7: Not self-propelled motorized HDE | BM7: Engine hours, GPS | BN7: Lighting set, signal motorized | BO7: Assigned | BP7: Stationary use at FIELD & EXPORT only | BQ7: N/A | BR7: N/A | BS7: 12 | BT7: 90 Ah | BU7: 56 A | BV7: 40 kvA | BW7: N/A | BX7: N/A | BZ7: 200-4401 | CA7: mssls@tengizchevroil.com | CF7: Not found | CG7: Maintenance: Assylbek Amangaliyev / Yerkin Dauletov | CH7: Assylbek Amangaliyev | CI7: sent to Finance Kaiyrbek on 15.12.2025
A8: 702040 | B8: Active | D8: GENERATOR DIESEL STATIONARY PU-951 | E8: N-COCR | F8: HDE Heavy Duty Equipment | G8: Tengiz | H8: 154978-1 | I8: 154978-1 | J8: 29200 | K8: ACTIVE | L8: 200 | M8: KTL Plant | N8: Operations | O8: 207 | P8: Production Operations | Q8: 745 | R8: KTL | S8: KTL | T8: KTL Plant | U8: 909 | V8: Tengiz fleet | Z8: Non-Critical | AB8: PU-951 | AC8: USD | AD8: 22000 | AF8: 18 | AL8: 20 | AM8: 38471 | AO8: 1 | AP8: 1 | AT8: LG 001 | AV8: 2015 | AW8: 2025 | AZ8: 911 | BD8: NO | BE8: 0 | BG8: 0 | BI8: 0 | BK8: For Write-off | BL8: Stationary HDE | BM8: Engine hours, GPS | BN8: Generator stationary | BO8: Assigned | BP8: Stationary use at KTL Plant only | BQ8: N/A | BR8: N/A | BS8: 24 | BT8: 120 Ah | BU8: 476 A | BV8: 330 kvA | BW8: N/A | BX8: N/A | BY8: TCO MSS BP | BZ8: 200-4410 | CA8: msslte@tengizchevroil.com | CF8: Approved for write-off | CG8: Maintenance: Assylbek Amangaliyev / Yerkin Dauletov | CH8: Assylbek Amangaliyev | CI8: sent to Finance Kaiyrbek on 15.12.2025
